Workbook
Name a: 'Project 2 Staffing Needs'!#REF!
Name a: Staffing!#REF!
Name a: 'Staffing - Baseline'!#REF!
Name a: #REF!
Name aa: 'Project 2 Staffing Needs'!#REF!
Name aa: Staffing!#REF!
Name aa: 'Staffing - Baseline'!#REF!
Name aa: #REF!
Name BPA: 'Project 2 Staffing Needs'!#REF!
Name BPA: Staffing!#REF!
Name BPA: 'Staffing - Baseline'!#REF!
Name BPA: #REF!
Name COMPLEXITY: #REF!
Name DeloitteTeamMembers: 'Project 2 Staffing Needs'!#REF!
Name DeloitteTeamMembers: Staffing!#REF!
Name DeloitteTeamMembers: 'Staffing - Baseline'!#REF!
Name DeloitteTeamMembers: #REF!
Name level: #REF!
Name Manufacturingsites: #REF!
Name MM_Level: 'Project 2 Staffing Needs'!#REF!
Name MM_Level: Staffing!#REF!
Name MM_Level: 'Staffing - Baseline'!#REF!
Name MM_Level: #REF!
Name MM_MD_Level: 'Project 2 Staffing Needs'!#REF!
Name MM_MD_Level: Staffing!#REF!
Name MM_MD_Level: 'Staffing - Baseline'!#REF!
Name MM_MD_Level: #REF!
Name MMNew: 'Project 2 Staffing Needs'!#REF!
Name MMNew: Staffing!#REF!
Name MMNew: 'Staffing - Baseline'!#REF!
Name MMNew: #REF!
Name Projects: 'Project 2 Staffing Needs'!#REF!
Name Projects: Staffing!#REF!
Name Projects: 'Staffing - Baseline'!#REF!
Name Projects: #REF!
Name Rates_b_: #REF!
Name Rates_c_: #REF!
Name Region: #REF!
Name Regions: #REF!
Name reqCat: #REF!
Name reqSubCat: #REF!
Name ReqType: #REF!
Name ResourceCohort_Filtered: _xlfn.ANCHORARRAY(#REF!)
Name STATUS: #REF!
Name Team: 'Project 2 Staffing Needs'!#REF!
Name Team: Staffing!#REF!
Name Team: 'Staffing - Baseline'!#REF!
Name Team: #REF!
Name VP: #REF!

Sheet Timeline - Monthly
E1: 46023 | AN1: 46388 | CN1: 46753
E2: 46148 | I2: 46174 | N2: 46209 | R2: 46237 | W2: 46272 | AA2: 46300 | AE2: 46328 | AJ2: 46363 | AN2: 46391 | AR2: 46419 | AV2: 46447 | BA2: 46482 | BE2: 46510 | BJ2: 46543 | BN2: 46573 | BR2: 46602 | BW2: 46635 | CA2: 46665 | CE2: 46694 | CJ2: 46726 | CN2: 46755 | CS2: 46788 | CW2: 46817 | DA2: 46848 | DE2: 46876 | DJ2: 46909 | DN2: 46937 | DS2: 46970 | DW2: 47001 | EA2: 47029 | EF2: 47062 | EJ2: 47092 | EN2: 47121
E3: =F3-7 -> 46146 | F3: =G3-7 -> 46153 | G3: =H3-7 -> 46160 | H3: =I3-7 -> 46167 | I3: 46174 | J3: =I3+7 -> 46181 | K3: =J3+7 -> 46188 | L3: =K3+7 -> 46195 | M3: =L3+7 -> 46202 | N3: =M3+7 -> 46209 | O3: =N3+7 -> 46216 | P3: =O3+7 -> 46223 | Q3: =P3+7 -> 46230 | ... EW3: =EV3+7 -> 47182
B4: Ending | G4: =G3+4 -> 46164 | H4: =H3+4 -> 46171 | I4: =I3+4 -> 46178 | J4: =J3+4 -> 46185 | K4: =K3+4 -> 46192 | L4: =L3+4 -> 46199 | M4: =M3+4 -> 46206 | N4: =N3+4 -> 46213 | ... CM4: =CM3+4 -> 46752
B5: Week# | G5: 1 | H5: 2 | I5: 3 | J5: 4 | K5: 5 | L5: 6 | M5: 7 | P5: 1 | Q5: =P5+1 -> 2 | R5: =Q5+1 -> 3 | S5: =R5+1 -> 4 | T5: =S5+1 -> 5 | U5: =T5+1 -> 6 | V5: =U5+1 -> 7 | W5: =V5+1 -> 8 | X5: =W5+1 -> 9 | ... CD5: =CC5+1 -> 67
B7: Edison | G7: Edison
N8: ROM for S/4 Enterprise implementation
B10: Global Design | I10: Global Design | Y10: Cross OpCo - Phase 0 | AG10: High Level Scoping, KDDs, Harmonization Opportunities
B13: ABT Implementation | L13: AlphaBio Implementaiton | U13: Prep | W13: 1 | AA13: 2 | AE13: 3 | AI13: 4 | AV13: MC1 | BB13: MC2 | BH13: CS | BP13: FC | BS13: HYC
AJ14: 1 | AP14: 2 | AS14: 3 | AX14: SIT 1 | BD14: SIT 2 | BK14: UAT/OQ/PQ
B21: Assessment Phase
B24: S4 Implementation
R34: Assessment
X37: Prep | Z37: 1 | AF37: 2 | AN37: 3 | AT37: 4 | AZ37: 5 | BX37: MC1 | CG37: MC2 | CR37: CS | DB37: FPC | DF37: HYC
AC38: 1 | AZ38: 1 | BF38: 2 | BL38: 3 | BR38: 4 | CB38: SIT 1 | CK38: SIT 2 | CN38: SIT 2 | CV38: UAT/OQ/PQ

Sheet Timeline
B1: Year | C1: 46023 | AU1: 46388 | CW1: 46753
B2: Month | C2: 46082 | H2: 46118 | L2: 46148 | P2: 46174 | U2: 46209 | Y2: 46237 | AD2: 46272 | AH2: 46300 | AL2: 46328 | AQ2: 46363 | AU2: 46391 | AY2: 46419 | BC2: 46447 | BH2: 46482 | BL2: 46510 | BQ2: 46543 | BU2: 46573 | BZ2: 46602 | CF2: 46635 | CJ2: 46665 | CN2: 46694 | CS2: 46726 | CW2: 46755 | DB2: 46788 | DF2: 46817 | DJ2: 46848 | DN2: 46876 | DS2: 46909 | DW2: 46937 | EB2: 46970 | EF2: 47001 | EJ2: 47029 | EO2: 47062 | ES2: 47092 | EW2: 47121
B3: Week Start | C3: =D3-7 -> 46083 | D3: =E3-7 -> 46090 | E3: =F3-7 -> 46097 | F3: =G3-7 -> 46104 | G3: =H3-7 -> 46111 | H3: =I3-7 -> 46118 | I3: =J3-7 -> 46125 | J3: =K3-7 -> 46132 | ... O3: =P3-7 -> 46167 | P3: 46174 | Q3: =P3+7 -> 46181 | R3: =Q3+7 -> 46188 | S3: =R3+7 -> 46195 | T3: =S3+7 -> 46202 | U3: =T3+7 -> 46209 | V3: =U3+7 -> 46216 | W3: =V3+7 -> 46223 | X3: =W3+7 -> 46230 | ... BU3: =BT3+7 -> 46573 | BW3: =BU3+7 -> 46580 | BX3: =BW3+7 -> 46587 | BY3: =BX3+7 -> 46594 | BZ3: =BY3+7 -> 46601 | CA3: =BZ3+7 -> 46608 | CB3: =CA3+7 -> 46615 | CC3: =CB3+7 -> 46622 | CE3: =CC3+7 -> 46629 | CF3: =CE3+7 -> 46636 | CG3: =CF3+7 -> 46643 | CH3: =CG3+7 -> 46650 | CI3: =CH3+7 -> 46657 | CJ3: =CI3+7 -> 46664 | CK3: =CJ3+7 -> 46671 | CL3: =CK3+7 -> 46678 | CM3: =CL3+7 -> 46685 | ... FF3: =FE3+7 -> 47182
B4: Week End | C4: =C3+4 -> 46087 | D4: =D3+4 -> 46094 | E4: =E3+4 -> 46101 | F4: =F3+4 -> 46108 | G4: =G3+4 -> 46115 | H4: =H3+4 -> 46122 | I4: =I3+4 -> 46129 | J4: =J3+4 -> 46136 | ... BU4: =BU3+4 -> 46577 | BW4: =BW3+4 -> 46584 | BX4: =BX3+4 -> 46591 | BY4: =BY3+4 -> 46598 | BZ4: =BZ3+4 -> 46605 | CA4: =CA3+4 -> 46612 | CB4: =CB3+4 -> 46619 | CC4: =CC3+4 -> 46626 | CE4: =CE3+4 -> 46633 | CF4: =CF3+4 -> 46640 | CG4: =CG3+4 -> 46647 | CH4: =CH3+4 -> 46654 | CI4: =CI3+4 -> 46661 | CJ4: =CJ3+4 -> 46668 | CK4: =CK3+4 -> 46675 | CL4: =CL3+4 -> 46682 | ... FA4: =FA3+4 -> 47151
B5: Week# | N5: 1 | O5: 2 | P5: 3 | Q5: 4 | R5: 5 | S5: 6 | T5: 7 | W5: 1 | X5: =W5+1 -> 2 | Y5: =X5+1 -> 3 | Z5: =Y5+1 -> 4 | AA5: =Z5+1 -> 5 | AB5: =AA5+1 -> 6 | AC5: =AB5+1 -> 7 | AD5: =AC5+1 -> 8 | AE5: =AD5+1 -> 9 | ... BU5: =BT5+1 -> 51 | BW5: =BU5+1 -> 52 | BX5: =BW5+1 -> 53 | BY5: =BX5+1 -> 54 | BZ5: =BY5+1 -> 55 | CA5: =BZ5+1 -> 56 | CB5: =CA5+1 -> 57 | CC5: =CB5+1 -> 58 | CE5: =CC5+1 -> 59 | CF5: =CE5+1 -> 60 | CG5: =CF5+1 -> 61 | CH5: =CG5+1 -> 62 | CI5: =CH5+1 -> 63 | CJ5: =CI5+1 -> 64 | CK5: =CJ5+1 -> 65 | CL5: =CK5+1 -> 66 | CM5: =CL5+1 -> 67
B7: Original
B8: S4 Implementation | L8: Readiness | Y8: 1 | AC8: 2 | AG8: 3 | AK8: 4 | AO8: 5 | AU8: 6 | AY8: 7 | BX8: MC1 | CH8: MC2 | CQ8: MC3 | DB8: CS | DK8: FPC | DO8: HYC
W9: Prep | AB9: 1 | AU9: 1 | AY9: 2 | BC9: 3 | BG9: 4 | BK9: 5 | BO9: 6 | BS9: 7 | CB9: SIT 1 | CL9: SIT 2 | CW9: UAT/Val test | DF9: Dry Run
B10: Go-Live: 21 Months
Y11: Non-Prod Hardware Deployment | BX11: Prod Hardware Deployment
B16: Updated
B17: Assessment Phase | AD17: Assessment
B20: S4 Implementation | AN20: Prep | AP20: 1 | AT20: 2 | AZ20: 3 | BD20: 4 | BH20: 5 | BL20: 6 | BP20: 7 | CP20: MC1 | DA20: MC2 | DJ20: MC3 | DS20: CS | EB20: FPC | EF20: HYC
AS21: 1 | BL21: 1 | BP21: 2 | BT21: 3 | BY21: 4 | CC21: 5 | CH21: 6 | CL21: 7 | CT21: SIT 1 | DE21: SIT 2 | DN21: UAT/Val test | DW21: Dry Run
B22: Go-Live: 21 Months | AP22: Non-Prod Hardware Deployment
AD27: PLAN | AP27: Imagine
BD28: Deliver - Build | CC28: Deliver - Test | DJ28: Run (Deploy / Run)
B29: S4 Implementation | AD29: Scoping and Planning Phase | BD29: Build 1 | BH29: Build 2 | BL29: Build 3 | BP29: Build 4 | BT29: Build 5 | BY29: Build 6 | CG29: SIT 1 | CP29: SIT 2 | DA29: UAT/Val Test | DJ29: Dry Run
AN30: Prep | AP30: Design 1 | AV30: Design 2 | AZ30: Design 3 | BD30: Design 4 | BH30: Design 5 | CA30: MC1 | CK30: MC2 | CX30: MC3 | DG30: CS | DP30: FPC | DS30: HYC
B34: PMO | AP34: Ongoing project execution activities and status reporting | BP34: MC1 Plan | CA34: Mock Cutover 1 | CK34: Mock Cutover 2 | CX34: MC 3 | DG34: Cutover Simulation | DP34: Final Cutover
AN35: Sprint plan | BD35: Test Strategy | BP35: SIT 1 Plan | BY35: SIT 1 Scripts | CG35: SIT 1 Execution | CP35: SIT 2 Execution | DA35: UAT Execution | DJ35: Dry Run Execution | DP35: AMS KT | DS35: Hypercare Support
CM36: SIT 2 Scripts | CX36: UAT/CSV scripts Scripts
AZ38: golden copy
B39: Brownfield/Tech
AL40: Upgrade Prep | AP40: Sandbox Upgrade | AV40: Dev Build | AX40: Dev SPAU | BA40: Dev Code Rem | BL40: SBX Build | BQ40: Pre-Prod Build | BU40: QA Build | CH40: Pre-Prod Build | CR40: QA Build | DC40: Pre-Prod Build | DJ40: Prod Build | DS40: Hypercare Support
B44: Process | AL44: WS Prep | AQ44: Innov. Design WS | AZ44: Fit/Gap | BE44: Configuration, WRICEF Development, Unit Testing | CG44: Execute SIT 1 | CP44: Execute SIT 2 | DA44: Support UAT | DJ44: Support Dry Run | DS44: Support HYP
AX45: SDT Review | BG45: Support SDT & Remediation Activities | BW45: SIT Prep | CB45: Support MC1 | CK45: Support MC2 | CX45: Support MC2 | DG45: Support CS | DP45: Support FC
B49: Data | BC49: SDT Setup | BF49: SDT Blueprint | BJ49: SDT Build | BN49: SDT DDR1 | BR49: Def Fix
AN50: Profiling Tool Setup | AT50: Data Profling build | AX50: Profiling results review & Cleansing plan | BD50: Finalize FI structure
AP51: Data Profilng wkshp | AX51: Fin Data restructuring analysis | BG51: Data Validation Tool Build | BR51: Data Validation Tool execution
CS53: Training translations & LMS uploads
B54: OCM | AD54: OCM Scans | AH54: OCM Project Plans | AP54: Change Impact Analysis | BM54: Training Strategy | BT54: Training curriculum | CE54: Training material development | CX54: Train the Trainer | DF54: End User Training delivery
AF55: Plan for Project Team Training | AM55: Stakeholder Identification & Analysis | BC55: OCM Strategy | CV55: Training delivery planning and logistics
BG56: Comms Strategy & Comms Plan | BP56: Foundational Comms & Adoption Assistant Stand-up | BZ56: Communication and engagement deployment per plan
BZ57: Awareness Campaign | CN57: Understanding Campaign | DB57: Readiness Campaign | DN57: Cutover & Go-Live Campaign
CL58: Change Readiness Survey | DA58: Change Readiness Survey | DM58: Change Readiness Survey
BU59: Change Network Identification & Stand-up | CC59: Change Network Engagement
B61: Analytics | AE61: Data Source Impact | AP61: Fit-to-standard workshops | AW61: Rationalization | BD61: Migrate and re-point data sources | BL61: Extractor Remediation | BT61: New CDS view Developments | CE61: MC1 | CG61: Analytics SIT 1 Support | CN61: MC2 | CP61: Analytics SIT 2 Support | CY61: MC3 | DA61: UAT/Val Test Support | DJ61: Dry Run Support | DS61: Hypercare Support
AE62: Analytics Scope & BDC Decision | AR62: Fit Gap of Data Sources | AY62: FDS for reimagine | BE62: Technical Design | BN62: Data Model Remediation | BT62: New Data Sources | CA62: Test Scripts for SIT | CS62: Test Scripts for UAT
B66: Security | AF66: Cyber Risk Assessment | AQ66: Conduct Security Workshops for Reimagine Processes | BI66: Build and Unit Test Security Design
AF67: Security and Controls Assessment | AZ67: Define Security Strategy and Approach
AQ68: Review of Impacted Risks and Controls | BM68: Review Risk and Control Matrix | CH68: Support Testing and Resolve Security Defects
B71: Validation | AE71: Finalize Validation Approach | AN71: Review of User Requirements | CA71: an you
AV72: Develop Validation Plan | BD72: Conduct Functional Risk Assessment | CX72: IQ/CQ/DQ - QA | DG72: IQ/CQ/DQ - CS | DP72: IQ/CQ/DQ - Prod
BD73: Review of Impacted Functional, Technical & Configuration Design Documents | DA73: OQ/PQ & Regression Test Execution : Validation | DP73: RTM & VSR Sign Offs
BW74: Review & Approval of IQ/CQ/OQ/PQ/ Data Migration Qualification test cases

Sheet Sheet1

Sheet Pivot
B4: Sum of Total Fees | C4: Location
B5: Team | C5: India | D5: Mexico | E5: US | F5: Total Result | I5: Current % | J5: Proposed % | K5: Proposed Fee | L5: Reduction Fees | M5: Comments
B6: Analytics | C6: 911250 | E6: 269280 | F6: 1180530 | I6: =GETPIVOTDATA("Total Fees",$B$4,"Team","Analytics")/GETPIVOTDATA("Total Fees",$B$4) -> #REF! | J6: 0.057 | K6: =J6*$F$22 -> 2451000 | L6: =GETPIVOTDATA("Total Fees",$B$4,"Team","Analytics")-K6 -> #REF!
B7: Data | C7: 515340 | E7: 1126080 | F7: 1641420 | I7: =GETPIVOTDATA("Total Fees",$B$4,"Team","Data")/GETPIVOTDATA("Total Fees",$B$4) -> #REF! | J7: 0.03 | K7: =J7*$F$22 -> 1290000 | L7: =GETPIVOTDATA("Total Fees",$B$4,"Team","Data")-K7 -> #REF!
B8: Deployment | C8: 371340 | E8: 685440 | F8: 1056780 | I8: =GETPIVOTDATA("Total Fees",$B$4,"Team","Deployment")/GETPIVOTDATA("Total Fees",$B$4) -> #REF! | J8: 0.03 | K8: =J8*$F$22 -> 1290000 | L8: =GETPIVOTDATA("Total Fees",$B$4,"Team","Deployment")-K8 -> #REF!
B9: OCM | C9: 936896 | D9: 512358 | E9: 3060974 | F9: 4510228 | I9: =GETPIVOTDATA("Total Fees",$B$4,"Team","OCM")/GETPIVOTDATA("Total Fees",$B$4) -> #REF! | J9: 0.1 | K9: =J9*$F$22 -> 4300000 | L9: =GETPIVOTDATA("Total Fees",$B$4,"Team","OCM")-K9 -> #REF!
B10: OTC | C10: 1164420 | E10: 1546830 | F10: 2711250 | I10: =GETPIVOTDATA("Total Fees",$B$4,"Team","OTC")/GETPIVOTDATA("Total Fees",$B$4) -> #REF! | J10: 0.06 | K10: =J10*$F$22 -> 2580000 | L10: =GETPIVOTDATA("Total Fees",$B$4,"Team","OTC")-K10 -> #REF!
B11: PMO | C11: 737936 | E11: 2584144 | F11: 3322080 | I11: =GETPIVOTDATA("Total Fees",$B$4,"Team","PMO")/GETPIVOTDATA("Total Fees",$B$4) -> #REF! | J11: 0.08 | K11: =J11*$F$22 -> 3440000 | L11: =GETPIVOTDATA("Total Fees",$B$4,"Team","PMO")-K11 -> #REF!
B12: PTD | C12: 4541850 | E12: 2202480 | F12: 6744330 | I12: =GETPIVOTDATA("Total Fees",$B$4,"Team","PTD")/GETPIVOTDATA("Total Fees",$B$4) -> #REF! | J12: 0.12 | K12: =J12*$F$22 -> 5160000 | L12: =GETPIVOTDATA("Total Fees",$B$4,"Team","PTD")-K12 -> #REF! | M12: Plan 2%; Mfg 4%; Logistics 6%
B13: PTP | C13: 1416960 | E13: 1101600 | F13: 2518560 | I13: =GETPIVOTDATA("Total Fees",$B$4,"Team","PTP")/GETPIVOTDATA("Total Fees",$B$4) -> #REF! | J13: 0.05 | K13: =J13*$F$22 -> 2150000 | L13: =GETPIVOTDATA("Total Fees",$B$4,"Team","PTP")-K13 -> #REF!
B14: RTR | C14: 2692215 | E14: 1839060 | F14: 4531275 | I14: =GETPIVOTDATA("Total Fees",$B$4,"Team","RTR")/GETPIVOTDATA("Total Fees",$B$4) -> #REF! | J14: 0.1 | K14: =J14*$F$22 -> 4300000 | L14: =GETPIVOTDATA("Total Fees",$B$4,"Team","RTR")-K14 -> #REF!
B15: S&R | C15: 626400 | E15: 889200 | F15: 1515600 | I15: =GETPIVOTDATA("Total Fees",$B$4,"Team","S&R")/GETPIVOTDATA("Total Fees",$B$4) -> #REF! | J15: 0.03 | K15: =J15*$F$22 -> 1290000 | L15: =GETPIVOTDATA("Total Fees",$B$4,"Team","S&R")-K15 -> #REF!
B16: Security | C16: 871750 | E16: 2257035 | F16: 3128785 | I16: =GETPIVOTDATA("Total Fees",$B$4,"Team","Solution Architecture")/GETPIVOTDATA("Total Fees",$B$4) -> #REF! | J16: 0.06 | K16: =J16*$F$22 -> 2580000 | L16: =GETPIVOTDATA("Total Fees",$B$4,"Team","Security")-K16 -> #REF!
B17: Solution Architecture | C17: 277965 | E17: 979488 | F17: 1257453 | I17: =GETPIVOTDATA("Total Fees",$B$4,"Team","Solution Architecture")/GETPIVOTDATA("Total Fees",$B$4) -> #REF! | J17: 0.02 | K17: =J17*$F$22 -> 860000 | L17: =GETPIVOTDATA("Total Fees",$B$4,"Team","Solution Architecture")-K17 -> #REF!
B18: TAX | C18: 2512200 | E18: 1643700 | F18: 4155900 | I18: =GETPIVOTDATA("Total Fees",$B$4,"Team","TAX")/GETPIVOTDATA("Total Fees",$B$4) -> #REF! | J18: 0.08 | K18: =J18*$F$22 -> 3440000 | L18: =GETPIVOTDATA("Total Fees",$B$4,"Team","TAX")-K18 -> #REF! | M18: Vertex Upgrade; E-Invoice 4 Countries
B19: Technology | C19: 5913530 | E19: 4122162 | F19: 10035692 | I19: =GETPIVOTDATA("Total Fees",$B$4,"Team","Technology ")/GETPIVOTDATA("Total Fees",$B$4) -> #REF! | J19: 0.18 | K19: =J19*$F$22 -> 7740000 | L19: =GETPIVOTDATA("Total Fees",$B$4,"Team","Technology ")-K19 -> #REF!
B20: Validation | C20: 36225 | E20: 91742 | F20: 127967 | I20: =GETPIVOTDATA("Total Fees",$B$4,"Team","Validation")/GETPIVOTDATA("Total Fees",$B$4) -> #REF! | J20: 0.003 | K20: =J20*$F$22 -> 129000 | L20: =GETPIVOTDATA("Total Fees",$B$4,"Team","Validation")-K20 -> #REF!
B21: Total Result | C21: 23526277 | D21: 512358 | E21: 24399215 | F21: 48437850 | I21: =SUM(I6:I20) -> #REF! | J21: =SUM(J6:J20) -> 1 | K21: =SUM(K6:K20) -> 43000000 | L21: =SUM(L6:L20) -> #REF!
E22: Target Fees | F22: 43000000
B25: Sum of Planning Fees | C25: Geography
B26: Team | C26: India | D26: Mexico | E26: US | F26: US - Project | G26: Total Result | P26: PTD % | Q26: Total %
B27: Analytics | C27: 56250 | E27: 122400 | G27: 178650 | N27: PTD Total | O27: 6240000 | Q27: =O27/$O$33 -> 0.14511628
B28: Data | C28: 43740 | E28: 146880 | G28: 190620 | N28: LOG | O28: 2430000 | P28: =O28/$O$27 -> 0.38942308 | Q28: =O28/$O$33 -> 0.056511628
B29: Deployment | C29: 0 | E29: 0 | G29: 0 | N29: MFG | O29: 3420000 | P29: =O29/$O$27 -> 0.54807692 | Q29: =O29/$O$33 -> 0.079534884
B30: OCM | C30: 0 | D30: 24114 | E30: 157264 | G30: 181378 | N30: PLAN | O30: 488340 | P30: =O30/$O$27 -> 0.078259615 | Q30: =O30/$O$33 -> 0.011356744
B31: OTC | C31: 44550 | E31: 134640 | G31: 179190
B32: PMO | C32: 92496 | E32: 322284 | G32: 414780
B33: PTD | C33: 209385 | E33: 287280 | G33: 496665 | N33: Total | O33: 43000000
B34: PTP | C34: 115965 | E34: 134640 | G34: 250605
B35: RTR | C35: 84330 | E35: 109440 | G35: 193770
B36: S&R | C36: 21600 | E36: 117000 | G36: 138600
B37: Security | C37: 72850 | E37: 193460 | G37: 266310
B38: Solution Architecture | C38: 31950 | E38: 131328 | G38: 163278
B39: TAX | C39: 32850 | E39: 139500 | G39: 172350
B40: Technology | C40: 51900 | E40: 305280 | F40: 0 | G40: 357180
B41: Validation | C41: 36225 | E41: 91742 | G41: 127967
B42: Total Result | C42: 894091 | D42: 24114 | E42: 2393138 | F42: 0 | G42: 3311343
B47: Team | C47: Sum of Total Hours
B48: Analytics | C48: 15640
B49: Data | C49: 11510
B50: Deployment | C50: 8405
B51: OCM | C51: 27025
B52: OTC | C52: 22725
B53: PMO | C53: 15923
B54: PTD | C54: 80270
B55: PTP | C55: 26415
B56: RTR | C56: 48465
B57: S&R | C57: 13860
B58: Security | C58: 19475
B59: Solution Architecture | C59: 6779
... B63: Total Result | C63: 415210
B76: (empty) | C76: Location
B77: Row Labels | C77: US | D77: India | E77: Location | F77: Mexico | G77: Total Result
B78: PMO
B79: PMO
B80: RTR
B81: RTR
B82: OTC
B83: Order Management
B84: PTD
B85: Delivery Warehouse
B86: Logistics
B87: Manufacturing - PM
B88: Manufacturing - PP
B89: Manufacturing - QM
B90: Plan
B91: PTP | AB91: 0.5
B92: Accounts Payable
B93: Procurement
B94: OCM
B95: Training
B96: OCM
B97: Deployment
B98: Cutover
B99: Testing
C100: Column Labels
C101: Roles | G101: Fees | K101: Total Roles | L101: Total Fees
B102: Row Labels | C102: US | D102: India | E102: Location | F102: Mexico | G102: US | H102: India | I102: Location | J102: Mexico
B103: PMO | C103: 4 | D103: 3 | G103: 2584144 | H103: 737936 | K103: 7 | L103: 3322080
B104: PMO | C104: 4 | D104: 3 | G104: 2584144 | H104: 737936 | K104: 7 | L104: 3322080
B105: RTR | C105: 2 | D105: 12 | G105: 1839060 | H105: 2692215 | K105: 14 | L105: 4531275
B106: RTR | C106: 2 | D106: 12 | G106: 1839060 | H106: 2692215 | K106: 14 | L106: 4531275
B107: OTC | C107: 2 | D107: 5 | G107: 1546830 | H107: 1164420 | K107: 7 | L107: 2711250
B108: Order Management | C108: 2 | D108: 5 | G108: 1546830 | H108: 1164420 | K108: 7 | L108: 2711250
B109: PTD | C109: 2 | D109: 30 | G109: 2202480 | H109: 4541850 | K109: 32 | L109: 6744330
B110: Delivery Warehouse | C110: 1 | D110: 8 | G110: 1076400 | H110: 1515195 | K110: 9 | L110: 2591595
B111: Logistics | D111: 3 | H111: 354645 | K111: 3 | L111: 354645
B112: Manufacturing - PM | D112: 2 | H112: 314280 | K112: 2 | L112: 314280
B113: Manufacturing - PP | C113: 1 | D113: 13 | G113: 1126080 | H113: 1530270 | K113: 14 | L113: 2656350
B114: Manufacturing - QM | D114: 2 | H114: 378000 | K114: 2 | L114: 378000
B115: Plan | D115: 2 | H115: 449460 | K115: 2 | L115: 449460
B116: PTP | C116: 1 | D116: 7 | G116: 1101600 | H116: 1416960 | K116: 8 | L116: 2518560
B117: Accounts Payable | D117: 4 | H117: 618030 | K117: 4 | L117: 618030
B118: Procurement | C118: 1 | D118: 3 | G118: 1101600 | H118: 798930 | K118: 4 | L118: 1900530
B119: OCM | C119: 8 | D119: 15 | F119: 3 | G119: 3060974 | H119: 936896 | J119: 512358 | K119: 26 | L119: 4510228
B120: Training | C120: 1 | D120: 14 | G120: 396090 | H120: 922424 | K120: 15 | L120: 1318514
B121: OCM | C121: 7 | D121: 1 | F121: 3 | G121: 2664884 | H121: 14472 | J121: 512358 | K121: 11 | L121: 3191714
B122: Deployment | C122: 2 | D122: 4 | G122: 685440 | H122: 371340 | K122: 6 | L122: 1056780
B123: Cutover | D123: 2 | H123: 263340 | K123: 2 | L123: 263340
B124: Testing | D124: 1 | H124: 108000 | K124: 1 | L124: 108000
...

Sheet Staffing
B3: Fees | C3: =SUM(Q10:Q228) -> 96875700 | E3: Technology | F3: =SUMIFS($S$10:$S$146,$X$10:$X$146,E3)/$C$4 -> #VALUE! | BB3: Scoping and Planning Phase | CB3: Build 1 | CF3: Build 2 | CJ3: Build 3 | CN3: Build 4 | CR3: Build 5 | CV3: Build 6 | DC3: SIT 1 | DL3: SIT 2 | DW3: UAT/Val Test | EF3: Dry Run
B4: Hours | C4: =SUM(S10:S228) -> #VALUE! | E4: Consulting | F4: =SUMIFS($S$10:$S$146,$X$10:$X$146,E4)/$C$4 -> #VALUE! | BL4: Prep | BN4: Design 1 | BT4: Design 2 | BX4: Design 3 | CB4: Design 4 | CF4: Design 5 | CZ4: MC1 | DI4: MC2 | DT4: MC3 | EC4: CS | EL4: FPC | EO4: HYC
B5: RPH | C5: =C3/C4 -> #VALUE! | E5: Tax | F5: =SUMIFS($S$10:$S$146,$X$10:$X$146,E5)/$C$4 -> #VALUE!
FQ6: P9 | FR6: P10 | FS6: P11 | FT6: P12 | FU6: P13 | FV6: P1 | FW6: P2 | FX6: P3 | FY6: P4 | FZ6: P5 | GA6: P6 | GB6: P7 | GC6: P8 | GD6: P9 | GE6: P10 | GF6: P11 | GG6: P12 | GH6: P13 | GI6: P1 | GJ6: P2 | GK6: P3 | GL6: P4 | GM6: P5 | GN6: P6 | GO6: P7 | GP6: P8 | GQ6: P9 | GR6: P10 | GS6: P11 | GT6: P12 | GU6: P13 | GV6: P1 | GW6: P2 | GX6: P3 | GY6: P4 | GZ6: P5 | HA6: P6 | HB6: P7 | HC6: P8 | HD6: P9 | HE6: P10
AB7: FY26 | AC7: FY26 | AD7: FY26 | AE7: FY26 | AF7: FY26 | AG7: FY26 | AH7: FY26 | AI7: FY26 | AJ7: FY26 | AK7: FY26 | AL7: FY26 | AM7: FY26 | AN7: FY26 | AO7: FY26 | AP7: FY26 | AQ7: FY26 | AR7: FY26 | AS7: FY27 | AT7: FY27 | AU7: FY27 | AV7: FY27 | AW7: FY27 | AX7: FY27 | AY7: FY27 | AZ7: FY27 | BA7: FY27 | BB7: FY27 | BC7: FY27 | BD7: FY27 | BE7: FY27 | BF7: FY27 | BG7: FY27 | BH7: FY27 | BI7: FY27 | BJ7: FY27 | BK7: FY27 | BL7: FY27 | BM7: FY27 | BN7: FY27 | BO7: FY27 | BP7: FY27 | BQ7: FY27 | BR7: FY27 | BS7: FY27 | BT7: FY27 | BU7: FY27 | BV7: FY27 | BW7: FY27 | BX7: FY27 | BY7: FY27 | BZ7: FY27 | CA7: FY27 | CB7: FY27 | CC7: FY27 | CD7: FY27 | CE7: FY27 | CF7: FY27 | CG7: FY27 | CH7: FY27 | CI7: FY27 | CJ7: FY27 | CK7: FY27 | CL7: FY27 | CM7: FY27 | CN7: FY28 | CO7: FY28 | CP7: FY28 | CQ7: FY28 | CR7: FY28 | CS7: FY28 | CT7: FY28 | CU7: FY28 | CV7: FY28 | CW7: FY28 | CX7: FY28 | CY7: FY28 | CZ7: FY28 | DA7: FY28 | DB7: FY28 | DC7: FY28 | DD7: FY28 | DE7: FY28 | DF7: FY28 | DG7: FY28 | DH7: FY28 | DI7: FY28 | DJ7: FY28 | DK7: FY28 | DL7: FY28 | DM7: FY28 | DN7: FY28 | DO7: FY28 | DP7: FY28 | DQ7: FY28 | DR7: FY28 | DS7: FY28 | DT7: FY28 | DU7: FY28 | DV7: FY28 | DW7: FY28 | DX7: FY28 | DY7: FY28 | DZ7: FY28 | EA7: FY28 | EB7: FY28 | EC7: FY28 | ED7: FY28 | EE7: FY28 | EF7: FY28 | EG7: FY28 | EH7: FY28 | EI7: FY28 | EJ7: FY28 | EK7: FY28 | EL7: FY28 | EM7: FY28 | EN7: FY29-P1 | EO7: FY29 | EP7: FY29 | EQ7: FY29 | ER7: FY29 | ES7: FY29 | ET7: FY29 | EU7: FY29 | EV7: FY29 | EW7: FY29 | EX7: FY29 | EY7: FY29 | EZ7: FY29 | FA7: FY29 | FB7: FY29 | FC7: FY29 | FD7: FY29 | FE7: FY29 | FF7: FY29 | FG7: FY29 | FH7: FY29 | FI7: FY29 | FJ7: FY29 | FK7: FY29 | FL7: FY29 | FM7: FY29 | FN7: FY29 | FO7: FY29 | FP7: Start Date | FQ7: 46033 | FR7: 46061 | FS7: 46089 | FT7: 46117 | FU7: 46145 | FV7: 46173 | FW7: 46201 | FX7: 46229 | FY7: 46257 | FZ7: 46285 | GA7: 46313 | GB7: 46341 | GC7: 46369 | GD7: 46397 | GE7: 46425 | GF7: 46453 | GG7: 46481 | GH7: 46509 | GI7: 46537 | GJ7: 46565 | GK7: 46593 | GL7: 46621 | GM7: 46649 | GN7: 46677 | GO7: 46705 | GP7: 46733
Q8: =SUBTOTAL(9,Q10:Q228) -> 96875700 | S8: =SUBTOTAL(9,S10:S228) -> #VALUE! | X8: Rate Information | AB8: FY26-P09 | AC8: FY26-P10 | AD8: FY26-P10 | AE8: FY26-P10 | AF8: FY26-P10 | AG8: FY26-P11 | AH8: FY26-P11 | AI8: FY26-P11 | AJ8: FY26-P11 | AK8: FY26-P12 | AL8: FY26-P12 | AM8: FY26-P12 | AN8: FY26-P12 | AO8: FY26-P13 | AP8: FY26-P13 | AQ8: FY26-P13 | AR8: FY26-P13 | AS8: FY27-P01 | AT8: FY27-P01 | AU8: FY27-P2 | AV8: FY27-P3 | AW8: FY27-P3 | AX8: FY27-P3 | AY8: FY27-P3 | AZ8: FY27-P4 | BA8: FY27-P4 | BB8: FY27-P4 | BC8: FY27-P4 | BD8: FY27-P5 | BE8: FY27-P5 | BF8: FY27-P5 | BG8: FY27-P5 | BH8: FY27-P6 | BI8: FY27-P6 | BJ8: FY27-P6 | BK8: FY27-P6 | BL8: FY27-P7 | BM8: FY27-P7 | BN8: FY27-P7 | BO8: FY27-P7 | BP8: FY27-P8 | BQ8: FY27-P8 | BR8: FY27-P8 | BS8: FY27-P8 | BT8: FY27-P9 | BU8: FY27-P9 | BV8: FY27-P9 | BW8: FY27-P9 | BX8: FY27-P10 | BY8: FY27-P10 | BZ8: FY27-P10 | CA8: FY27-P10 | CB8: FY27-P11 | CC8: FY27-P11 | CD8: FY27-P11 | CE8: FY27-P11 | CF8: FY27-P12 | CG8: FY27-P12 | CH8: FY27-P12 | CI8: FY27-P12 | CJ8: FY27-P13 | CK8: FY27-P13 | CL8: FY27-P13 | CM8: FY27-P13 | CN8: FY28-P1 | CO8: FY28-P1 | CP8: FY28-P1 | CQ8: FY28-P1 | CR8: FY28-P2 | CS8: FY28-P2 | CT8: FY28-P2 | CU8: FY28-P2 | CV8: FY28-P3 | CW8: FY28-P3 | CX8: FY28-P3 | CY8: FY28-P3 | CZ8: FY28-P4 | DA8: FY28-P4 | DB8: FY28-P4 | DC8: FY28-P4 | DD8: FY28-P5 | DE8: FY28-P5 | DF8: FY28-P5 | DG8: FY28-P5 | DH8: FY28-P6 | DI8: FY28-P6 | DJ8: FY28-P6 | DK8: FY28-P6 | DL8: FY28-P7 | DM8: FY28-P7 | DN8: FY28-P7 | DO8: FY28-P7 | DP8: FY28-P8 | DQ8: FY28-P8 | DR8: FY28-P8 | DS8: FY28-P8 | DT8: FY28-P9 | DU8: FY28-P9 | DV8: FY28-P9 | DW8: FY28-P9 | DX8: FY28-P10 | DY8: FY28-P10 | DZ8: FY28-P10 | EA8: FY28-P10 | EB8: FY28-P11 | EC8: FY28-P11 | ED8: FY28-P11 | EE8: FY28-P11 | EF8: FY28-P12 | EG8: FY28-P12 | EH8: FY28-P12 | EI8: FY28-P12 | EJ8: FY28-P13 | EK8: FY28-P13 | EL8: FY28-P13 | EM8: FY28-P13 | EN8: FY29-P1 | EO8: FY29-P1 | EP8: FY29-P1 | EQ8: FY29-P1 | ER8: FY29-P2 | ES8: FY29-P2 | ET8: FY29-P2 | EU8: FY29-P2 | EV8: FY29-P3 | EW8: FY29-P3 | EX8: FY29-P3 | EY8: FY29-P3 | EZ8: FY29-P4 | FA8: FY29-P4 | FB8: FY29-P4 | FC8: FY29-P4 | FD8: FY29-P5 | FE8: FY29-P5 | FF8: FY29-P5 | FG8: FY29-P5 | FH8: FY29-P6 | FI8: FY29-P6 | FJ8: FY29-P6 | FK8: FY29-P6 | FL8: FY29-P7 | FM8: FY29-P7 | FN8: FY29-P7 | FO8: FY29-P7 | FP8: End Date | FQ8: 46060 | FR8: 46088 | FS8: 46116 | FT8: 46144 | FU8: 46172 | FV8: 46200 | FW8: 46228 | FX8: 46256 | FY8: 46284 | FZ8: 46312 | GA8: 46340 | GB8: 46368 | GC8: 46396 | GD8: 46424 | GE8: 46452 | GF8: 46480 | GG8: 46508 | GH8: 46536 | GI8: 46564 | GJ8: 46592 | GK8: 46620 | GL8: 46648 | GM8: 46676 | GN8: 46704 | GO8: 46732 | GP8: 46760 | HF8: =SUM(HF10:HF175) -> #VALUE! | HG8: =SUM(HG10:HG175) -> #VALUE!
B9: Process or Enabling | C9: Team | D9: Sub-Team | E9: Role Name | F9: Location | G9: Business | H9: Offering Portfolio | I9: Offering | J9: Geography | K9: Job Family | L9: Sub Family | M9: Deloitte Level | N9: Phase / Work Team | O9: Rate Helper (do not delete) | P9: Client Role | Q9: Total Fees | R9: Planning Fees | S9: CV Total Hrs Not Actual Total Hours | T9: Total Hours | U9: Staffing Role | V9: Years of Experience | W9: Staffing Location | X9: Rate Type | Y9: Role | Z9: Rate Card Level | AA9: PM Avg Rates | AB9: Rate Card Yr2 Rates | AC9: 46090 | AD9: 46097 | AE9: 46104 | AF9: 46111 | AG9: 46118 | AH9: 46125 | AI9: 46132 | AJ9: 46139 | AK9: 46146 | AL9: 46153 | AM9: 46160 | AN9: 46167 | AO9: 46174 | AP9: 46181 | AQ9: 46188 | AR9: 46195 | AS9: 46202 | AT9: 46209 | AU9: 46216 | AV9: 46223 | AW9: 46230 | AX9: 46237 | AY9: 46244 | AZ9: 46251 | BA9: 46258 | BB9: 46265 | BC9: 46272 | BD9: 46279 | BE9: 46286 | BF9: 46293 | BG9: 46300 | BH9: 46307 | BI9: 46314 | BJ9: 46321 | BK9: 46328 | BL9: 46335 | BM9: 46342 | BN9: 46349 | BO9: 46356 | BP9: 46363 | BQ9: 46370 | BR9: 46377 | BS9: 46384 | BT9: 46391 | BU9: 46398 | BV9: 46405 | BW9: 46412 | BX9: 46419 | BY9: 46426 | BZ9: 46433 | CA9: 46440 | CB9: 46447 | CC9: 46454 | CD9: 46461 | CE9: 46468 | CF9: 46475 | CG9: 46482 | CH9: 46489 | CI9: 46496 | CJ9: 46503 | CK9: 46510 | CL9: 46517 | CM9: 46524 | CN9: 46531 | CO9: 46538 | CP9: 46545 | CQ9: 46552 | CR9: 46559 | CS9: 46566 | CT9: 46573 | CU9: 46580 | CV9: 46587 | CW9: 46594 | CX9: 46601 | CY9: 46608 | CZ9: 46615 | DA9: 46622 | DB9: 46629 | DC9: 46636 | DD9: 46643 | DE9: 46650 | DF9: 46657 | DG9: 46664 | DH9: 46671 | DI9: 46678 | DJ9: 46685 | DK9: 46692 | DL9: 46699 | DM9: 46706 | DN9: 46713 | DO9: 46720 | DP9: 46727 | DQ9: 46734 | DR9: 46741 | DS9: 46748 | DT9: 46755 | DU9: 46762 | DV9: 46769 | DW9: 46776 | DX9: 46783 | DY9: 46790 | DZ9: 46797 | EA9: 46804 | EB9: 46811 | EC9: 46818 | ED9: 46825 | EE9: 46832 | EF9: 46839 | EG9: 46846 | EH9: 46853 | EI9: 46860 | EJ9: 46867 | EK9: 46874 | EL9: 46881 | EM9: 46888 | EN9: 46895 | EO9: 46902 | EP9: 46909 | EQ9: 46916 | ER9: 46923 | ES9: 46930 | ET9: 46937 | EU9: 46944 | EV9: 46951 | EW9: 46958 | EX9: 46965 | EY9: 46972 | EZ9: 46979 | FA9: 46986 | FB9: 46993 | FC9: 47000 | FD9: 47007 | FE9: 47014 | FF9: 47021 | FG9: 47028 | FH9: 47035 | FI9: 47042 | FJ9: 47049 | FK9: 47056 | FL9: 47063 | FM9: 47070 | FN9: 47077 | FO9: 47084 | FP9: 47091 | FQ9: FY27-P4 | FR9: FY27-P5 | FS9: FY27-P6 | FT9: FY27-P7 | FU9: FY27-P8 | FV9: FY27-P9 | FW9: FY27-P10 | FX9: FY27-P11 | FY9: FY27-P12 | FZ9: FY27-P13 | GA9: FY28-P1 | GB9: FY28-P2 | GC9: FY28-P3 | GD9: FY28-P4 | GE9: FY28-P5 | GF9: FY28-P6 | GG9: FY28-P7 | GH9: FY28-P8 | GI9: FY28-P9 | GJ9: FY28-P10 | GK9: FY28-P11 | GL9: FY28-P12 | GM9: FY28-P13 | GN9: FY29-P1 | GO9: FY29-P2 | GP9: FY28-P8 | GQ9: FY28-P9 | GR9: FY28-P10 | GS9: FY28-P11 | GT9: FY28-P12 | GU9: FY28-P13 | GV9: FY29-P1 | GW9: FY29-P2 | GX9: FY29-P3 | GY9: FY29-P4 | GZ9: FY29-P5 | HA9: FY29-P6 | HB9: FY29-P7 | HC9: FY29-P8 | HD9: FY29-P9 | HE9: FY29-P10 | HF9: Total | HG9: Check
B10: Enabling | C10: PMO | D10: PMO | E10: Project Sponsor | F10: US | G10: Consulting Services | H10: Enterprise Performance | I10: SAP | J10: US | K10: Package and Technology Enablement | L10: Package Program and Solution Management | M10: LMD - Managing Director | N10: =_xlfn.CONCAT(C10,"-",D10) -> PMO-PMO | O10: =_xlfn.CONCAT(Y10,"-",Z10,"-",F10,"-",X10) -> Technology-Principal-US-Consulting | P10: =_xlfn.CONCAT(C10," - ",Y10) -> PMO - Technology | Q10: =AB10*SUM(AZ10:ET10) -> 62046 | R10: =AB10*SUM(BC10:BN10) -> 4596 | S10: =SUM(GP10:HN10) -> #VALUE! | T10: =SUM(AZ10:EZ10) -> 162 | U10: =_xlfn.CONCAT(Y10," - ",Z10) -> Technology - Principal | V10: =VLOOKUP(O10,$B$187:$H$848,4,0) -> 15+ years | W10: =IF(F10="US", "Onshore",IF(F10="India","Offshore", "Nearshore")) -> Onshore | X10: Consulting | Y10: Technology | Z10: Principal | AA10: =[1]Resourcing!QD14 -> 0 | AB10: =IFERROR(VLOOKUP(O10,$B$187:$S$848,6,FALSE()),"combination not found") -> 383 | BC10: 1 | BD10: 1 | BE10: 1 | BF10: 1 | BG10: 1 | BH10: 1 | BI10: 1 | BJ10: 1 | BK10: 1 | BL10: 1 | BM10: 1 | BN10: 1 | BO10: 2 | BP10: 2 | BQ10: 2 | BT10: 2 | BU10: 2 | BV10: 2 | BW10: 2 | BX10: 2 | BY10: 2 | BZ10: 2 | CA10: 2 | CB10: 2 | CC10: 2 | CD10: 2 | CE10: 2 | CF10: 2 | CG10: 2 | CH10: 2 | CI10: 2 | CJ10: 2 | CK10: 2 | CL10: 2 | CM10: 2 | CN10: 2 | CO10: 2 | CP10: 2 | CQ10: 2 | CR10: 2 | CS10: 2 | CT10: 2 | CU10: 2 | CV10: 2 | CW10: 2 | CX10: 2 | CY10: 2 | CZ10: 2 | DA10: 2 | DB10: 2 | DC10: 2 | DD10: 2 | DE10: 2 | DF10: 2 | DG10: 2 | DH10: 2 | DI10: 2 | DJ10: 2 | DK10: 2 | DL10: 2 | DM10: 2 | DN10: 2 | DO10: 2 | DP10: 2 | DQ10: 2 | DT10: 2 | DU10: 2 | DV10: 2 | DW10: 2 | DX10: 2 | DY10: 2 | DZ10: 2 | EA10: 2 | EB10: 2 | EC10: 2 | ED10: 2 | EE10: 2 | EF10: 2 | EG10: 2 | EH10: 2 | EI10: 2 | EJ10: 2 | EK10: 2 | EL10: 2 | EM10: 2 | EN10: 2 | EO10: 2 | FQ10: =SUMIF($AC$11:$FP$11,FQ$12,$AC10:$FP10) -> #VALUE! | FR10: =SUMIF($AC$11:$FP$11,FR$12,$AC10:$FP10) -> #VALUE! | FS10: =SUMIF($AC$11:$FP$11,FS$12,$AC10:$FP10) -> #VALUE! | FT10: =SUMIF($AC$11:$FP$11,FT$12,$AC10:$FP10) -> #VALUE! | FU10: =SUMIF($AC$11:$FP$11,FU$12,$AC10:$FP10) -> #VALUE! | FV10: =SUMIF($AC$11:$FP$11,FV$12,$AC10:$FP10) -> #VALUE! | FW10: =SUMIF($AC$11:$FP$11,FW$12,$AC10:$FP10) -> #VALUE! | FX10: =SUMIF($AC$11:$FP$11,FX$12,$AC10:$FP10) -> #VALUE! | ... GO10: =SUMIF($AC$11:$FP$11,GO$12,$AC10:$FP10) -> #VALUE! | GP10: =SUMIF($AB$8:$FO$8,GP$9,$AB10:$FO10) -> 4 | GQ10: =SUMIF($AB$8:$FO$8,GQ$9,$AB10:$FO10) -> 8 | GR10: =SUMIF($AB$8:$FO$8,GR$9,$AB10:$FO10) -> 8 | GS10: =SUMIF($AB$8:$FO$8,GS$9,$AB10:$FO10) -> 8 | GT10: =SUMIF($AB$8:$FO$8,GT$9,$AB10:$FO10) -> 8 | GU10: =SUMIF($AB$8:$FO$8,GU$9,$AB10:$FO10) -> 8 | GV10: =SUMIF($AB$8:$FO$8,GV$9,$AB10:$FO10) -> 4 | GW10: =SUMIF($AB$8:$FO$8,GW$9,$AB10:$FO10) -> 0 | ... HE10: =SUMIF($AB$8:$FO$8,HE$9,$AB10:$FO10) -> 0 | HF10: =SUM(FQ10:HE10) -> #VALUE! | HG10: =HF10-S10 -> #VALUE!
B11: Enabling | C11: PMO | D11: PMO | E11: Engagement Lead | F11: US | G11: Consulting Services | H11: Enterprise Performance | I11: SAP | J11: US | K11: Package and Technology Enablement | L11: Package Program and Solution Management | M11: LMD - Managing Director | N11: =_xlfn.CONCAT(C11,"-",D11) -> PMO-PMO | O11: =_xlfn.CONCAT(Y11,"-",Z11,"-",F11,"-",X11) -> Technology-Managing Director-US-Consulting | P11: =_xlfn.CONCAT(C11," - ",Y11) -> PMO - Technology | Q11: =AB11*SUM(AZ11:ET11) -> 524710 | R11: =AB11*SUM(BC11:BN11) -> 45960 | S11: =SUM(GP11:HN11) -> #VALUE! | T11: =SUM(AZ11:EZ11) -> 1370 | U11: =_xlfn.CONCAT(Y11," - ",Z11) -> Technology - Managing Director | V11: =VLOOKUP(O11,$B$187:$H$848,4,0) -> 10-15 years | W11: =IF(F11="US", "Onshore",IF(F11="India","Offshore", "Nearshore")) -> Onshore | X11: Consulting | Y11: Technology | Z11: Managing Director | AA11: =[1]Resourcing!QD15 -> 0 | AB11: =IFERROR(VLOOKUP(O11,$B$187:$S$848,6,FALSE()),"combination not found") -> 383 | BC11: 10 | BD11: 10 | BE11: 10 | BF11: 10 | BG11: 10 | BH11: 10 | BI11: 10 | BJ11: 10 | BK11: 10 | BL11: 10 | BM11: 10 | BN11: 10 | BO11: 16 | BP11: 16 | BQ11: 16 | BT11: 16 | BU11: 16 | BV11: 16 | BW11: 16 | BX11: 16 | BY11: 16 | BZ11: 16 | CA11: 16 | CB11: 16 | CC11: 16 | CD11: 16 | CE11: 16 | CF11: 16 | CG11: 16 | CH11: 16 | CI11: 16 | CJ11: 16 | CK11: 16 | CL11: 16 | CM11: 16 | CN11: 16 | CO11: 16 | CP11: 16 | CQ11: 16 | CR11: 16 | CS11: 16 | CT11: 16 | CU11: 16 | CV11: 16 | CW11: 16 | CX11: 16 | CY11: 16 | CZ11: 16 | DA11: 16 | DB11: 16 | DC11: 16 | DD11: 16 | DE11: 16 | DF11: 16 | DG11: 16 | DH11: 16 | DI11: 16 | DJ11: 16 | DK11: 16 | DL11: 16 | DM11: 16 | DN11: 16 | DO11: 16 | DP11: 16 | DQ11: 16 | DT11: 16 | DU11: 16 | DV11: 16 | DW11: 16 | DX11: 16 | DY11: 16 | DZ11: 16 | EA11: 16 | EB11: 16 | EC11: 16 | ED11: 16 | EE11: 16 | EF11: 16 | EG11: 16 | EH11: 16 | EI11: 16 | EJ11: 16 | EK11: 16 | EL11: 16 | EM11: 16 | EN11: 16 | EO11: 16 | EP11: 10 | EQ11: 10 | ER11: 10 | ES11: 10 | ET11: 10 | FQ11: =SUMIF($AC$11:$FP$11,FQ$12,$AC11:$FP11) -> #VALUE! | FR11: =SUMIF($AC$11:$FP$11,FR$12,$AC11:$FP11) -> #VALUE! | FS11: =SUMIF($AC$11:$FP$11,FS$12,$AC11:$FP11) -> #VALUE! | FT11: =SUMIF($AC$11:$FP$11,FT$12,$AC11:$FP11) -> #VALUE! | FU11: =SUMIF($AC$11:$FP$11,FU$12,$AC11:$FP11) -> #VALUE! | FV11: =SUMIF($AC$11:$FP$11,FV$12,$AC11:$FP11) -> #VALUE! | FW11: =SUMIF($AC$11:$FP$11,FW$12,$AC11:$FP11) -> #VALUE! | FX11: =SUMIF($AC$11:$FP$11,FX$12,$AC11:$FP11) -> #VALUE! | ... GO11: =SUMIF($AC$11:$FP$11,GO$12,$AC11:$FP11) -> #VALUE! | GP11: =SUMIF($AB$8:$FO$8,GP$9,$AB11:$FO11) -> 32 | GQ11: =SUMIF($AB$8:$FO$8,GQ$9,$AB11:$FO11) -> 64 | GR11: =SUMIF($AB$8:$FO$8,GR$9,$AB11:$FO11) -> 64 | GS11: =SUMIF($AB$8:$FO$8,GS$9,$AB11:$FO11) -> 64 | GT11: =SUMIF($AB$8:$FO$8,GT$9,$AB11:$FO11) -> 64 | GU11: =SUMIF($AB$8:$FO$8,GU$9,$AB11:$FO11) -> 64 | GV11: =SUMIF($AB$8:$FO$8,GV$9,$AB11:$FO11) -> 52 | GW11: =SUMIF($AB$8:$FO$8,GW$9,$AB11:$FO11) -> 30 | ... HE11: =SUMIF($AB$8:$FO$8,HE$9,$AB11:$FO11) -> 0 | HF11: =SUM(FQ11:HE11) -> #VALUE! | HG11: =HF11-S11 -> #VALUE!
B12: Enabling | C12: PMO | D12: PMO | E12: Program Manager | F12: US | G12: Consulting Services | H12: Enterprise Performance | I12: SAP | J12: US | K12: Package and Technology Enablement | L12: Package Functional Transformation | M12: L65 - Senior Manager | N12: =_xlfn.CONCAT(C12,"-",D12) -> PMO-PMO | O12: =_xlfn.CONCAT(Y12,"-",Z12,"-",F12,"-",X12) -> Technology-Senior Manager-US-Consulting | P12: =_xlfn.CONCAT(C12," - ",Y12) -> PMO - Technology | Q12: =AB12*SUM(AZ12:ET12) -> 979488 | R12: =AB12*SUM(BC12:BN12) -> 131328 | S12: =SUM(GP12:HN12) -> #VALUE! | T12: =SUM(AZ12:EZ12) -> 2864 | U12: =_xlfn.CONCAT(Y12," - ",Z12) -> Technology - Senior Manager | V12: =VLOOKUP(O12,$B$187:$H$848,4,0) -> 7-10 years | W12: =IF(F12="US", "Onshore",IF(F12="India","Offshore", "Nearshore")) -> Onshore | X12: Consulting | Y12: Technology | Z12: Senior Manager | AA12: =[1]Resourcing!QD16 -> 0 | AB12: =IFERROR(VLOOKUP(O12,$B$187:$S$848,6,FALSE()),"combination not found") -> 342 | BC12: 32 | BD12: 32 | BE12: 32 | BF12: 32 | BG12: 32 | BH12: 32 | BI12: 32 | BJ12: 32 | BK12: 32 | BL12: 32 | BM12: 32 | BN12: 32 | BO12: 32 | BP12: 32 | BQ12: 32 | BT12: 32 | BU12: 32 | BV12: 32 | BW12: 32 | BX12: 32 | BY12: 32 | BZ12: 32 | CA12: 32 | CB12: 32 | CC12: 32 | CD12: 32 | CE12: 32 | CF12: 32 | CG12: 32 | CH12: 32 | CI12: 32 | CJ12: 32 | CK12: 32 | CL12: 32 | CM12: 32 | CN12: 32 | CO12: 32 | CP12: 32 | CQ12: 32 | CR12: 32 | CS12: 32 | CT12: 32 | CU12: 32 | CV12: 32 | CW12: 32 | CX12: 32 | CY12: 32 | CZ12: 32 | DA12: 32 | DB12: 32 | DC12: 32 | DD12: 32 | DE12: 32 | DF12: 32 | DG12: 32 | DH12: 32 | DI12: 32 | DJ12: 32 | DK12: 32 | DL12: 32 | DM12: 32 | DN12: 32 | DO12: 32 | DP12: 32 | DQ12: 32 | DT12: 32 | DU12: 32 | DV12: 32 | DW12: 32 | DX12: 32 | DY12: 32 | DZ12: 32 | EA12: 32 | EB12: 32 | EC12: 32 | ED12: 32 | EE12: 32 | EF12: 32 | EG12: 32 | EH12: 32 | EI12: 32 | EJ12: 32 | EK12: 32 | EL12: 32 | EM12: 32 | EN12: 32 | EO12: 32 | EP12: 16 | EQ12: 16 | ER12: 16 | ES12: 16 | ET12: 16 | FQ12: =SUMIF($AC$11:$FP$11,FQ$12,$AC12:$FP12) -> #VALUE! | FR12: =SUMIF($AC$11:$FP$11,FR$12,$AC12:$FP12) -> #VALUE! | FS12: =SUMIF($AC$11:$FP$11,FS$12,$AC12:$FP12) -> #VALUE! | FT12: =SUMIF($AC$11:$FP$11,FT$12,$AC12:$FP12) -> #VALUE! | FU12: =SUMIF($AC$11:$FP$11,FU$12,$AC12:$FP12) -> #VALUE! | FV12: =SUMIF($AC$11:$FP$11,FV$12,$AC12:$FP12) -> #VALUE! | FW12: =SUMIF($AC$11:$FP$11,FW$12,$AC12:$FP12) -> #VALUE! | FX12: =SUMIF($AC$11:$FP$11,FX$12,$AC12:$FP12) -> #VALUE! | ... GO12: =SUMIF($AC$11:$FP$11,GO$12,$AC12:$FP12) -> #VALUE! | GP12: =SUMIF($AB$8:$FO$8,GP$9,$AB12:$FO12) -> 64 | GQ12: =SUMIF($AB$8:$FO$8,GQ$9,$AB12:$FO12) -> 128 | GR12: =SUMIF($AB$8:$FO$8,GR$9,$AB12:$FO12) -> 128 | GS12: =SUMIF($AB$8:$FO$8,GS$9,$AB12:$FO12) -> 128 | GT12: =SUMIF($AB$8:$FO$8,GT$9,$AB12:$FO12) -> 128 | GU12: =SUMIF($AB$8:$FO$8,GU$9,$AB12:$FO12) -> 128 | GV12: =SUMIF($AB$8:$FO$8,GV$9,$AB12:$FO12) -> 96 | GW12: =SUMIF($AB$8:$FO$8,GW$9,$AB12:$FO12) -> 48 | ... HE12: =SUMIF($AB$8:$FO$8,HE$9,$AB12:$FO12) -> 0 | HF12: =SUM(FQ12:HE12) -> #VALUE! | HG12: =HF12-S12 -> #VALUE!
B13: Enabling | C13: PMO | D13: PMO | E13: PMO Consultant | F13: US | G13: Consulting Services | H13: Enterprise Performance | I13: SAP | J13: US | K13: Package and Technology Enablement | L13: Package Functional Transformation | M13: L25 - Analyst | N13: =_xlfn.CONCAT(C13,"-",D13) -> PMO-PMO | O13: =_xlfn.CONCAT(Y13,"-",Z13,"-",F13,"-",X13) -> Technology-Senior Consultant-US-Consulting | P13: =_xlfn.CONCAT(C13," - ",Y13) -> PMO - Technology | Q13: =AB13*SUM(AZ13:ET13) -> 1017900 | R13: =AB13*SUM(BC13:BN13) -> 140400 | S13: =SUM(GP13:HN13) -> #VALUE! | T13: =SUM(AZ13:EZ13) -> 3915 | U13: =_xlfn.CONCAT(Y13," - ",Z13) -> Technology - Senior Consultant | V13: =VLOOKUP(O13,$B$187:$H$848,4,0) -> 3-5 years | W13: =IF(F13="US", "Onshore",IF(F13="India","Offshore", "Nearshore")) -> Onshore | X13: Consulting | Y13: Technology | Z13: Senior Consultant | AA13: =[1]Resourcing!QD17 -> 402.16037 | AB13: =IFERROR(VLOOKUP(O13,$B$187:$S$848,6,FALSE()),"combination not found") -> 260 | BC13: 45 | BD13: 45 | BE13: 45 | BF13: 45 | BG13: 45 | BH13: 45 | BI13: 45 | BJ13: 45 | BK13: 45 | BL13: 45 | BM13: 45 | BN13: 45 | BO13: 45 | BP13: 45 | BQ13: 45 | BT13: 45 | BU13: 45 | BV13: 45 | BW13: 45 | BX13: 45 | BY13: 45 | BZ13: 45 | CA13: 45 | CB13: 45 | CC13: 45 | CD13: 45 | CE13: 45 | CF13: 45 | CG13: 45 | CH13: 45 | CI13: 45 | CJ13: 45 | CK13: 45 | CL13: 45 | CM13: 45 | CN13: 45 | CO13: 45 | CP13: 45 | CQ13: 45 | CR13: 45 | CS13: 45 | CT13: 45 | CU13: 45 | CV13: 45 | CW13: 45 | CX13: 45 | CY13: 45 | CZ13: 45 | DA13: 45 | DB13: 45 | DC13: 45 | DD13: 45 | DE13: 45 | DF13: 45 | DG13: 45 | DH13: 45 | DI13: 45 | DJ13: 45 | DK13: 45 | DL13: 45 | DM13: 45 | DN13: 45 | DO13: 45 | DP13: 45 | DQ13: 45 | DT13: 45 | DU13: 45 | DV13: 45 | DW13: 45 | DX13: 45 | DY13: 45 | DZ13: 45 | EA13: 45 | EB13: 45 | EC13: 45 | ED13: 45 | EE13: 45 | EF13: 45 | EG13: 45 | EH13: 45 | EI13: 45 | EJ13: 45 | EK13: 45 | EL13: 45 | EM13: 45 | EN13: 45 | EO13: 45 | FQ13: 90 | FR13: =SUMIF($AC$11:$FP$11,FR$12,$AC13:$FP13) -> #VALUE! | FS13: =SUMIF($AC$11:$FP$11,FS$12,$AC13:$FP13) -> #VALUE! | FT13: =SUMIF($AC$11:$FP$11,FT$12,$AC13:$FP13) -> #VALUE! | FU13: =SUMIF($AC$11:$FP$11,FU$12,$AC13:$FP13) -> #VALUE! | FV13: =SUMIF($AC$11:$FP$11,FV$12,$AC13:$FP13) -> #VALUE! | FW13: =SUMIF($AC$11:$FP$11,FW$12,$AC13:$FP13) -> #VALUE! | FX13: =SUMIF($AC$11:$FP$11,FX$12,$AC13:$FP13) -> #VALUE! | FY13: =SUMIF($AC$11:$FP$11,FY$12,$AC13:$FP13) -> #VALUE! | ... GO13: =SUMIF($AC$11:$FP$11,GO$12,$AC13:$FP13) -> #VALUE! | GP13: =SUMIF($AB$8:$FO$8,GP$9,$AB13:$FO13) -> 90 | GQ13: =SUMIF($AB$8:$FO$8,GQ$9,$AB13:$FO13) -> 180 | GR13: =SUMIF($AB$8:$FO$8,GR$9,$AB13:$FO13) -> 180 | GS13: =SUMIF($AB$8:$FO$8,GS$9,$AB13:$FO13) -> 180 | GT13: =SUMIF($AB$8:$FO$8,GT$9,$AB13:$FO13) -> 180 | GU13: =SUMIF($AB$8:$FO$8,GU$9,$AB13:$FO13) -> 180 | GV13: =SUMIF($AB$8:$FO$8,GV$9,$AB13:$FO13) -> 90 | GW13: =SUMIF($AB$8:$FO$8,GW$9,$AB13:$FO13) -> 0 | ... HE13: =SUMIF($AB$8:$FO$8,HE$9,$AB13:$FO13) -> 0 | HF13: =SUM(FQ13:HE13) -> #VALUE! | HG13: =HF13-S13 -> #VALUE!
B14: Enabling | C14: PMO | D14: PMO | E14: Offshore Lead | F14: India | G14: Consulting Services | H14: Enterprise Performance | I14: SAP | J14: India | K14: Package and Technology Enablement | L14: Package Program and Solution Management | M14: LMD - Managing Director | N14: =_xlfn.CONCAT(C14,"-",D14) -> PMO-PMO | O14: =_xlfn.CONCAT(Y14,"-",Z14,"-",F14,"-",X14) -> Technology-Principal-India-Consulting | P14: =_xlfn.CONCAT(C14," - ",Y14) -> PMO - Technology | Q14: =AB14*SUM(AZ14:ET14) -> 95040 | R14: =AB14*SUM(BC14:BN14) -> 8640 | S14: =SUM(GP14:HN14) -> #VALUE! | T14: =SUM(AZ14:EZ14) -> 528 | U14: =_xlfn.CONCAT(Y14," - ",Z14) -> Technology - Principal | V14: =VLOOKUP(O14,$B$187:$H$848,4,0) -> 15+ years | W14: =IF(F14="US", "Onshore",IF(F14="India","Offshore", "Nearshore")) -> Offshore | X14: Consulting | Y14: Technology | Z14: Principal | AA14: =[1]Resourcing!QD18 -> 403.10063 | AB14: =IFERROR(VLOOKUP(O14,$B$187:$S$848,6,FALSE()),"combination not found") -> 180 | BC14: 4 | BD14: 4 | BE14: 4 | BF14: 4 | BG14: 4 | BH14: 4 | BI14: 4 | BJ14: 4 | BK14: 4 | BL14: 4 | BM14: 4 | BN14: 4 | BO14: 6 | BP14: 6 | BQ14: 6 | BT14: 6 | BU14: 6 | BV14: 6 | BW14: 6 | BX14: 6 | BY14: 6 | BZ14: 6 | CA14: 6 | CB14: 6 | CC14: 6 | CD14: 6 | CE14: 6 | CF14: 6 | CG14: 6 | CH14: 6 | CI14: 6 | CJ14: 6 | CK14: 6 | CL14: 6 | CM14: 6 | CN14: 6 | CO14: 6 | CP14: 6 | CQ14: 6 | CR14: 6 | CS14: 6 | CT14: 6 | CU14: 6 | CV14: 6 | CW14: 6 | CX14: 6 | CY14: 6 | CZ14: 6 | DA14: 6 | DB14: 6 | DC14: 6 | DD14: 6 | DE14: 6 | DF14: 6 | DG14: 6 | DH14: 6 | DI14: 6 | DJ14: 6 | DK14: 6 | DL14: 6 | DM14: 6 | DN14: 6 | DO14: 6 | DP14: 6 | DQ14: 6 | DT14: 6 | DU14: 6 | DV14: 6 | DW14: 6 | DX14: 6 | DY14: 6 | DZ14: 6 | EA14: 6 | EB14: 6 | EC14: 6 | ED14: 6 | EE14: 6 | EF14: 6 | EG14: 6 | EH14: 6 | EI14: 6 | EJ14: 6 | EK14: 6 | EL14: 6 | EM14: 6 | EN14: 6 | EO14: 6 | EP14: 6 | EQ14: 6 | ER14: 6 | ES14: 6 | ET14: 6 | FQ14: =SUMIF($AC$11:$FP$11,FQ$12,$AC14:$FP14) -> #VALUE! | FR14: =SUMIF($AC$11:$FP$11,FR$12,$AC14:$FP14) -> #VALUE! | FS14: =SUMIF($AC$11:$FP$11,FS$12,$AC14:$FP14) -> #VALUE! | FT14: =SUMIF($AC$11:$FP$11,FT$12,$AC14:$FP14) -> #VALUE! | FU14: =SUMIF($AC$11:$FP$11,FU$12,$AC14:$FP14) -> #VALUE! | FV14: =SUMIF($AC$11:$FP$11,FV$12,$AC14:$FP14) -> #VALUE! | FW14: =SUMIF($AC$11:$FP$11,FW$12,$AC14:$FP14) -> #VALUE! | FX14: =SUMIF($AC$11:$FP$11,FX$12,$AC14:$FP14) -> #VALUE! | ... GO14: =SUMIF($AC$11:$FP$11,GO$12,$AC14:$FP14) -> #VALUE! | GP14: =SUMIF($AB$8:$FO$8,GP$9,$AB14:$FO14) -> 12 | GQ14: =SUMIF($AB$8:$FO$8,GQ$9,$AB14:$FO14) -> 24 | GR14: =SUMIF($AB$8:$FO$8,GR$9,$AB14:$FO14) -> 24 | GS14: =SUMIF($AB$8:$FO$8,GS$9,$AB14:$FO14) -> 24 | GT14: =SUMIF($AB$8:$FO$8,GT$9,$AB14:$FO14) -> 24 | GU14: =SUMIF($AB$8:$FO$8,GU$9,$AB14:$FO14) -> 24 | GV14: =SUMIF($AB$8:$FO$8,GV$9,$AB14:$FO14) -> 24 | GW14: =SUMIF($AB$8:$FO$8,GW$9,$AB14:$FO14) -> 18 | ... HE14: =SUMIF($AB$8:$FO$8,HE$9,$AB14:$FO14) -> 0 | HF14: =SUM(FQ14:HE14) -> #VALUE! | HG14: =HF14-S14 -> #VALUE!
B15: Enabling | C15: PMO | D15: PMO | E15: Offshore GDM | F15: India | G15: Consulting Services | H15: Enterprise Performance | I15: SAP | J15: India | K15: Package and Technology Enablement | L15: Package Functional Transformation | M15: L65 - Senior Manager | N15: =_xlfn.CONCAT(C15,"-",D15) -> PMO-PMO | O15: =_xlfn.CONCAT(Y15,"-",Z15,"-",F15,"-",X15) -> Technology-Senior Manager-India-Consulting | P15: =_xlfn.CONCAT(C15," - ",Y15) -> PMO - Technology | Q15: =AB15*SUM(AZ15:ET15) -> 394496 | R15: =AB15*SUM(BC15:BN15) -> 51456 | S15: =SUM(GP15:HN15) -> #VALUE! | T15: =SUM(AZ15:EZ15) -> 2944 | U15: =_xlfn.CONCAT(Y15," - ",Z15) -> Technology - Senior Manager | V15: =VLOOKUP(O15,$B$187:$H$848,4,0) -> 7-10 years | W15: =IF(F15="US", "Onshore",IF(F15="India","Offshore", "Nearshore")) -> Offshore | X15: Consulting | Y15: Technology | Z15: Senior Manager | AA15: =[1]Resourcing!QD19 -> 380.11732 | AB15: =IFERROR(VLOOKUP(O15,$B$187:$S$848,6,FALSE()),"combination not found") -> 134 | BC15: 32 | BD15: 32 | BE15: 32 | BF15: 32 | BG15: 32 | BH15: 32 | BI15: 32 | BJ15: 32 | BK15: 32 | BL15: 32 | BM15: 32 | BN15: 32 | BO15: 32 | BP15: 32 | BQ15: 32 | BT15: 32 | BU15: 32 | BV15: 32 | BW15: 32 | BX15: 32 | BY15: 32 | BZ15: 32 | CA15: 32 | CB15: 32 | CC15: 32 | CD15: 32 | CE15: 32 | CF15: 32 | CG15: 32 | CH15: 32 | CI15: 32 | CJ15: 32 | CK15: 32 | CL15: 32 | CM15: 32 | CN15: 32 | CO15: 32 | CP15: 32 | CQ15: 32 | CR15: 32 | CS15: 32 | CT15: 32 | CU15: 32 | CV15: 32 | CW15: 32 | CX15: 32 | CY15: 32 | CZ15: 32 | DA15: 32 | DB15: 32 | DC15: 32 | DD15: 32 | DE15: 32 | DF15: 32 | DG15: 32 | DH15: 32 | DI15: 32 | DJ15: 32 | DK15: 32 | DL15: 32 | DM15: 32 | DN15: 32 | DO15: 32 | DP15: 32 | DQ15: 32 | DT15: 32 | DU15: 32 | DV15: 32 | DW15: 32 | DX15: 32 | DY15: 32 | DZ15: 32 | EA15: 32 | EB15: 32 | EC15: 32 | ED15: 32 | EE15: 32 | EF15: 32 | EG15: 32 | EH15: 32 | EI15: 32 | EJ15: 32 | EK15: 32 | EL15: 32 | EM15: 32 | EN15: 32 | EO15: 32 | EP15: 32 | EQ15: 32 | ER15: 32 | ES15: 32 | ET15: 32 | FQ15: =SUMIF($AC$11:$FP$11,FQ$12,$AC15:$FP15) -> #VALUE! | FR15: =SUMIF($AC$11:$FP$11,FR$12,$AC15:$FP15) -> #VALUE! | FS15: =SUMIF($AC$11:$FP$11,FS$12,$AC15:$FP15) -> #VALUE! | FT15: =SUMIF($AC$11:$FP$11,FT$12,$AC15:$FP15) -> #VALUE! | FU15: =SUMIF($AC$11:$FP$11,FU$12,$AC15:$FP15) -> #VALUE! | FV15: =SUMIF($AC$11:$FP$11,FV$12,$AC15:$FP15) -> #VALUE! | FW15: =SUMIF($AC$11:$FP$11,FW$12,$AC15:$FP15) -> #VALUE! | FX15: =SUMIF($AC$11:$FP$11,FX$12,$AC15:$FP15) -> #VALUE! | ... GO15: =SUMIF($AC$11:$FP$11,GO$12,$AC15:$FP15) -> #VALUE! | GP15: =SUMIF($AB$8:$FO$8,GP$9,$AB15:$FO15) -> 64 | GQ15: =SUMIF($AB$8:$FO$8,GQ$9,$AB15:$FO15) -> 128 | GR15: =SUMIF($AB$8:$FO$8,GR$9,$AB15:$FO15) -> 128 | GS15: =SUMIF($AB$8:$FO$8,GS$9,$AB15:$FO15) -> 128 | GT15: =SUMIF($AB$8:$FO$8,GT$9,$AB15:$FO15) -> 128 | GU15: =SUMIF($AB$8:$FO$8,GU$9,$AB15:$FO15) -> 128 | GV15: =SUMIF($AB$8:$FO$8,GV$9,$AB15:$FO15) -> 128 | GW15: =SUMIF($AB$8:$FO$8,GW$9,$AB15:$FO15) -> 96 | ... HE15: =SUMIF($AB$8:$FO$8,HE$9,$AB15:$FO15) -> 0 | HF15: =SUM(FQ15:HE15) -> #VALUE! | HG15: =HF15-S15 -> #VALUE!
B16: Enabling | C16: PMO | D16: PMO | E16: PMO Consultant | F16: India | G16: Consulting Services | H16: Enterprise Performance | I16: SAP | J16: India | K16: Package and Technology Enablement | L16: Package Functional Transformation | M16: L35 - Consultant | N16: =_xlfn.CONCAT(C16,"-",D16) -> PMO-PMO | O16: =_xlfn.CONCAT(Y16,"-",Z16,"-",F16,"-",X16) -> Technology-Consultant-India-Consulting | P16: =_xlfn.CONCAT(C16," - ",Y16) -> PMO - Technology | Q16: =AB16*SUM(AZ16:ET16) -> 248400 | R16: =AB16*SUM(BC16:BN16) -> 32400 | S16: =SUM(GP16:HN16) -> #VALUE! | T16: =SUM(AZ16:EZ16) -> 4140 | U16: =_xlfn.CONCAT(Y16," - ",Z16) -> Technology - Consultant | V16: =VLOOKUP(O16,$B$187:$H$848,4,0) -> 1-3 years | W16: =IF(F16="US", "Onshore",IF(F16="India","Offshore", "Nearshore")) -> Offshore | X16: Consulting | Y16: Technology | Z16: Consultant | AA16: =[1]Resourcing!QD20 -> 264.54736 | AB16: =IFERROR(VLOOKUP(O16,$B$187:$S$848,6,FALSE()),"combination not found") -> 60 | BC16: 45 | BD16: 45 | BE16: 45 | BF16: 45 | BG16: 45 | BH16: 45 | BI16: 45 | BJ16: 45 | BK16: 45 | BL16: 45 | BM16: 45 | BN16: 45 | BO16: 45 | BP16: 45 | BQ16: 45 | BT16: 45 | BU16: 45 | BV16: 45 | BW16: 45 | BX16: 45 | BY16: 45 | BZ16: 45 | CA16: 45 | CB16: 45 | CC16: 45 | CD16: 45 | CE16: 45 | CF16: 45 | CG16: 45 | CH16: 45 | CI16: 45 | CJ16: 45 | CK16: 45 | CL16: 45 | CM16: 45 | CN16: 45 | CO16: 45 | CP16: 45 | CQ16: 45 | CR16: 45 | CS16: 45 | CT16: 45 | CU16: 45 | CV16: 45 | CW16: 45 | CX16: 45 | CY16: 45 | CZ16: 45 | DA16: 45 | DB16: 45 | DC16: 45 | DD16: 45 | DE16: 45 | DF16: 45 | DG16: 45 | DH16: 45 | DI16: 45 | DJ16: 45 | DK16: 45 | DL16: 45 | DM16: 45 | DN16: 45 | DO16: 45 | DP16: 45 | DQ16: 45 | DT16: 45 | DU16: 45 | DV16: 45 | DW16: 45 | DX16: 45 | DY16: 45 | DZ16: 45 | EA16: 45 | EB16: 45 | EC16: 45 | ED16: 45 | EE16: 45 | EF16: 45 | EG16: 45 | EH16: 45 | EI16: 45 | EJ16: 45 | EK16: 45 | EL16: 45 | EM16: 45 | EN16: 45 | EO16: 45 | EP16: 45 | EQ16: 45 | ER16: 45 | ES16: 45 | ET16: 45 | FQ16: =SUMIF($AC$11:$FP$11,FQ$12,$AC16:$FP16) -> #VALUE! | FR16: =SUMIF($AC$11:$FP$11,FR$12,$AC16:$FP16) -> #VALUE! | FS16: =SUMIF($AC$11:$FP$11,FS$12,$AC16:$FP16) -> #VALUE! | FT16: =SUMIF($AC$11:$FP$11,FT$12,$AC16:$FP16) -> #VALUE! | FU16: =SUMIF($AC$11:$FP$11,FU$12,$AC16:$FP16) -> #VALUE! | FV16: =SUMIF($AC$11:$FP$11,FV$12,$AC16:$FP16) -> #VALUE! | FW16: =SUMIF($AC$11:$FP$11,FW$12,$AC16:$FP16) -> #VALUE! | FX16: =SUMIF($AC$11:$FP$11,FX$12,$AC16:$FP16) -> #VALUE! | ... GO16: =SUMIF($AC$11:$FP$11,GO$12,$AC16:$FP16) -> #VALUE! | GP16: =SUMIF($AB$8:$FO$8,GP$9,$AB16:$FO16) -> 90 | GQ16: =SUMIF($AB$8:$FO$8,GQ$9,$AB16:$FO16) -> 180 | GR16: =SUMIF($AB$8:$FO$8,GR$9,$AB16:$FO16) -> 180 | GS16: =SUMIF($AB$8:$FO$8,GS$9,$AB16:$FO16) -> 180 | GT16: =SUMIF($AB$8:$FO$8,GT$9,$AB16:$FO16) -> 180 | GU16: =SUMIF($AB$8:$FO$8,GU$9,$AB16:$FO16) -> 180 | GV16: =SUMIF($AB$8:$FO$8,GV$9,$AB16:$FO16) -> 180 | GW16: =SUMIF($AB$8:$FO$8,GW$9,$AB16:$FO16) -> 135 | ... HE16: =SUMIF($AB$8:$FO$8,HE$9,$AB16:$FO16) -> 0 | HF16: =SUM(FQ16:HE16) -> #VALUE! | HG16: =HF16-S16 -> #VALUE!
Q17: =AB17*SUM(AZ17:ET17) -> 0 | R17: =AB17*SUM(BC17:BN17) -> 0 | T17: =SUM(AZ17:EZ17) -> 0 | AA17: =[1]Resourcing!QD21 -> 179.31318 | FQ17: =SUMIF($AC$11:$FP$11,FQ$12,$AC17:$FP17) -> #VALUE! | FR17: =SUMIF($AC$11:$FP$11,FR$12,$AC17:$FP17) -> #VALUE! | FS17: =SUMIF($AC$11:$FP$11,FS$12,$AC17:$FP17) -> #VALUE! | FT17: =SUMIF($AC$11:$FP$11,FT$12,$AC17:$FP17) -> #VALUE! | FU17: =SUMIF($AC$11:$FP$11,FU$12,$AC17:$FP17) -> #VALUE! | FV17: =SUMIF($AC$11:$FP$11,FV$12,$AC17:$FP17) -> #VALUE! | FW17: =SUMIF($AC$11:$FP$11,FW$12,$AC17:$FP17) -> #VALUE! | FX17: =SUMIF($AC$11:$FP$11,FX$12,$AC17:$FP17) -> #VALUE! | ... GO17: =SUMIF($AC$11:$FP$11,GO$12,$AC17:$FP17) -> #VALUE!
B18: Process | C18: Solution Architecture | D18: Solution Delivery | E18: Solution Architect | F18: US | G18: Consulting Services | H18: Enterprise Performance | I18: SAP | J18: US | K18: Package and Technology Enablement | L18: Package Functional Transformation | M18: L65 - Senior Manager | N18: =_xlfn.CONCAT(C18,"-",D18) -> Solution Architecture-Solution Delivery | O18: =_xlfn.CONCAT(Y18,"-",Z18,"-",F18,"-",X18) -> Technology-Senior Manager-US-Consulting | P18: =_xlfn.CONCAT(C18," - ",Y18) -> Solution Architecture - Technology | Q18: =AB18*SUM(AZ18:ET18) -> 979488 | R18: =AB18*SUM(BC18:BN18) -> 131328 | S18: =SUM(GP18:HN18) -> 0 | T18: =SUM(AZ18:EZ18) -> 2864 | U18: =_xlfn.CONCAT(Y18," - ",Z18) -> Technology - Senior Manager | V18: =VLOOKUP(O18,$B$187:$H$848,4,0) -> 7-10 years | W18: =IF(F18="US", "Onshore",IF(F18="India","Offshore", "Nearshore")) -> Onshore | X18: Consulting | Y18: Technology | Z18: Senior Manager | AA18: =[1]Resourcing!QD22 -> 126.96174 | AB18: =IFERROR(VLOOKUP(O18,$B$187:$S$848,6,FALSE()),"combination not found") -> 342 | BC18: 32 | BD18: 32 | BE18: 32 | BF18: 32 | BG18: 32 | BH18: 32 | BI18: 32 | BJ18: 32 | BK18: 32 | BL18: 32 | BM18: 32 | BN18: 32 | BO18: 32 | BP18: 32 | BQ18: 32 | BT18: 32 | BU18: 32 | BV18: 32 | BW18: 32 | BX18: 32 | BY18: 32 | BZ18: 32 | CA18: 32 | CB18: 32 | CC18: 32 | CD18: 32 | CE18: 32 | CF18: 32 | CG18: 32 | CH18: 32 | CI18: 32 | CJ18: 32 | CK18: 32 | CL18: 32 | CM18: 32 | CN18: 32 | CO18: 32 | CP18: 32 | CQ18: 32 | CR18: 32 | CS18: 32 | CT18: 32 | CU18: 32 | CV18: 32 | CW18: 32 | CX18: 32 | CY18: 32 | CZ18: 32 | DA18: 32 | DB18: 32 | DC18: 32 | DD18: 32 | DE18: 32 | DF18: 32 | DG18: 32 | DH18: 32 | DI18: 32 | DJ18: 32 | DK18: 32 | DL18: 32 | DM18: 32 | DN18: 32 | DO18: 32 | DP18: 32 | DQ18: 32 | DT18: 32 | DU18: 32 | DV18: 32 | DW18: 32 | DX18: 32 | DY18: 32 | DZ18: 32 | EA18: 32 | EB18: 32 | EC18: 32 | ED18: 32 | EE18: 32 | EF18: 32 | EG18: 32 | EH18: 32 | EI18: 32 | EJ18: 32 | EK18: 32 | EL18: 32 | EM18: 32 | EN18: 32 | EO18: 32 | EP18: 16 | EQ18: 16 | ER18: 16 | ES18: 16 | ET18: 16 | FQ18: =SUMIF($AC$11:$FP$11,FQ$12,$AC18:$FP18) -> #VALUE! | FR18: =SUMIF($AC$11:$FP$11,FR$12,$AC18:$FP18) -> #VALUE! | FS18: =SUMIF($AC$11:$FP$11,FS$12,$AC18:$FP18) -> #VALUE! | FT18: =SUMIF($AC$11:$FP$11,FT$12,$AC18:$FP18) -> #VALUE! | FU18: =SUMIF($AC$11:$FP$11,FU$12,$AC18:$FP18) -> #VALUE! | FV18: =SUMIF($AC$11:$FP$11,FV$12,$AC18:$FP18) -> #VALUE! | FW18: =SUMIF($AC$11:$FP$11,FW$12,$AC18:$FP18) -> #VALUE! | FX18: =SUMIF($AC$11:$FP$11,FX$12,$AC18:$FP18) -> #VALUE! | ... GO18: =SUMIF($AC$11:$FP$11,GO$12,$AC18:$FP18) -> #VALUE!
B19: Process | C19: Solution Architecture | D19: Solution Delivery | E19: Solution Lead - offshore | F19: India | G19: Consulting Services | H19: Enterprise Performance | I19: SAP | J19: India | K19: Package and Technology Enablement | L19: Package Functional Transformation | M19: L55 - Manager | N19: =_xlfn.CONCAT(C19,"-",D19) -> Solution Architecture-Solution Delivery | O19: =_xlfn.CONCAT(Y19,"-",Z19,"-",F19,"-",X19) -> Technology-Senior Consultant-India-Consulting | P19: =_xlfn.CONCAT(C19," - ",Y19) -> Solution Architecture - Technology | Q19: =AB19*SUM(AZ19:ET19) -> 277965 | R19: =AB19*SUM(BC19:BN19) -> 31950 | S19: =SUM(GP19:HN19) -> #VALUE! | T19: =SUM(AZ19:EZ19) -> 3915 | U19: =_xlfn.CONCAT(Y19," - ",Z19) -> Technology - Senior Consultant | V19: =VLOOKUP(O19,$B$187:$H$848,4,0) -> 3-5 years | W19: =IF(F19="US", "Onshore",IF(F19="India","Offshore", "Nearshore")) -> Offshore | X19: Consulting | Y19: Technology | Z19: Senior Consultant | AA19: =[1]Resourcing!QD23 -> 53.073913 | AB19: =IFERROR(VLOOKUP(O19,$B$187:$S$848,6,FALSE()),"combination not found") -> 71 | BE19: 45 | BF19: 45 | BG19: 45 | BH19: 45 | BI19: 45 | BJ19: 45 | BK19: 45 | BL19: 45 | BM19: 45 | BN19: 45 | BO19: 45 | BP19: 45 | BQ19: 45 | BT19: 45 | BU19: 45 | BV19: 45 | BW19: 45 | BX19: 45 | BY19: 45 | BZ19: 45 | CA19: 45 | CB19: 45 | CC19: 45 | CD19: 45 | CE19: 45 | CF19: 45 | CG19: 45 | CH19: 45 | CI19: 45 | CJ19: 45 | CK19: 45 | CL19: 45 | CM19: 45 | CN19: 45 | CO19: 45 | CP19: 45 | CQ19: 45 | CR19: 45 | CS19: 45 | CT19: 45 | CU19: 45 | CV19: 45 | CW19: 45 | CX19: 45 | CY19: 45 | CZ19: 45 | DA19: 45 | DB19: 45 | DC19: 45 | DD19: 45 | DE19: 45 | DF19: 45 | DG19: 45 | DH19: 45 | DI19: 45 | DJ19: 45 | DK19: 45 | DL19: 45 | DM19: 45 | DN19: 45 | DO19: 45 | DP19: 45 | DQ19: 45 | DT19: 45 | DU19: 45 | DV19: 45 | DW19: 45 | DX19: 45 | DY19: 45 | DZ19: 45 | EA19: 45 | EB19: 45 | EC19: 45 | ED19: 45 | EE19: 45 | EF19: 45 | EG19: 45 | EH19: 45 | EI19: 45 | EJ19: 45 | EK19: 45 | EL19: 45 | EM19: 45 | EN19: 45 | EO19: 45 | EP19: 45 | EQ19: 45 | FQ19: =SUMIF($AC$11:$FP$11,FQ$12,$AC19:$FP19) -> #VALUE! | FR19: =SUMIF($AC$11:$FP$11,FR$12,$AC19:$FP19) -> #VALUE! | FS19: =SUMIF($AC$11:$FP$11,FS$12,$AC19:$FP19) -> #VALUE! | FT19: =SUMIF($AC$11:$FP$11,FT$12,$AC19:$FP19) -> #VALUE! | FU19: =SUMIF($AC$11:$FP$11,FU$12,$AC19:$FP19) -> #VALUE! | FV19: =SUMIF($AC$11:$FP$11,FV$12,$AC19:$FP19) -> #VALUE! | FW19: =SUMIF($AC$11:$FP$11,FW$12,$AC19:$FP19) -> #VALUE! | FX19: =SUMIF($AC$11:$FP$11,FX$12,$AC19:$FP19) -> #VALUE! | ... GO19: =SUMIF($AC$11:$FP$11,GO$12,$AC19:$FP19) -> #VALUE! | GP19: =SUMIF($AB$8:$FO$8,GP$9,$AB19:$FO19) -> 90 | GQ19: =SUMIF($AB$8:$FO$8,GQ$9,$AB19:$FO19) -> 180 | GR19: =SUMIF($AB$8:$FO$8,GR$9,$AB19:$FO19) -> 180 | GS19: =SUMIF($AB$8:$FO$8,GS$9,$AB19:$FO19) -> 180 | GT19: =SUMIF($AB$8:$FO$8,GT$9,$AB19:$FO19) -> 180 | GU19: =SUMIF($AB$8:$FO$8,GU$9,$AB19:$FO19) -> 180 | GV19: =SUMIF($AB$8:$FO$8,GV$9,$AB19:$FO19) -> 180 | GW19: =SUMIF($AB$8:$FO$8,GW$9,$AB19:$FO19) -> 0 | ... HE19: =SUMIF($AB$8:$FO$8,HE$9,$AB19:$FO19) -> 0 | HF19: =SUM(FQ19:HE19) -> #VALUE! | HG19: =HF19-S45 -> #VALUE!
Q20: =AB20*SUM(AZ20:ET20) -> 0 | R20: =AB20*SUM(BC20:BN20) -> 0 | T20: =SUM(AZ20:EZ20) -> 0 | AA20: =[1]Resourcing!QD24 -> 0 | FQ20: =SUMIF($AC$11:$FP$11,FQ$12,$AC20:$FP20) -> #VALUE! | FR20: =SUMIF($AC$11:$FP$11,FR$12,$AC20:$FP20) -> #VALUE! | FS20: =SUMIF($AC$11:$FP$11,FS$12,$AC20:$FP20) -> #VALUE! | FT20: =SUMIF($AC$11:$FP$11,FT$12,$AC20:$FP20) -> #VALUE! | FU20: =SUMIF($AC$11:$FP$11,FU$12,$AC20:$FP20) -> #VALUE! | FV20: =SUMIF($AC$11:$FP$11,FV$12,$AC20:$FP20) -> #VALUE! | FW20: =SUMIF($AC$11:$FP$11,FW$12,$AC20:$FP20) -> #VALUE! | FX20: =SUMIF($AC$11:$FP$11,FX$12,$AC20:$FP20) -> #VALUE! | ... GO20: =SUMIF($AC$11:$FP$11,GO$12,$AC20:$FP20) -> #VALUE! | GP20: =SUMIF($AB$8:$FO$8,GP$9,$AB20:$FO20) -> 0 | GQ20: =SUMIF($AB$8:$FO$8,GQ$9,$AB20:$FO20) -> 0 | GR20: =SUMIF($AB$8:$FO$8,GR$9,$AB20:$FO20) -> 0 | GS20: =SUMIF($AB$8:$FO$8,GS$9,$AB20:$FO20) -> 0 | GT20: =SUMIF($AB$8:$FO$8,GT$9,$AB20:$FO20) -> 0 | GU20: =SUMIF($AB$8:$FO$8,GU$9,$AB20:$FO20) -> 0 | GV20: =SUMIF($AB$8:$FO$8,GV$9,$AB20:$FO20) -> 0 | GW20: =SUMIF($AB$8:$FO$8,GW$9,$AB20:$FO20) -> 0 | ... HE20: =SUMIF($AB$8:$FO$8,HE$9,$AB20:$FO20) -> 0 | HF20: =SUM(FQ20:HE20) -> #VALUE! | HG20: =HF20-S57 -> #VALUE!
B21: Process | C21: RTR | D21: RTR | E21: RTR Overall Lead | F21: US | G21: Consulting Services | H21: Enterprise Performance | I21: SAP | J21: US | K21: Package and Technology Enablement | L21: Package Functional Transformation | M21: L65 - Senior Manager | N21: =_xlfn.CONCAT(C21,"-",D21) -> RTR-RTR | O21: =_xlfn.CONCAT(Y21,"-",Z21,"-",F21,"-",X21) -> Technology-Senior Manager-US-Consulting | P21: =_xlfn.CONCAT(C21," - ",Y21) -> RTR - Technology | Q21: =AB21*SUM(AZ21:ET21) -> 984960 | R21: =AB21*SUM(BC21:BN21) -> 109440 | S21: =SUM(GP21:HN21) -> 0 | T21: =SUM(AZ21:EZ21) -> 2880 | U21: =_xlfn.CONCAT(Y21," - ",Z21) -> Technology - Senior Manager | V21: =VLOOKUP(O21,$B$187:$H$848,4,0) -> 7-10 years | W21: =IF(F21="US", "Onshore",IF(F21="India","Offshore", "Nearshore")) -> Onshore | X21: Consulting | Y21: Technology | Z21: Senior Manager | AA21: =[1]Resourcing!QD25 -> 380.11732 | AB21: =IFERROR(VLOOKUP(O21,$B$187:$S$848,6,FALSE()),"combination not found") -> 342 | BE21: 32 | BF21: 32 | BG21: 32 | BH21: 32 | BI21: 32 | BJ21: 32 | BK21: 32 | BL21: 32 | BM21: 32 | BN21: 32 | BO21: 32 | BP21: 32 | BQ21: 32 | BT21: 32 | BU21: 32 | BV21: 32 | BW21: 32 | BX21: 32 | BY21: 32 | BZ21: 32 | CA21: 32 | CB21: 32 | CC21: 32 | CD21: 32 | CE21: 32 | CF21: 32 | CG21: 32 | CH21: 32 | CI21: 32 | CJ21: 32 | CK21: 32 | CL21: 32 | CM21: 32 | CN21: 32 | CO21: 32 | CP21: 32 | CQ21: 32 | CR21: 32 | CS21: 32 | CT21: 32 | CU21: 32 | CV21: 32 | CW21: 32 | CX21: 32 | CY21: 32 | CZ21: 32 | DA21: 32 | DB21: 32 | DC21: 32 | DD21: 32 | DE21: 32 | DF21: 32 | DG21: 32 | DH21: 32 | DI21: 32 | DJ21: 32 | DK21: 32 | DL21: 32 | DM21: 32 | DN21: 32 | DO21: 32 | DP21: 32 | DQ21: 32 | DT21: 32 | DU21: 32 | DV21: 32 | DW21: 32 | DX21: 32 | DY21: 32 | DZ21: 32 | EA21: 32 | EB21: 32 | EC21: 32 | ED21: 32 | EE21: 32 | EF21: 32 | EG21: 32 | EH21: 32 | EI21: 32 | EJ21: 32 | EK21: 32 | EL21: 32 | EM21: 32 | EN21: 32 | EO21: 32 | EP21: 32 | EQ21: 32 | ER21: 32 | ES21: 32 | ET21: 32 | FQ21: =SUMIF($AC$11:$FP$11,FQ$12,$AC21:$FP21) -> #VALUE! | FR21: =SUMIF($AC$11:$FP$11,FR$12,$AC21:$FP21) -> #VALUE! | FS21: =SUMIF($AC$11:$FP$11,FS$12,$AC21:$FP21) -> #VALUE! | FT21: =SUMIF($AC$11:$FP$11,FT$12,$AC21:$FP21) -> #VALUE! | FU21: =SUMIF($AC$11:$FP$11,FU$12,$AC21:$FP21) -> #VALUE! | FV21: =SUMIF($AC$11:$FP$11,FV$12,$AC21:$FP21) -> #VALUE! | FW21: =SUMIF($AC$11:$FP$11,FW$12,$AC21:$FP21) -> #VALUE! | FX21: =SUMIF($AC$11:$FP$11,FX$12,$AC21:$FP21) -> #VALUE! | ... GO21: =SUMIF($AC$11:$FP$11,GO$12,$AC21:$FP21) -> #VALUE!
B22: Process | C22: RTR | D22: RTR | E22: RTR CO Lead | F22: US | G22: Consulting Services | H22: Enterprise Performance | I22: SAP | J22: US | K22: Package and Technology Enablement | L22: Package Functional Transformation | M22: L45 - Senior Consultant | N22: =_xlfn.CONCAT(C22,"-",D22) -> RTR-RTR | O22: =_xlfn.CONCAT(Y22,"-",Z22,"-",F22,"-",X22) -> Technology-Senior Consultant-US-Consulting | P22: =_xlfn.CONCAT(C22," - ",Y22) -> RTR - Technology | Q22: =AB22*SUM(AZ22:ET22) -> 854100 | R22: =AB22*SUM(BC22:BN22) -> 0 | S22: =SUM(GP22:HN22) -> 990 | T22: =SUM(AZ22:EZ22) -> 3285 | U22: =_xlfn.CONCAT(Y22," - ",Z22) -> Technology - Senior Consultant | V22: =VLOOKUP(O22,$B$187:$H$848,4,0) -> 3-5 years | W22: =IF(F22="US", "Onshore",IF(F22="India","Offshore", "Nearshore")) -> Onshore | X22: Consulting | Y22: Technology | Z22: Senior Consultant | AA22: =[1]Resourcing!QD26 -> 85.177241 | AB22: =IFERROR(VLOOKUP(O22,$B$187:$S$848,6,FALSE()),"combination not found") -> 260 | BO22: 45 | BP22: 45 | BQ22: 45 | BT22: 45 | BU22: 45 | BV22: 45 | BW22: 45 | BX22: 45 | BY22: 45 | BZ22: 45 | CA22: 45 | CB22: 45 | CC22: 45 | CD22: 45 | CE22: 45 | CF22: 45 | CG22: 45 | CH22: 45 | CI22: 45 | CJ22: 45 | CK22: 45 | CL22: 45 | CM22: 45 | CN22: 45 | CO22: 45 | CP22: 45 | CQ22: 45 | CR22: 45 | CS22: 45 | CT22: 45 | CU22: 45 | CV22: 45 | CW22: 45 | CX22: 45 | CY22: 45 | CZ22: 45 | DA22: 45 | DB22: 45 | DC22: 45 | DD22: 45 | DE22: 45 | DF22: 45 | DG22: 45 | DH22: 45 | DI22: 45 | DJ22: 45 | DK22: 45 | DL22: 45 | DM22: 45 | DN22: 45 | DO22: 45 | DP22: 45 | DQ22: 45 | DT22: 45 | DU22: 45 | DV22: 45 | DW22: 45 | DX22: 45 | DY22: 45 | DZ22: 45 | EA22: 45 | EB22: 45 | EC22: 45 | ED22: 45 | EE22: 45 | EF22: 45 | EG22: 45 | EH22: 45 | EI22: 45 | EJ22: 45 | EK22: 45 | EL22: 45 | EM22: 45 | FQ22: =SUMIF($AC$11:$FP$11,FQ$12,$AC22:$FP22) -> #VALUE! | FR22: =SUMIF($AC$11:$FP$11,FR$12,$AC22:$FP22) -> #VALUE! | FS22: =SUMIF($AC$11:$FP$11,FS$12,$AC22:$FP22) -> #VALUE! | FT22: =SUMIF($AC$11:$FP$11,FT$12,$AC22:$FP22) -> #VALUE! | FU22: =SUMIF($AC$11:$FP$11,FU$12,$AC22:$FP22) -> #VALUE! | FV22: =SUMIF($AC$11:$FP$11,FV$12,$AC22:$FP22) -> #VALUE! | FW22: =SUMIF($AC$11:$FP$11,FW$12,$AC22:$FP22) -> #VALUE! | FX22: =SUMIF($AC$11:$FP$11,FX$12,$AC22:$FP22) -> #VALUE! | ... GO22: =SUMIF($AC$11:$FP$11,GO$12,$AC22:$FP22) -> #VALUE! | GP22: =SUMIF($AB$8:$FO$8,GP$9,$AB22:$FO22) -> 90 | GQ22: =SUMIF($AB$8:$FO$8,GQ$9,$AB22:$FO22) -> 180 | GR22: =SUMIF($AB$8:$FO$8,GR$9,$AB22:$FO22) -> 180 | GS22: =SUMIF($AB$8:$FO$8,GS$9,$AB22:$FO22) -> 180 | GT22: =SUMIF($AB$8:$FO$8,GT$9,$AB22:$FO22) -> 180 | GU22: =SUMIF($AB$8:$FO$8,GU$9,$AB22:$FO22) -> 180 | GV22: =SUMIF($AB$8:$FO$8,GV$9,$AB22:$FO22) -> 0 | GW22: =SUMIF($AB$8:$FO$8,GW$9,$AB22:$FO22) -> 0 | ... HE22: =SUMIF($AB$8:$FO$8,HE$9,$AB22:$FO22) -> 0
B23: Process | C23: RTR | D23: RTR | E23: RTR Offshore Lead (GL/Intercompany) | F23: India | G23: Consulting Services | H23: Enterprise Performance | I23: SAP | J23: India | K23: Package and Technology Enablement | L23: Package Functional Transformation | M23: L55 - Manager | N23: =_xlfn.CONCAT(C23,"-",D23) -> RTR-RTR | O23: =_xlfn.CONCAT(Y23,"-",Z23,"-",F23,"-",X23) -> Technology-Manager-India-Consulting | P23: =_xlfn.CONCAT(C23," - ",Y23) -> RTR - Technology | Q23: =AB23*SUM(AZ23:ET23) -> 400950 | R23: =AB23*SUM(BC23:BN23) -> 44550 | S23: =SUM(GP23:HN23) -> 1305 | T23: =SUM(AZ23:EZ23) -> 4050 | U23: =_xlfn.CONCAT(Y23," - ",Z23) -> Technology - Manager | V23: =VLOOKUP(O23,$B$187:$H$848,4,0) -> 5-7 years | W23: =IF(F23="US", "Onshore",IF(F23="India","Offshore", "Nearshore")) -> Offshore | X23: Consulting | Y23: Technology | Z23: Manager | AA23: =[1]Resourcing!QD27 -> 0 | AB23: =IFERROR(VLOOKUP(O23,$B$187:$S$848,6,FALSE()),"combination not found") -> 99 | BE23: 45 | BF23: 45 | BG23: 45 | BH23: 45 | BI23: 45 | BJ23: 45 | BK23: 45 | BL23: 45 | BM23: 45 | BN23: 45 | BO23: 45 | BP23: 45 | BQ23: 45 | BT23: 45 | BU23: 45 | BV23: 45 | BW23: 45 | BX23: 45 | BY23: 45 | BZ23: 45 | CA23: 45 | CB23: 45 | CC23: 45 | CD23: 45 | CE23: 45 | CF23: 45 | CG23: 45 | CH23: 45 | CI23: 45 | CJ23: 45 | CK23: 45 | CL23: 45 | CM23: 45 | CN23: 45 | CO23: 45 | CP23: 45 | CQ23: 45 | CR23: 45 | CS23: 45 | CT23: 45 | CU23: 45 | CV23: 45 | CW23: 45 | CX23: 45 | CY23: 45 | CZ23: 45 | DA23: 45 | DB23: 45 | DC23: 45 | DD23: 45 | DE23: 45 | DF23: 45 | DG23: 45 | DH23: 45 | DI23: 45 | DJ23: 45 | DK23: 45 | DL23: 45 | DM23: 45 | DN23: 45 | DO23: 45 | DP23: 45 | DQ23: 45 | DT23: 45 | DU23: 45 | DV23: 45 | DW23: 45 | DX23: 45 | DY23: 45 | DZ23: 45 | EA23: 45 | EB23: 45 | EC23: 45 | ED23: 45 | EE23: 45 | EF23: 45 | EG23: 45 | EH23: 45 | EI23: 45 | EJ23: 45 | EK23: 45 | EL23: 45 | EM23: 45 | EN23: 45 | EO23: 45 | EP23: 45 | EQ23: 45 | ER23: 45 | ES23: 45 | ET23: 45 | FQ23: =SUMIF($AC$11:$FP$11,FQ$12,$AC23:$FP23) -> #VALUE! | FR23: =SUMIF($AC$11:$FP$11,FR$12,$AC23:$FP23) -> #VALUE! | FS23: =SUMIF($AC$11:$FP$11,FS$12,$AC23:$FP23) -> #VALUE! | FT23: =SUMIF($AC$11:$FP$11,FT$12,$AC23:$FP23) -> #VALUE! | FU23: =SUMIF($AC$11:$FP$11,FU$12,$AC23:$FP23) -> #VALUE! | FV23: =SUMIF($AC$11:$FP$11,FV$12,$AC23:$FP23) -> #VALUE! | FW23: =SUMIF($AC$11:$FP$11,FW$12,$AC23:$FP23) -> #VALUE! | FX23: =SUMIF($AC$11:$FP$11,FX$12,$AC23:$FP23) -> #VALUE! | ... GO23: =SUMIF($AC$11:$FP$11,GO$12,$AC23:$FP23) -> #VALUE! | GP23: =SUMIF($AB$8:$FO$8,GP$9,$AB23:$FO23) -> 90 | GQ23: =SUMIF($AB$8:$FO$8,GQ$9,$AB23:$FO23) -> 180 | GR23: =SUMIF($AB$8:$FO$8,GR$9,$AB23:$FO23) -> 180 | GS23: =SUMIF($AB$8:$FO$8,GS$9,$AB23:$FO23) -> 180 | GT23: =SUMIF($AB$8:$FO$8,GT$9,$AB23:$FO23) -> 180 | GU23: =SUMIF($AB$8:$FO$8,GU$9,$AB23:$FO23) -> 180 | GV23: =SUMIF($AB$8:$FO$8,GV$9,$AB23:$FO23) -> 180 | GW23: =SUMIF($AB$8:$FO$8,GW$9,$AB23:$FO23) -> 135 | ... HE23: =SUMIF($AB$8:$FO$8,HE$9,$AB23:$FO23) -> 0
B24: Process | C24: RTR | D24: RTR | E24: RTR AR/FSCM Lead - Offshore | F24: India | G24: Consulting Services | H24: Enterprise Performance | I24: SAP | J24: India | K24: Package and Technology Enablement | L24: Package Functional Transformation | M24: L45 - Senior Consultant | N24: =_xlfn.CONCAT(C24,"-",D24) -> RTR-RTR | O24: =_xlfn.CONCAT(Y24,"-",Z24,"-",F24,"-",X24) -> Technology-Consultant-India-Consulting | P24: =_xlfn.CONCAT(C24," - ",Y24) -> RTR - Technology | Q24: =AB24*SUM(AZ24:ET24) -> 210600 | R24: =AB24*SUM(BC24:BN24) -> 0 | S24: =SUM(GP24:HN24) -> 1215 | T24: =SUM(AZ24:EZ24) -> 3510 | U24: =_xlfn.CONCAT(Y24," - ",Z24) -> Technology - Consultant | V24: =VLOOKUP(O24,$B$187:$H$848,4,0) -> 1-3 years | W24: =IF(F24="US", "Onshore",IF(F24="India","Offshore", "Nearshore")) -> Offshore | X24: Consulting | Y24: Technology | Z24: Consultant | AA24: =[1]Resourcing!QD28 -> 381.296 | AB24: =IFERROR(VLOOKUP(O24,$B$187:$S$848,6,FALSE()),"combination not found") -> 60 | BO24: 45 | BP24: 45 | BQ24: 45 | BT24: 45 | BU24: 45 | BV24: 45 | BW24: 45 | BX24: 45 | BY24: 45 | BZ24: 45 | CA24: 45 | CB24: 45 | CC24: 45 | CD24: 45 | CE24: 45 | CF24: 45 | CG24: 45 | CH24: 45 | CI24: 45 | CJ24: 45 | CK24: 45 | CL24: 45 | CM24: 45 | CN24: 45 | CO24: 45 | CP24: 45 | CQ24: 45 | CR24: 45 | CS24: 45 | CT24: 45 | CU24: 45 | CV24: 45 | CW24: 45 | CX24: 45 | CY24: 45 | CZ24: 45 | DA24: 45 | DB24: 45 | DC24: 45 | DD24: 45 | DE24: 45 | DF24: 45 | DG24: 45 | DH24: 45 | DI24: 45 | DJ24: 45 | DK24: 45 | DL24: 45 | DM24: 45 | DN24: 45 | DO24: 45 | DP24: 45 | DQ24: 45 | DT24: 45 | DU24: 45 | DV24: 45 | DW24: 45 | DX24: 45 | DY24: 45 | DZ24: 45 | EA24: 45 | EB24: 45 | EC24: 45 | ED24: 45 | EE24: 45 | EF24: 45 | EG24: 45 | EH24: 45 | EI24: 45 | EJ24: 45 | EK24: 45 | EL24: 45 | EM24: 45 | EN24: 45 | EO24: 45 | EP24: 45 | EQ24: 45 | ER24: 45 | FQ24: =SUMIF($AC$11:$FP$11,FQ$12,$AC24:$FP24) -> #VALUE! | FR24: =SUMIF($AC$11:$FP$11,FR$12,$AC24:$FP24) -> #VALUE! | FS24: =SUMIF($AC$11:$FP$11,FS$12,$AC24:$FP24) -> #VALUE! | FT24: =SUMIF($AC$11:$FP$11,FT$12,$AC24:$FP24) -> #VALUE! | FU24: =SUMIF($AC$11:$FP$11,FU$12,$AC24:$FP24) -> #VALUE! | FV24: =SUMIF($AC$11:$FP$11,FV$12,$AC24:$FP24) -> #VALUE! | FW24: =SUMIF($AC$11:$FP$11,FW$12,$AC24:$FP24) -> #VALUE! | FX24: =SUMIF($AC$11:$FP$11,FX$12,$AC24:$FP24) -> #VALUE! | ... GO24: =SUMIF($AC$11:$FP$11,GO$12,$AC24:$FP24) -> #VALUE! | GP24: =SUMIF($AB$8:$FO$8,GP$9,$AB24:$FO24) -> 90 | GQ24: =SUMIF($AB$8:$FO$8,GQ$9,$AB24:$FO24) -> 180 | GR24: =SUMIF($AB$8:$FO$8,GR$9,$AB24:$FO24) -> 180 | GS24: =SUMIF($AB$8:$FO$8,GS$9,$AB24:$FO24) -> 180 | GT24: =SUMIF($AB$8:$FO$8,GT$9,$AB24:$FO24) -> 180 | GU24: =SUMIF($AB$8:$FO$8,GU$9,$AB24:$FO24) -> 180 | GV24: =SUMIF($AB$8:$FO$8,GV$9,$AB24:$FO24) -> 180 | GW24: =SUMIF($AB$8:$FO$8,GW$9,$AB24:$FO24) -> 45 | ... HE24: =SUMIF($AB$8:$FO$8,HE$9,$AB24:$FO24) -> 0
B25: Process | C25: RTR | D25: RTR | E25: RTR Fixed Assets Lead - Offshore | F25: India | G25: Consulting Services | H25: Enterprise Performance | I25: SAP | J25: India | K25: Package and Technology Enablement | L25: Package Functional Transformation | M25: L45 - Senior Consultant | N25: =_xlfn.CONCAT(C25,"-",D25) -> RTR-RTR | O25: =_xlfn.CONCAT(Y25,"-",Z25,"-",F25,"-",X25) -> Technology-Senior Consultant-India-Consulting | P25: =_xlfn.CONCAT(C25," - ",Y25) -> RTR - Technology | Q25: =AB25*SUM(AZ25:ET25) -> 268380 | R25: =AB25*SUM(BC25:BN25) -> 12780 | S25: =SUM(GP25:HN25) -> 1305 | T25: =SUM(AZ25:EZ25) -> 3780 | U25: =_xlfn.CONCAT(Y25," - ",Z25) -> Technology - Senior Consultant | V25: =VLOOKUP(O25,$B$187:$H$848,4,0) -> 3-5 years | W25: =IF(F25="US", "Onshore",IF(F25="India","Offshore", "Nearshore")) -> Offshore | X25: Consulting | Y25: Technology | Z25: Senior Consultant | AA25: =[1]Resourcing!QD29 -> 322.53493 | AB25: =IFERROR(VLOOKUP(O25,$B$187:$S$848,6,FALSE()),"combination not found") -> 71 | BK25: 45 | BL25: 45 | BM25: 45 | BN25: 45 | BO25: 45 | BP25: 45 | BQ25: 45 | BT25: 45 | BU25: 45 | BV25: 45 | BW25: 45 | BX25: 45 | BY25: 45 | BZ25: 45 | CA25: 45 | CB25: 45 | CC25: 45 | CD25: 45 | CE25: 45 | CF25: 45 | CG25: 45 | CH25: 45 | CI25: 45 | CJ25: 45 | CK25: 45 | CL25: 45 | CM25: 45 | CN25: 45 | CO25: 45 | CP25: 45 | CQ25: 45 | CR25: 45 | CS25: 45 | CT25: 45 | CU25: 45 | CV25: 45 | CW25: 45 | CX25: 45 | CY25: 45 | CZ25: 45 | DA25: 45 | DB25: 45 | DC25: 45 | DD25: 45 | DE25: 45 | DF25: 45 | DG25: 45 | DH25: 45 | DI25: 45 | DJ25: 45 | DK25: 45 | DL25: 45 | DM25: 45 | DN25: 45 | DO25: 45 | DP25: 45 | DQ25: 45 | DT25: 45 | DU25: 45 | DV25: 45 | DW25: 45 | DX25: 45 | DY25: 45 | DZ25: 45 | EA25: 45 | EB25: 45 | EC25: 45 | ED25: 45 | EE25: 45 | EF25: 45 | EG25: 45 | EH25: 45 | EI25: 45 | EJ25: 45 | EK25: 45 | EL25: 45 | EM25: 45 | EN25: 45 | EO25: 45 | EP25: 45 | EQ25: 45 | ER25: 45 | ES25: 45 | ET25: 45 | FQ25: =SUMIF($AC$11:$FP$11,FQ$12,$AC25:$FP25) -> #VALUE! | FR25: =SUMIF($AC$11:$FP$11,FR$12,$AC25:$FP25) -> #VALUE! | FS25: =SUMIF($AC$11:$FP$11,FS$12,$AC25:$FP25) -> #VALUE! | FT25: =SUMIF($AC$11:$FP$11,FT$12,$AC25:$FP25) -> #VALUE! | FU25: =SUMIF($AC$11:$FP$11,FU$12,$AC25:$FP25) -> #VALUE! | FV25: =SUMIF($AC$11:$FP$11,FV$12,$AC25:$FP25) -> #VALUE! | FW25: =SUMIF($AC$11:$FP$11,FW$12,$AC25:$FP25) -> #VALUE! | FX25: =SUMIF($AC$11:$FP$11,FX$12,$AC25:$FP25) -> #VALUE! | ... GO25: =SUMIF($AC$11:$FP$11,GO$12,$AC25:$FP25) -> #VALUE! | GP25: =SUMIF($AB$8:$FO$8,GP$9,$AB25:$FO25) -> 90 | GQ25: =SUMIF($AB$8:$FO$8,GQ$9,$AB25:$FO25) -> 180 | GR25: =SUMIF($AB$8:$FO$8,GR$9,$AB25:$FO25) -> 180 | GS25: =SUMIF($AB$8:$FO$8,GS$9,$AB25:$FO25) -> 180 | GT25: =SUMIF($AB$8:$FO$8,GT$9,$AB25:$FO25) -> 180 | GU25: =SUMIF($AB$8:$FO$8,GU$9,$AB25:$FO25) -> 180 | GV25: =SUMIF($AB$8:$FO$8,GV$9,$AB25:$FO25) -> 180 | GW25: =SUMIF($AB$8:$FO$8,GW$9,$AB25:$FO25) -> 135 | ... HE25: =SUMIF($AB$8:$FO$8,HE$9,$AB25:$FO25) -> 0
B26: Process | C26: RTR | D26: RTR | E26: RTR RAR Lead | F26: India | G26: Consulting Services | H26: Enterprise Performance | I26: SAP | J26: India | K26: Package and Technology Enablement | L26: Package Functional Transformation | M26: L45 - Senior Consultant | N26: =_xlfn.CONCAT(C26,"-",D26) -> RTR-RTR | O26: =_xlfn.CONCAT(Y26,"-",Z26,"-",F26,"-",X26) -> Technology-Senior Consultant-India-Consulting | P26: =_xlfn.CONCAT(C26," - ",Y26) -> RTR - Technology | Q26: =AB26*SUM(AZ26:ET26) -> 207675 | R26: =AB26*SUM(BC26:BN26) -> 0 | S26: =SUM(GP26:HN26) -> 630 | T26: =SUM(AZ26:EZ26) -> 2925 | U26: =_xlfn.CONCAT(Y26," - ",Z26) -> Technology - Senior Consultant | V26: =VLOOKUP(O26,$B$187:$H$848,4,0) -> 3-5 years | W26: =IF(F26="US", "Onshore",IF(F26="India","Offshore", "Nearshore")) -> Offshore | X26: Consulting | Y26: Technology | Z26: Senior Consultant | AA26: =[1]Resourcing!QD30 -> 85.409333 | AB26: =IFERROR(VLOOKUP(O26,$B$187:$S$848,6,FALSE()),"combination not found") -> 71 | BO26: 45 | BP26: 45 | BQ26: 45 | BT26: 45 | BU26: 45 | BV26: 45 | BW26: 45 | BX26: 45 | BY26: 45 | BZ26: 45 | CA26: 45 | CB26: 45 | CC26: 45 | CD26: 45 | CE26: 45 | CF26: 45 | CG26: 45 | CH26: 45 | CI26: 45 | CJ26: 45 | CK26: 45 | CL26: 45 | CM26: 45 | CN26: 45 | CO26: 45 | CP26: 45 | CQ26: 45 | CR26: 45 | CS26: 45 | CT26: 45 | CU26: 45 | CV26: 45 | CW26: 45 | CX26: 45 | CY26: 45 | CZ26: 45 | DA26: 45 | DB26: 45 | DC26: 45 | DD26: 45 | DE26: 45 | DF26: 45 | DG26: 45 | DH26: 45 | DI26: 45 | DJ26: 45 | DK26: 45 | DL26: 45 | DM26: 45 | DN26: 45 | DO26: 45 | DP26: 45 | DQ26: 45 | DT26: 45 | DU26: 45 | DV26: 45 | DW26: 45 | DX26: 45 | DY26: 45 | DZ26: 45 | EA26: 45 | EB26: 45 | EC26: 45 | ED26: 45 | EE26: 45 | FQ26: =SUMIF($AC$11:$FP$11,FQ$12,$AC26:$FP26) -> #VALUE! | FR26: =SUMIF($AC$11:$FP$11,FR$12,$AC26:$FP26) -> #VALUE! | FS26: =SUMIF($AC$11:$FP$11,FS$12,$AC26:$FP26) -> #VALUE! | FT26: =SUMIF($AC$11:$FP$11,FT$12,$AC26:$FP26) -> #VALUE! | FU26: =SUMIF($AC$11:$FP$11,FU$12,$AC26:$FP26) -> #VALUE! | FV26: =SUMIF($AC$11:$FP$11,FV$12,$AC26:$FP26) -> #VALUE! | FW26: =SUMIF($AC$11:$FP$11,FW$12,$AC26:$FP26) -> #VALUE! | FX26: =SUMIF($AC$11:$FP$11,FX$12,$AC26:$FP26) -> #VALUE! | ... GO26: =SUMIF($AC$11:$FP$11,GO$12,$AC26:$FP26) -> #VALUE! | GP26: =SUMIF($AB$8:$FO$8,GP$9,$AB26:$FO26) -> 90 | GQ26: =SUMIF($AB$8:$FO$8,GQ$9,$AB26:$FO26) -> 180 | GR26: =SUMIF($AB$8:$FO$8,GR$9,$AB26:$FO26) -> 180 | GS26: =SUMIF($AB$8:$FO$8,GS$9,$AB26:$FO26) -> 180 | GT26: =SUMIF($AB$8:$FO$8,GT$9,$AB26:$FO26) -> 0 | GU26: =SUMIF($AB$8:$FO$8,GU$9,$AB26:$FO26) -> 0 | GV26: =SUMIF($AB$8:$FO$8,GV$9,$AB26:$FO26) -> 0 | GW26: =SUMIF($AB$8:$FO$8,GW$9,$AB26:$FO26) -> 0 | ... HE26: =SUMIF($AB$8:$FO$8,HE$9,$AB26:$FO26) -> 0
B27: Process | C27: RTR | D27: RTR | E27: RTR TRM Lead | F27: India | G27: Consulting Services | H27: Enterprise Performance | I27: SAP | J27: India | K27: Package and Technology Enablement | L27: Package Functional Transformation | M27: L45 - Senior Consultant | N27: =_xlfn.CONCAT(C27,"-",D27) -> RTR-RTR | O27: =_xlfn.CONCAT(Y27,"-",Z27,"-",F27,"-",X27) -> Technology-Senior Consultant-India-Consulting | P27: =_xlfn.CONCAT(C27," - ",Y27) -> RTR - Technology | Q27: =AB27*SUM(AZ27:ET27) -> 249210 | R27: =AB27*SUM(BC27:BN27) -> 0 | S27: =SUM(GP27:HN27) -> 1215 | T27: =SUM(AZ27:EZ27) -> 3510 | U27: =_xlfn.CONCAT(Y27," - ",Z27) -> Technology - Senior Consultant | V27: =VLOOKUP(O27,$B$187:$H$848,4,0) -> 3-5 years | W27: =IF(F27="US", "Onshore",IF(F27="India","Offshore", "Nearshore")) -> Offshore | X27: Consulting | Y27: Technology | Z27: Senior Consultant | AA27: =[1]Resourcing!QD31 -> 62.688205 | AB27: =IFERROR(VLOOKUP(O27,$B$187:$S$848,6,FALSE()),"combination not found") -> 71 | BO27: 45 | BP27: 45 | BQ27: 45 | BT27: 45 | BU27: 45 | BV27: 45 | BW27: 45 | BX27: 45 | BY27: 45 | BZ27: 45 | CA27: 45 | CB27: 45 | CC27: 45 | CD27: 45 | CE27: 45 | CF27: 45 | CG27: 45 | CH27: 45 | CI27: 45 | CJ27: 45 | CK27: 45 | CL27: 45 | CM27: 45 | CN27: 45 | CO27: 45 | CP27: 45 | CQ27: 45 | CR27: 45 | CS27: 45 | CT27: 45 | CU27: 45 | CV27: 45 | CW27: 45 | CX27: 45 | CY27: 45 | CZ27: 45 | DA27: 45 | DB27: 45 | DC27: 45 | DD27: 45 | DE27: 45 | DF27: 45 | DG27: 45 | DH27: 45 | DI27: 45 | DJ27: 45 | DK27: 45 | DL27: 45 | DM27: 45 | DN27: 45 | DO27: 45 | DP27: 45 | DQ27: 45 | DT27: 45 | DU27: 45 | DV27: 45 | DW27: 45 | DX27: 45 | DY27: 45 | DZ27: 45 | EA27: 45 | EB27: 45 | EC27: 45 | ED27: 45 | EE27: 45 | EF27: 45 | EG27: 45 | EH27: 45 | EI27: 45 | EJ27: 45 | EK27: 45 | EL27: 45 | EM27: 45 | EN27: 45 | EO27: 45 | EP27: 45 | EQ27: 45 | ER27: 45 | FQ27: =SUMIF($AC$11:$FP$11,FQ$12,$AC27:$FP27) -> #VALUE! | FR27: =SUMIF($AC$11:$FP$11,FR$12,$AC27:$FP27) -> #VALUE! | FS27: =SUMIF($AC$11:$FP$11,FS$12,$AC27:$FP27) -> #VALUE! | FT27: =SUMIF($AC$11:$FP$11,FT$12,$AC27:$FP27) -> #VALUE! | FU27: =SUMIF($AC$11:$FP$11,FU$12,$AC27:$FP27) -> #VALUE! | FV27: =SUMIF($AC$11:$FP$11,FV$12,$AC27:$FP27) -> #VALUE! | FW27: =SUMIF($AC$11:$FP$11,FW$12,$AC27:$FP27) -> #VALUE! | FX27: =SUMIF($AC$11:$FP$11,FX$12,$AC27:$FP27) -> #VALUE! | ... GO27: =SUMIF($AC$11:$FP$11,GO$12,$AC27:$FP27) -> #VALUE! | GP27: =SUMIF($AB$8:$FO$8,GP$9,$AB27:$FO27) -> 90 | GQ27: =SUMIF($AB$8:$FO$8,GQ$9,$AB27:$FO27) -> 180 | GR27: =SUMIF($AB$8:$FO$8,GR$9,$AB27:$FO27) -> 180 | GS27: =SUMIF($AB$8:$FO$8,GS$9,$AB27:$FO27) -> 180 | GT27: =SUMIF($AB$8:$FO$8,GT$9,$AB27:$FO27) -> 180 | GU27: =SUMIF($AB$8:$FO$8,GU$9,$AB27:$FO27) -> 180 | GV27: =SUMIF($AB$8:$FO$8,GV$9,$AB27:$FO27) -> 180 | GW27: =SUMIF($AB$8:$FO$8,GW$9,$AB27:$FO27) -> 45 | ... HE27: =SUMIF($AB$8:$FO$8,HE$9,$AB27:$FO27) -> 0
B28: Process | C28: RTR | D28: RTR | E28: RTR CO Support - Offshore | F28: India | G28: Consulting Services | H28: Enterprise Performance | I28: SAP | J28: India | K28: Package and Technology Enablement | L28: Package Functional Transformation | M28: L35 - Consultant | N28: =_xlfn.CONCAT(C28,"-",D28) -> RTR-RTR | O28: =_xlfn.CONCAT(Y28,"-",Z28,"-",F28,"-",X28) -> Technology-Consultant-India-Consulting | P28: =_xlfn.CONCAT(C28," - ",Y28) -> RTR - Technology | Q28: =AB28*SUM(AZ28:ET28) -> 243000 | R28: =AB28*SUM(BC28:BN28) -> 27000 | S28: =SUM(GP28:HN28) -> 1305 | T28: =SUM(AZ28:EZ28) -> 4050 | U28: =_xlfn.CONCAT(Y28," - ",Z28) -> Technology - Consultant | V28: =VLOOKUP(O28,$B$187:$H$848,4,0) -> 1-3 years | W28: =IF(F28="US", "Onshore",IF(F28="India","Offshore", "Nearshore")) -> Offshore | X28: Consulting | Y28: Technology | Z28: Consultant | AA28: =[1]Resourcing!QD32 -> 62.672857 | AB28: =IFERROR(VLOOKUP(O28,$B$187:$S$848,6,FALSE()),"combination not found") -> 60 | BE28: 45 | BF28: 45 | BG28: 45 | BH28: 45 | BI28: 45 | BJ28: 45 | BK28: 45 | BL28: 45 | BM28: 45 | BN28: 45 | BO28: 45 | BP28: 45 | BQ28: 45 | BT28: 45 | BU28: 45 | BV28: 45 | BW28: 45 | BX28: 45 | BY28: 45 | BZ28: 45 | CA28: 45 | CB28: 45 | CC28: 45 | CD28: 45 | CE28: 45 | CF28: 45 | CG28: 45 | CH28: 45 | CI28: 45 | CJ28: 45 | CK28: 45 | CL28: 45 | CM28: 45 | CN28: 45 | CO28: 45 | CP28: 45 | CQ28: 45 | CR28: 45 | CS28: 45 | CT28: 45 | CU28: 45 | CV28: 45 | CW28: 45 | CX28: 45 | CY28: 45 | CZ28: 45 | DA28: 45 | DB28: 45 | DC28: 45 | DD28: 45 | DE28: 45 | DF28: 45 | DG28: 45 | DH28: 45 | DI28: 45 | DJ28: 45 | DK28: 45 | DL28: 45 | DM28: 45 | DN28: 45 | DO28: 45 | DP28: 45 | DQ28: 45 | DT28: 45 | DU28: 45 | DV28: 45 | DW28: 45 | DX28: 45 | DY28: 45 | DZ28: 45 | EA28: 45 | EB28: 45 | EC28: 45 | ED28: 45 | EE28: 45 | EF28: 45 | EG28: 45 | EH28: 45 | EI28: 45 | EJ28: 45 | EK28: 45 | EL28: 45 | EM28: 45 | EN28: 45 | EO28: 45 | EP28: 45 | EQ28: 45 | ER28: 45 | ES28: 45 | ET28: 45 | FQ28: =SUMIF($AC$11:$FP$11,FQ$12,$AC28:$FP28) -> #VALUE! | FR28: =SUMIF($AC$11:$FP$11,FR$12,$AC28:$FP28) -> #VALUE! | FS28: =SUMIF($AC$11:$FP$11,FS$12,$AC28:$FP28) -> #VALUE! | FT28: =SUMIF($AC$11:$FP$11,FT$12,$AC28:$FP28) -> #VALUE! | FU28: =SUMIF($AC$11:$FP$11,FU$12,$AC28:$FP28) -> #VALUE! | FV28: =SUMIF($AC$11:$FP$11,FV$12,$AC28:$FP28) -> #VALUE! | FW28: =SUMIF($AC$11:$FP$11,FW$12,$AC28:$FP28) -> #VALUE! | FX28: =SUMIF($AC$11:$FP$11,FX$12,$AC28:$FP28) -> #VALUE! | ... GO28: =SUMIF($AC$11:$FP$11,GO$12,$AC28:$FP28) -> #VALUE! | GP28: =SUMIF($AB$8:$FO$8,GP$9,$AB28:$FO28) -> 90 | GQ28: =SUMIF($AB$8:$FO$8,GQ$9,$AB28:$FO28) -> 180 | GR28: =SUMIF($AB$8:$FO$8,GR$9,$AB28:$FO28) -> 180 | GS28: =SUMIF($AB$8:$FO$8,GS$9,$AB28:$FO28) -> 180 | GT28: =SUMIF($AB$8:$FO$8,GT$9,$AB28:$FO28) -> 180 | GU28: =SUMIF($AB$8:$FO$8,GU$9,$AB28:$FO28) -> 180 | GV28: =SUMIF($AB$8:$FO$8,GV$9,$AB28:$FO28) -> 180 | GW28: =SUMIF($AB$8:$FO$8,GW$9,$AB28:$FO28) -> 135 | ... HE28: =SUMIF($AB$8:$FO$8,HE$9,$AB28:$FO28) -> 0
B29: Process | C29: RTR | D29: RTR | E29: RTR Intercompany/Close Support | F29: India | G29: Consulting Services | H29: Enterprise Performance | I29: SAP | J29: India | K29: Package and Technology Enablement | L29: Package Functional Transformation | M29: L35 - Consultant | N29: =_xlfn.CONCAT(C29,"-",D29) -> RTR-RTR | O29: =_xlfn.CONCAT(Y29,"-",Z29,"-",F29,"-",X29) -> Technology-Consultant-India-Consulting | P29: =_xlfn.CONCAT(C29," - ",Y29) -> RTR - Technology | Q29: =AB29*SUM(AZ29:ET29) -> 216000 | R29: =AB29*SUM(BC29:BN29) -> 0 | S29: =SUM(GP29:HN29) -> 1305 | T29: =SUM(AZ29:EZ29) -> 3600 | U29: =_xlfn.CONCAT(Y29," - ",Z29) -> Technology - Consultant | V29: =VLOOKUP(O29,$B$187:$H$848,4,0) -> 1-3 years | W29: =IF(F29="US", "Onshore",IF(F29="India","Offshore", "Nearshore")) -> Offshore | X29: Consulting | Y29: Technology | Z29: Consultant | AA29: =[1]Resourcing!QD33 -> 62.270769 | AB29: =IFERROR(VLOOKUP(O29,$B$187:$S$848,6,FALSE()),"combination not found") -> 60 | BO29: 45 | BP29: 45 | BQ29: 45 | BT29: 45 | BU29: 45 | BV29: 45 | BW29: 45 | BX29: 45 | BY29: 45 | BZ29: 45 | CA29: 45 | CB29: 45 | CC29: 45 | CD29: 45 | CE29: 45 | CF29: 45 | CG29: 45 | CH29: 45 | CI29: 45 | CJ29: 45 | CK29: 45 | CL29: 45 | CM29: 45 | CN29: 45 | CO29: 45 | CP29: 45 | CQ29: 45 | CR29: 45 | CS29: 45 | CT29: 45 | CU29: 45 | CV29: 45 | CW29: 45 | CX29: 45 | CY29: 45 | CZ29: 45 | DA29: 45 | DB29: 45 | DC29: 45 | DD29: 45 | DE29: 45 | DF29: 45 | DG29: 45 | DH29: 45 | DI29: 45 | DJ29: 45 | DK29: 45 | DL29: 45 | DM29: 45 | DN29: 45 | DO29: 45 | DP29: 45 | DQ29: 45 | DT29: 45 | DU29: 45 | DV29: 45 | DW29: 45 | DX29: 45 | DY29: 45 | DZ29: 45 | EA29: 45 | EB29: 45 | EC29: 45 | ED29: 45 | EE29: 45 | EF29: 45 | EG29: 45 | EH29: 45 | EI29: 45 | EJ29: 45 | EK29: 45 | EL29: 45 | EM29: 45 | EN29: 45 | EO29: 45 | EP29: 45 | EQ29: 45 | ER29: 45 | ES29: 45 | ET29: 45 | FQ29: =SUMIF($AC$11:$FP$11,FQ$12,$AC29:$FP29) -> #VALUE! | FR29: =SUMIF($AC$11:$FP$11,FR$12,$AC29:$FP29) -> #VALUE! | FS29: =SUMIF($AC$11:$FP$11,FS$12,$AC29:$FP29) -> #VALUE! | FT29: =SUMIF($AC$11:$FP$11,FT$12,$AC29:$FP29) -> #VALUE! | FU29: =SUMIF($AC$11:$FP$11,FU$12,$AC29:$FP29) -> #VALUE! | FV29: =SUMIF($AC$11:$FP$11,FV$12,$AC29:$FP29) -> #VALUE! | FW29: =SUMIF($AC$11:$FP$11,FW$12,$AC29:$FP29) -> #VALUE! | FX29: =SUMIF($AC$11:$FP$11,FX$12,$AC29:$FP29) -> #VALUE! | ... GO29: =SUMIF($AC$11:$FP$11,GO$12,$AC29:$FP29) -> #VALUE! | GP29: =SUMIF($AB$8:$FO$8,GP$9,$AB29:$FO29) -> 90 | GQ29: =SUMIF($AB$8:$FO$8,GQ$9,$AB29:$FO29) -> 180 | GR29: =SUMIF($AB$8:$FO$8,GR$9,$AB29:$FO29) -> 180 | GS29: =SUMIF($AB$8:$FO$8,GS$9,$AB29:$FO29) -> 180 | GT29: =SUMIF($AB$8:$FO$8,GT$9,$AB29:$FO29) -> 180 | GU29: =SUMIF($AB$8:$FO$8,GU$9,$AB29:$FO29) -> 180 | GV29: =SUMIF($AB$8:$FO$8,GV$9,$AB29:$FO29) -> 180 | GW29: =SUMIF($AB$8:$FO$8,GW$9,$AB29:$FO29) -> 135 | ... HE29: =SUMIF($AB$8:$FO$8,HE$9,$AB29:$FO29) -> 0
B30: Process | C30: RTR | D30: RTR | E30: RTR GL Support | F30: India | G30: Consulting Services | H30: Enterprise Performance | I30: SAP | J30: India | K30: Package and Technology Enablement | L30: Package Functional Transformation | M30: L35 - Consultant | N30: =_xlfn.CONCAT(C30,"-",D30) -> RTR-RTR | O30: =_xlfn.CONCAT(Y30,"-",Z30,"-",F30,"-",X30) -> Technology-Analyst-India-Consulting | P30: =_xlfn.CONCAT(C30," - ",Y30) -> RTR - Technology | Q30: =AB30*SUM(AZ30:ET30) -> 166320 | R30: =AB30*SUM(BC30:BN30) -> 0 | S30: =SUM(GP30:HN30) -> 1305 | T30: =SUM(AZ30:EZ30) -> 3465 | U30: =_xlfn.CONCAT(Y30," - ",Z30) -> Technology - Analyst | V30: =VLOOKUP(O30,$B$187:$H$848,4,0) -> 0-1 years | W30: =IF(F30="US", "Onshore",IF(F30="India","Offshore", "Nearshore")) -> Offshore | X30: Consulting | Y30: Technology | Z30: Analyst | AA30: =[1]Resourcing!QD34 -> 62.688205 | AB30: =IFERROR(VLOOKUP(O30,$B$187:$S$848,6,FALSE()),"combination not found") -> 48 | BT30: 45 | BU30: 45 | BV30: 45 | BW30: 45 | BX30: 45 | BY30: 45 | BZ30: 45 | CA30: 45 | CB30: 45 | CC30: 45 | CD30: 45 | CE30: 45 | CF30: 45 | CG30: 45 | CH30: 45 | CI30: 45 | CJ30: 45 | CK30: 45 | CL30: 45 | CM30: 45 | CN30: 45 | CO30: 45 | CP30: 45 | CQ30: 45 | CR30: 45 | CS30: 45 | CT30: 45 | CU30: 45 | CV30: 45 | CW30: 45 | CX30: 45 | CY30: 45 | CZ30: 45 | DA30: 45 | DB30: 45 | DC30: 45 | DD30: 45 | DE30: 45 | DF30: 45 | DG30: 45 | DH30: 45 | DI30: 45 | DJ30: 45 | DK30: 45 | DL30: 45 | DM30: 45 | DN30: 45 | DO30: 45 | DP30: 45 | DQ30: 45 | DT30: 45 | DU30: 45 | DV30: 45 | DW30: 45 | DX30: 45 | DY30: 45 | DZ30: 45 | EA30: 45 | EB30: 45 | EC30: 45 | ED30: 45 | EE30: 45 | EF30: 45 | EG30: 45 | EH30: 45 | EI30: 45 | EJ30: 45 | EK30: 45 | EL30: 45 | EM30: 45 | EN30: 45 | EO30: 45 | EP30: 45 | EQ30: 45 | ER30: 45 | ES30: 45 | ET30: 45 | FQ30: =SUMIF($AC$11:$FP$11,FQ$12,$AC30:$FP30) -> #VALUE! | FR30: =SUMIF($AC$11:$FP$11,FR$12,$AC30:$FP30) -> #VALUE! | FS30: =SUMIF($AC$11:$FP$11,FS$12,$AC30:$FP30) -> #VALUE! | FT30: =SUMIF($AC$11:$FP$11,FT$12,$AC30:$FP30) -> #VALUE! | FU30: =SUMIF($AC$11:$FP$11,FU$12,$AC30:$FP30) -> #VALUE! | FV30: =SUMIF($AC$11:$FP$11,FV$12,$AC30:$FP30) -> #VALUE! | FW30: =SUMIF($AC$11:$FP$11,FW$12,$AC30:$FP30) -> #VALUE! | FX30: =SUMIF($AC$11:$FP$11,FX$12,$AC30:$FP30) -> #VALUE! | ... GO30: =SUMIF($AC$11:$FP$11,GO$12,$AC30:$FP30) -> #VALUE! | GP30: =SUMIF($AB$8:$FO$8,GP$9,$AB30:$FO30) -> 90 | GQ30: =SUMIF($AB$8:$FO$8,GQ$9,$AB30:$FO30) -> 180 | GR30: =SUMIF($AB$8:$FO$8,GR$9,$AB30:$FO30) -> 180 | GS30: =SUMIF($AB$8:$FO$8,GS$9,$AB30:$FO30) -> 180 | GT30: =SUMIF($AB$8:$FO$8,GT$9,$AB30:$FO30) -> 180 | GU30: =SUMIF($AB$8:$FO$8,GU$9,$AB30:$FO30) -> 180 | GV30: =SUMIF($AB$8:$FO$8,GV$9,$AB30:$FO30) -> 180 | GW30: =SUMIF($AB$8:$FO$8,GW$9,$AB30:$FO30) -> 135 | ... HE30: =SUMIF($AB$8:$FO$8,HE$9,$AB30:$FO30) -> 0
B31: Process | C31: RTR | D31: RTR | E31: RTR RAR Support | F31: India | G31: Consulting Services | H31: Enterprise Performance | I31: SAP | J31: India | K31: Package and Technology Enablement | L31: Package Functional Transformation | M31: L35 - Consultant | N31: =_xlfn.CONCAT(C31,"-",D31) -> RTR-RTR | O31: =_xlfn.CONCAT(Y31,"-",Z31,"-",F31,"-",X31) -> Technology-Consultant-India-Consulting | P31: =_xlfn.CONCAT(C31," - ",Y31) -> RTR - Technology | Q31: =AB31*SUM(AZ31:ET31) -> 216000 | R31: =AB31*SUM(BC31:BN31) -> 0 | S31: =SUM(GP31:HN31) -> 1305 | T31: =SUM(AZ31:EZ31) -> 3600 | U31: =_xlfn.CONCAT(Y31," - ",Z31) -> Technology - Consultant | V31: =VLOOKUP(O31,$B$187:$H$848,4,0) -> 1-3 years | W31: =IF(F31="US", "Onshore",IF(F31="India","Offshore", "Nearshore")) -> Offshore | X31: Consulting | Y31: Technology | Z31: Consultant | AA31: =[1]Resourcing!QD35 -> 53.12 | AB31: =IFERROR(VLOOKUP(O31,$B$187:$S$848,6,FALSE()),"combination not found") -> 60 | BO31: 45 | BP31: 45 | BQ31: 45 | BT31: 45 | BU31: 45 | BV31: 45 | BW31: 45 | BX31: 45 | BY31: 45 | BZ31: 45 | CA31: 45 | CB31: 45 | CC31: 45 | CD31: 45 | CE31: 45 | CF31: 45 | CG31: 45 | CH31: 45 | CI31: 45 | CJ31: 45 | CK31: 45 | CL31: 45 | CM31: 45 | CN31: 45 | CO31: 45 | CP31: 45 | CQ31: 45 | CR31: 45 | CS31: 45 | CT31: 45 | CU31: 45 | CV31: 45 | CW31: 45 | CX31: 45 | CY31: 45 | CZ31: 45 | DA31: 45 | DB31: 45 | DC31: 45 | DD31: 45 | DE31: 45 | DF31: 45 | DG31: 45 | DH31: 45 | DI31: 45 | DJ31: 45 | DK31: 45 | DL31: 45 | DM31: 45 | DN31: 45 | DO31: 45 | DP31: 45 | DQ31: 45 | DT31: 45 | DU31: 45 | DV31: 45 | DW31: 45 | DX31: 45 | DY31: 45 | DZ31: 45 | EA31: 45 | EB31: 45 | EC31: 45 | ED31: 45 | EE31: 45 | EF31: 45 | EG31: 45 | EH31: 45 | EI31: 45 | EJ31: 45 | EK31: 45 | EL31: 45 | EM31: 45 | EN31: 45 | EO31: 45 | EP31: 45 | EQ31: 45 | ER31: 45 | ES31: 45 | ET31: 45 | FQ31: =SUMIF($AC$11:$FP$11,FQ$12,$AC31:$FP31) -> #VALUE! | FR31: =SUMIF($AC$11:$FP$11,FR$12,$AC31:$FP31) -> #VALUE! | FS31: =SUMIF($AC$11:$FP$11,FS$12,$AC31:$FP31) -> #VALUE! | FT31: =SUMIF($AC$11:$FP$11,FT$12,$AC31:$FP31) -> #VALUE! | FU31: =SUMIF($AC$11:$FP$11,FU$12,$AC31:$FP31) -> #VALUE! | FV31: =SUMIF($AC$11:$FP$11,FV$12,$AC31:$FP31) -> #VALUE! | FW31: =SUMIF($AC$11:$FP$11,FW$12,$AC31:$FP31) -> #VALUE! | FX31: =SUMIF($AC$11:$FP$11,FX$12,$AC31:$FP31) -> #VALUE! | ... GO31: =SUMIF($AC$11:$FP$11,GO$12,$AC31:$FP31) -> #VALUE! | GP31: =SUMIF($AB$8:$FO$8,GP$9,$AB31:$FO31) -> 90 | GQ31: =SUMIF($AB$8:$FO$8,GQ$9,$AB31:$FO31) -> 180 | GR31: =SUMIF($AB$8:$FO$8,GR$9,$AB31:$FO31) -> 180 | GS31: =SUMIF($AB$8:$FO$8,GS$9,$AB31:$FO31) -> 180 | GT31: =SUMIF($AB$8:$FO$8,GT$9,$AB31:$FO31) -> 180 | GU31: =SUMIF($AB$8:$FO$8,GU$9,$AB31:$FO31) -> 180 | GV31: =SUMIF($AB$8:$FO$8,GV$9,$AB31:$FO31) -> 180 | GW31: =SUMIF($AB$8:$FO$8,GW$9,$AB31:$FO31) -> 135 | ... HE31: =SUMIF($AB$8:$FO$8,HE$9,$AB31:$FO31) -> 0
B32: Process | C32: RTR | D32: RTR | E32: RTR TRM Support | F32: India | G32: Consulting Services | H32: Enterprise Performance | I32: SAP | J32: India | K32: Package and Technology Enablement | L32: Package Functional Transformation | M32: L35 - Consultant | N32: =_xlfn.CONCAT(C32,"-",D32) -> RTR-RTR | O32: =_xlfn.CONCAT(Y32,"-",Z32,"-",F32,"-",X32) -> Technology-Consultant-India-Consulting | P32: =_xlfn.CONCAT(C32," - ",Y32) -> RTR - Technology | Q32: =AB32*SUM(AZ32:ET32) -> 216000 | R32: =AB32*SUM(BC32:BN32) -> 0 | S32: =SUM(GP32:HN32) -> 1305 | T32: =SUM(AZ32:EZ32) -> 3600 | U32: =_xlfn.CONCAT(Y32," - ",Z32) -> Technology - Consultant | V32: =VLOOKUP(O32,$B$187:$H$848,4,0) -> 1-3 years | W32: =IF(F32="US", "Onshore",IF(F32="India","Offshore", "Nearshore")) -> Offshore | X32: Consulting | Y32: Technology | Z32: Consultant | AA32: =[1]Resourcing!QD36 -> 53.385 | AB32: =IFERROR(VLOOKUP(O32,$B$187:$S$848,6,FALSE()),"combination not found") -> 60 | BO32: 45 | BP32: 45 | BQ32: 45 | BT32: 45 | BU32: 45 | BV32: 45 | BW32: 45 | BX32: 45 | BY32: 45 | BZ32: 45 | CA32: 45 | CB32: 45 | CC32: 45 | CD32: 45 | CE32: 45 | CF32: 45 | CG32: 45 | CH32: 45 | CI32: 45 | CJ32: 45 | CK32: 45 | CL32: 45 | CM32: 45 | CN32: 45 | CO32: 45 | CP32: 45 | CQ32: 45 | CR32: 45 | CS32: 45 | CT32: 45 | CU32: 45 | CV32: 45 | CW32: 45 | CX32: 45 | CY32: 45 | CZ32: 45 | DA32: 45 | DB32: 45 | DC32: 45 | DD32: 45 | DE32: 45 | DF32: 45 | DG32: 45 | DH32: 45 | DI32: 45 | DJ32: 45 | DK32: 45 | DL32: 45 | DM32: 45 | DN32: 45 | DO32: 45 | DP32: 45 | DQ32: 45 | DT32: 45 | DU32: 45 | DV32: 45 | DW32: 45 | DX32: 45 | DY32: 45 | DZ32: 45 | EA32: 45 | EB32: 45 | EC32: 45 | ED32: 45 | EE32: 45 | EF32: 45 | EG32: 45 | EH32: 45 | EI32: 45 | EJ32: 45 | EK32: 45 | EL32: 45 | EM32: 45 | EN32: 45 | EO32: 45 | EP32: 45 | EQ32: 45 | ER32: 45 | ES32: 45 | ET32: 45 | FQ32: =SUMIF($AC$11:$FP$11,FQ$12,$AC32:$FP32) -> #VALUE! | FR32: =SUMIF($AC$11:$FP$11,FR$12,$AC32:$FP32) -> #VALUE! | FS32: =SUMIF($AC$11:$FP$11,FS$12,$AC32:$FP32) -> #VALUE! | FT32: =SUMIF($AC$11:$FP$11,FT$12,$AC32:$FP32) -> #VALUE! | FU32: =SUMIF($AC$11:$FP$11,FU$12,$AC32:$FP32) -> #VALUE! | FV32: =SUMIF($AC$11:$FP$11,FV$12,$AC32:$FP32) -> #VALUE! | FW32: =SUMIF($AC$11:$FP$11,FW$12,$AC32:$FP32) -> #VALUE! | FX32: =SUMIF($AC$11:$FP$11,FX$12,$AC32:$FP32) -> #VALUE! | ... GO32: =SUMIF($AC$11:$FP$11,GO$12,$AC32:$FP32) -> #VALUE! | GP32: =SUMIF($AB$8:$FO$8,GP$9,$AB32:$FO32) -> 90 | GQ32: =SUMIF($AB$8:$FO$8,GQ$9,$AB32:$FO32) -> 180 | GR32: =SUMIF($AB$8:$FO$8,GR$9,$AB32:$FO32) -> 180 | GS32: =SUMIF($AB$8:$FO$8,GS$9,$AB32:$FO32) -> 180 | GT32: =SUMIF($AB$8:$FO$8,GT$9,$AB32:$FO32) -> 180 | GU32: =SUMIF($AB$8:$FO$8,GU$9,$AB32:$FO32) -> 180 | GV32: =SUMIF($AB$8:$FO$8,GV$9,$AB32:$FO32) -> 180 | GW32: =SUMIF($AB$8:$FO$8,GW$9,$AB32:$FO32) -> 135 | ... HE32: =SUMIF($AB$8:$FO$8,HE$9,$AB32:$FO32) -> 0
B33: Process | C33: RTR | D33: RTR | E33: RTR EBS Support | F33: India | G33: Consulting Services | H33: Enterprise Performance | I33: SAP | J33: India | K33: Package and Technology Enablement | L33: Package Functional Transformation | M33: L25 - Analyst | N33: =_xlfn.CONCAT(C33,"-",D33) -> RTR-RTR | O33: =_xlfn.CONCAT(Y33,"-",Z33,"-",F33,"-",X33) -> Technology-Analyst-India-Consulting | P33: =_xlfn.CONCAT(C33," - ",Y33) -> RTR - Technology | Q33: =AB33*SUM(AZ33:ET33) -> 153360 | R33: =AB33*SUM(BC33:BN33) -> 0 | S33: =SUM(GP33:HN33) -> 1305 | T33: =SUM(AZ33:EZ33) -> 3195 | U33: =_xlfn.CONCAT(Y33," - ",Z33) -> Technology - Analyst | V33: =VLOOKUP(O33,$B$187:$H$848,4,0) -> 0-1 years | W33: =IF(F33="US", "Onshore",IF(F33="India","Offshore", "Nearshore")) -> Offshore | X33: Consulting | Y33: Technology | Z33: Analyst | AA33: =[1]Resourcing!QD37 -> 53.477922 | AB33: =IFERROR(VLOOKUP(O33,$B$187:$S$848,6,FALSE()),"combination not found") -> 48 | BZ33: 45 | CA33: 45 | CB33: 45 | CC33: 45 | CD33: 45 | CE33: 45 | CF33: 45 | CG33: 45 | CH33: 45 | CI33: 45 | CJ33: 45 | CK33: 45 | CL33: 45 | CM33: 45 | CN33: 45 | CO33: 45 | CP33: 45 | CQ33: 45 | CR33: 45 | CS33: 45 | CT33: 45 | CU33: 45 | CV33: 45 | CW33: 45 | CX33: 45 | CY33: 45 | CZ33: 45 | DA33: 45 | DB33: 45 | DC33: 45 | DD33: 45 | DE33: 45 | DF33: 45 | DG33: 45 | DH33: 45 | DI33: 45 | DJ33: 45 | DK33: 45 | DL33: 45 | DM33: 45 | DN33: 45 | DO33: 45 | DP33: 45 | DQ33: 45 | DT33: 45 | DU33: 45 | DV33: 45 | DW33: 45 | DX33: 45 | DY33: 45 | DZ33: 45 | EA33: 45 | EB33: 45 | EC33: 45 | ED33: 45 | EE33: 45 | EF33: 45 | EG33: 45 | EH33: 45 | EI33: 45 | EJ33: 45 | EK33: 45 | EL33: 45 | EM33: 45 | EN33: 45 | EO33: 45 | EP33: 45 | EQ33: 45 | ER33: 45 | ES33: 45 | ET33: 45 | FQ33: =SUMIF($AC$11:$FP$11,FQ$12,$AC33:$FP33) -> #VALUE! | FR33: =SUMIF($AC$11:$FP$11,FR$12,$AC33:$FP33) -> #VALUE! | FS33: =SUMIF($AC$11:$FP$11,FS$12,$AC33:$FP33) -> #VALUE! | FT33: =SUMIF($AC$11:$FP$11,FT$12,$AC33:$FP33) -> #VALUE! | FU33: =SUMIF($AC$11:$FP$11,FU$12,$AC33:$FP33) -> #VALUE! | FV33: =SUMIF($AC$11:$FP$11,FV$12,$AC33:$FP33) -> #VALUE! | FW33: =SUMIF($AC$11:$FP$11,FW$12,$AC33:$FP33) -> #VALUE! | FX33: =SUMIF($AC$11:$FP$11,FX$12,$AC33:$FP33) -> #VALUE! | ... GO33: =SUMIF($AC$11:$FP$11,GO$12,$AC33:$FP33) -> #VALUE! | GP33: =SUMIF($AB$8:$FO$8,GP$9,$AB33:$FO33) -> 90 | GQ33: =SUMIF($AB$8:$FO$8,GQ$9,$AB33:$FO33) -> 180 | GR33: =SUMIF($AB$8:$FO$8,GR$9,$AB33:$FO33) -> 180 | GS33: =SUMIF($AB$8:$FO$8,GS$9,$AB33:$FO33) -> 180 | GT33: =SUMIF($AB$8:$FO$8,GT$9,$AB33:$FO33) -> 180 | GU33: =SUMIF($AB$8:$FO$8,GU$9,$AB33:$FO33) -> 180 | GV33: =SUMIF($AB$8:$FO$8,GV$9,$AB33:$FO33) -> 180 | GW33: =SUMIF($AB$8:$FO$8,GW$9,$AB33:$FO33) -> 135 | ... HE33: =SUMIF($AB$8:$FO$8,HE$9,$AB33:$FO33) -> 0
B34: Process | C34: RTR | D34: RTR | E34: RTR FA Support | F34: India | G34: Consulting Services | H34: Enterprise Performance | I34: SAP | J34: India | K34: Package and Technology Enablement | L34: Package Functional Transformation | M34: L25 - Analyst | N34: =_xlfn.CONCAT(C34,"-",D34) -> RTR-RTR | O34: =_xlfn.CONCAT(Y34,"-",Z34,"-",F34,"-",X34) -> Technology-Analyst-India-Consulting | P34: =_xlfn.CONCAT(C34," - ",Y34) -> RTR - Technology | Q34: =AB34*SUM(AZ34:ET34) -> 144720 | R34: =AB34*SUM(BC34:BN34) -> 0 | S34: =SUM(GP34:HN34) -> 1125 | T34: =SUM(AZ34:EZ34) -> 3015 | U34: =_xlfn.CONCAT(Y34," - ",Z34) -> Technology - Analyst | V34: =VLOOKUP(O34,$B$187:$H$848,4,0) -> 0-1 years | W34: =IF(F34="US", "Onshore",IF(F34="India","Offshore", "Nearshore")) -> Offshore | X34: Consulting | Y34: Technology | Z34: Analyst | AA34: =[1]Resourcing!QD38 -> 53.385 | AB34: =IFERROR(VLOOKUP(O34,$B$187:$S$848,6,FALSE()),"combination not found") -> 48 | BZ34: 45 | CA34: 45 | CB34: 45 | CC34: 45 | CD34: 45 | CE34: 45 | CF34: 45 | CG34: 45 | CH34: 45 | CI34: 45 | CJ34: 45 | CK34: 45 | CL34: 45 | CM34: 45 | CN34: 45 | CO34: 45 | CP34: 45 | CQ34: 45 | CR34: 45 | CS34: 45 | CT34: 45 | CU34: 45 | CV34: 45 | CW34: 45 | CX34: 45 | CY34: 45 | CZ34: 45 | DA34: 45 | DB34: 45 | DC34: 45 | DD34: 45 | DE34: 45 | DF34: 45 | DG34: 45 | DH34: 45 | DI34: 45 | DJ34: 45 | DK34: 45 | DL34: 45 | DM34: 45 | DN34: 45 | DO34: 45 | DP34: 45 | DQ34: 45 | DT34: 45 | DU34: 45 | DV34: 45 | DW34: 45 | DX34: 45 | DY34: 45 | DZ34: 45 | EA34: 45 | EB34: 45 | EC34: 45 | ED34: 45 | EE34: 45 | EF34: 45 | EG34: 45 | EH34: 45 | EI34: 45 | EJ34: 45 | EK34: 45 | EL34: 45 | EM34: 45 | EN34: 45 | EO34: 45 | EP34: 45 | FQ34: =SUMIF($AC$11:$FP$11,FQ$12,$AC34:$FP34) -> #VALUE! | FR34: =SUMIF($AC$11:$FP$11,FR$12,$AC34:$FP34) -> #VALUE! | FS34: =SUMIF($AC$11:$FP$11,FS$12,$AC34:$FP34) -> #VALUE! | FT34: =SUMIF($AC$11:$FP$11,FT$12,$AC34:$FP34) -> #VALUE! | FU34: =SUMIF($AC$11:$FP$11,FU$12,$AC34:$FP34) -> #VALUE! | FV34: =SUMIF($AC$11:$FP$11,FV$12,$AC34:$FP34) -> #VALUE! | FW34: =SUMIF($AC$11:$FP$11,FW$12,$AC34:$FP34) -> #VALUE! | FX34: =SUMIF($AC$11:$FP$11,FX$12,$AC34:$FP34) -> #VALUE! | ... GO34: =SUMIF($AC$11:$FP$11,GO$12,$AC34:$FP34) -> #VALUE! | GP34: =SUMIF($AB$8:$FO$8,GP$9,$AB34:$FO34) -> 90 | GQ34: =SUMIF($AB$8:$FO$8,GQ$9,$AB34:$FO34) -> 180 | GR34: =SUMIF($AB$8:$FO$8,GR$9,$AB34:$FO34) -> 180 | GS34: =SUMIF($AB$8:$FO$8,GS$9,$AB34:$FO34) -> 180 | GT34: =SUMIF($AB$8:$FO$8,GT$9,$AB34:$FO34) -> 180 | GU34: =SUMIF($AB$8:$FO$8,GU$9,$AB34:$FO34) -> 180 | GV34: =SUMIF($AB$8:$FO$8,GV$9,$AB34:$FO34) -> 135 | GW34: =SUMIF($AB$8:$FO$8,GW$9,$AB34:$FO34) -> 0 | ... HE34: =SUMIF($AB$8:$FO$8,HE$9,$AB34:$FO34) -> 0
Q35: =AB35*SUM(AZ35:ET35) -> 0 | R35: =AB35*SUM(BC35:BN35) -> 0 | T35: =SUM(AZ35:EZ35) -> 0 | AA35: =[1]Resourcing!QD39 -> 53.385 | FQ35: =SUMIF($AC$11:$FP$11,FQ$12,$AC35:$FP35) -> #VALUE! | FR35: =SUMIF($AC$11:$FP$11,FR$12,$AC35:$FP35) -> #VALUE! | FS35: =SUMIF($AC$11:$FP$11,FS$12,$AC35:$FP35) -> #VALUE! | FT35: =SUMIF($AC$11:$FP$11,FT$12,$AC35:$FP35) -> #VALUE! | FU35: =SUMIF($AC$11:$FP$11,FU$12,$AC35:$FP35) -> #VALUE! | FV35: =SUMIF($AC$11:$FP$11,FV$12,$AC35:$FP35) -> #VALUE! | FW35: =SUMIF($AC$11:$FP$11,FW$12,$AC35:$FP35) -> #VALUE! | FX35: =SUMIF($AC$11:$FP$11,FX$12,$AC35:$FP35) -> #VALUE! | ... GO35: =SUMIF($AC$11:$FP$11,GO$12,$AC35:$FP35) -> #VALUE! | GP35: =SUMIF($AB$8:$FO$8,GP$9,$AB35:$FO35) -> 0 | GQ35: =SUMIF($AB$8:$FO$8,GQ$9,$AB35:$FO35) -> 0 | GR35: =SUMIF($AB$8:$FO$8,GR$9,$AB35:$FO35) -> 0 | GS35: =SUMIF($AB$8:$FO$8,GS$9,$AB35:$FO35) -> 0 | GT35: =SUMIF($AB$8:$FO$8,GT$9,$AB35:$FO35) -> 0 | GU35: =SUMIF($AB$8:$FO$8,GU$9,$AB35:$FO35) -> 0 | GV35: =SUMIF($AB$8:$FO$8,GV$9,$AB35:$FO35) -> 0 | GW35: =SUMIF($AB$8:$FO$8,GW$9,$AB35:$FO35) -> 0 | ... HE35: =SUMIF($AB$8:$FO$8,HE$9,$AB35:$FO35) -> 0
B36: Process | C36: TAX | D36: TAX | E36: Tax Global Quality Lead - SAP / Vertex / DRC | F36: US | G36: TAX | H36: Tax Technology Consulting | I36: Tax Technology Consulting | J36: US | K36: Tax Services | L36: Tax Technology Consulting | M36: LMD - Managing Director | N36: =_xlfn.CONCAT(C36,"-",D36) -> TAX-TAX | O36: =_xlfn.CONCAT(Y36,"-",Z36,"-",F36,"-",X36) -> Tax Advisory-Managing Director-US-Tax | P36: =_xlfn.CONCAT(C36," - ",Y36) -> TAX - Tax Advisory | Q36: =AB36*SUM(AZ36:ET36) -> 108100 | R36: =AB36*SUM(BC36:BN36) -> 13800 | S36: =SUM(GP36:HN36) -> 0 | T36: =SUM(AZ36:EZ36) -> 188 | U36: =_xlfn.CONCAT(Y36," - ",Z36) -> Tax Advisory - Managing Director | V36: =VLOOKUP(O36,$B$187:$H$848,4,0) -> 12+ years | W36: =IF(F36="US", "Onshore",IF(F36="India","Offshore", "Nearshore")) -> Onshore | X36: Tax | Y36: Tax Advisory | Z36: Managing Director | AA36: =[1]Resourcing!QD40 -> 43.160845 | AB36: =IFERROR(VLOOKUP(O36,$B$187:$S$848,6,FALSE()),"combination not found") -> 575 | BA36: 2 | BB36: 2 | BC36: 2 | BD36: 2 | BE36: 2 | BF36: 2 | BG36: 2 | BH36: 2 | BI36: 2 | BJ36: 2 | BK36: 2 | BL36: 2 | BM36: 2 | BN36: 2 | BO36: 2 | BP36: 2 | BQ36: 2 | BT36: 2 | BU36: 2 | BV36: 2 | BW36: 2 | BX36: 2 | BY36: 2 | BZ36: 2 | CA36: 2 | CB36: 2 | CC36: 2 | CD36: 2 | CE36: 2 | CF36: 2 | CG36: 2 | CH36: 2 | CI36: 2 | CJ36: 2 | CK36: 2 | CL36: 2 | CM36: 2 | CN36: 2 | CO36: 2 | CP36: 2 | CQ36: 2 | CR36: 2 | CS36: 2 | CT36: 2 | CU36: 2 | CV36: 2 | CW36: 2 | CX36: 2 | CY36: 2 | CZ36: 2 | DA36: 2 | DB36: 2 | DC36: 2 | DD36: 2 | DE36: 2 | DF36: 2 | DG36: 2 | DH36: 2 | DI36: 2 | DJ36: 2 | DK36: 2 | DL36: 2 | DM36: 2 | DN36: 2 | DO36: 2 | DP36: 2 | DQ36: 2 | DT36: 2 | DU36: 2 | DV36: 2 | DW36: 2 | DX36: 2 | DY36: 2 | DZ36: 2 | EA36: 2 | EB36: 2 | EC36: 2 | ED36: 2 | EE36: 2 | EF36: 2 | EG36: 2 | EH36: 2 | EI36: 2 | EJ36: 2 | EK36: 2 | EL36: 2 | EM36: 2 | EN36: 2 | EO36: 2.5 | EP36: 2.5 | EQ36: 2.5 | ER36: 2.5 | ES36: 1 | ET36: 1 | FQ36: =SUMIF($AC$11:$FP$11,FQ$12,$AC36:$FP36) -> #VALUE! | FR36: =SUMIF($AC$11:$FP$11,FR$12,$AC36:$FP36) -> #VALUE! | FS36: =SUMIF($AC$11:$FP$11,FS$12,$AC36:$FP36) -> #VALUE! | FT36: =SUMIF($AC$11:$FP$11,FT$12,$AC36:$FP36) -> #VALUE! | FU36: =SUMIF($AC$11:$FP$11,FU$12,$AC36:$FP36) -> #VALUE! | FV36: =SUMIF($AC$11:$FP$11,FV$12,$AC36:$FP36) -> #VALUE! | FW36: =SUMIF($AC$11:$FP$11,FW$12,$AC36:$FP36) -> #VALUE! | FX36: =SUMIF($AC$11:$FP$11,FX$12,$AC36:$FP36) -> #VALUE! | ... GO36: =SUMIF($AC$11:$FP$11,GO$12,$AC36:$FP36) -> #VALUE!
B37: Process | C37: TAX | D37: TAX | E37: Tax Global Engagement Lead - SAP / Vertex / DRC | F37: US | G37: TAX | H37: Tax Technology Consulting | I37: Tax Technology Consulting | J37: US | K37: Tax Services | L37: Tax Technology Consulting | M37: L65 - Senior Manager | N37: =_xlfn.CONCAT(C37,"-",D37) -> TAX-TAX | O37: =_xlfn.CONCAT(Y37,"-",Z37,"-",F37,"-",X37) -> Tax Advisory-Senior Manager-US-Tax | P37: =_xlfn.CONCAT(C37," - ",Y37) -> TAX - Tax Advisory | Q37: =AB37*SUM(AZ37:ET37) -> 920000 | R37: =AB37*SUM(BC37:BN37) -> 120000 | S37: =SUM(GP37:HN37) -> 580 | T37: =SUM(AZ37:EZ37) -> 1840 | U37: =_xlfn.CONCAT(Y37," - ",Z37) -> Tax Advisory - Senior Manager | V37: =VLOOKUP(O37,$B$187:$H$848,4,0) -> 9-12 years | W37: =IF(F37="US", "Onshore",IF(F37="India","Offshore", "Nearshore")) -> Onshore | X37: Tax | Y37: Tax Advisory | Z37: Senior Manager | AA37: =[1]Resourcing!QD41 -> 42.987164 | AB37: =IFERROR(VLOOKUP(O37,$B$187:$S$848,6,FALSE()),"combination not found") -> 500 | BC37: 20 | BD37: 20 | BE37: 20 | BF37: 20 | BG37: 20 | BH37: 20 | BI37: 20 | BJ37: 20 | BK37: 20 | BL37: 20 | BM37: 20 | BN37: 20 | BO37: 20 | BP37: 20 | BQ37: 20 | BT37: 20 | BU37: 20 | BV37: 20 | BW37: 20 | BX37: 20 | BY37: 20 | BZ37: 20 | CA37: 20 | CB37: 20 | CC37: 20 | CD37: 20 | CE37: 20 | CF37: 20 | CG37: 20 | CH37: 20 | CI37: 20 | CJ37: 20 | CK37: 20 | CL37: 20 | CM37: 20 | CN37: 20 | CO37: 20 | CP37: 20 | CQ37: 20 | CR37: 20 | CS37: 20 | CT37: 20 | CU37: 20 | CV37: 20 | CW37: 20 | CX37: 20 | CY37: 20 | CZ37: 20 | DA37: 20 | DB37: 20 | DC37: 20 | DD37: 20 | DE37: 20 | DF37: 20 | DG37: 20 | DH37: 20 | DI37: 20 | DJ37: 20 | DK37: 20 | DL37: 20 | DM37: 20 | DN37: 20 | DO37: 20 | DP37: 20 | DQ37: 20 | DT37: 20 | DU37: 20 | DV37: 20 | DW37: 20 | DX37: 20 | DY37: 20 | DZ37: 20 | EA37: 20 | EB37: 20 | EC37: 20 | ED37: 20 | EE37: 20 | EF37: 20 | EG37: 20 | EH37: 20 | EI37: 20 | EJ37: 20 | EK37: 20 | EL37: 20 | EM37: 20 | EN37: 20 | EO37: 20 | EP37: 20 | EQ37: 20 | ER37: 20 | ES37: 20 | ET37: 20 | FQ37: =SUMIF($AC$11:$FP$11,FQ$12,$AC37:$FP37) -> #VALUE! | FR37: =SUMIF($AC$11:$FP$11,FR$12,$AC37:$FP37) -> #VALUE! | FS37: =SUMIF($AC$11:$FP$11,FS$12,$AC37:$FP37) -> #VALUE! | FT37: =SUMIF($AC$11:$FP$11,FT$12,$AC37:$FP37) -> #VALUE! | FU37: =SUMIF($AC$11:$FP$11,FU$12,$AC37:$FP37) -> #VALUE! | FV37: =SUMIF($AC$11:$FP$11,FV$12,$AC37:$FP37) -> #VALUE! | FW37: =SUMIF($AC$11:$FP$11,FW$12,$AC37:$FP37) -> #VALUE! | FX37: =SUMIF($AC$11:$FP$11,FX$12,$AC37:$FP37) -> #VALUE! | ... GO37: =SUMIF($AC$11:$FP$11,GO$12,$AC37:$FP37) -> #VALUE! | GP37: =SUMIF($AB$8:$FO$8,GP$9,$AB37:$FO37) -> 40 | GQ37: =SUMIF($AB$8:$FO$8,GQ$9,$AB37:$FO37) -> 80 | GR37: =SUMIF($AB$8:$FO$8,GR$9,$AB37:$FO37) -> 80 | GS37: =SUMIF($AB$8:$FO$8,GS$9,$AB37:$FO37) -> 80 | GT37: =SUMIF($AB$8:$FO$8,GT$9,$AB37:$FO37) -> 80 | GU37: =SUMIF($AB$8:$FO$8,GU$9,$AB37:$FO37) -> 80 | GV37: =SUMIF($AB$8:$FO$8,GV$9,$AB37:$FO37) -> 80 | GW37: =SUMIF($AB$8:$FO$8,GW$9,$AB37:$FO37) -> 60 | ... HE37: =SUMIF($AB$8:$FO$8,HE$9,$AB37:$FO37) -> 0
B38: Process | C38: TAX | D38: TAX | E38: Tax SAP / Vertex Team Lead | F38: India | G38: TAX | H38: Tax Technology Consulting | I38: Tax Technology Consulting | J38: India | K38: Tax Services | L38: Tax Technology Consulting | M38: L55 - Manager | N38: =_xlfn.CONCAT(C38,"-",D38) -> TAX-TAX | O38: =_xlfn.CONCAT(Y38,"-",Z38,"-",F38,"-",X38) -> Tax Advisory-Manager-India-Tax | P38: =_xlfn.CONCAT(C38," - ",Y38) -> TAX - Tax Advisory | Q38: =AB38*SUM(AZ38:ET38) -> 785040 | R38: =AB38*SUM(BC38:BN38) -> 10800 | S38: =SUM(GP38:HN38) -> 931 | T38: =SUM(AZ38:EZ38) -> 3271 | U38: =_xlfn.CONCAT(Y38," - ",Z38) -> Tax Advisory - Manager | V38: =VLOOKUP(O38,$B$187:$H$848,4,0) -> 6-9 years | W38: =IF(F38="US", "Onshore",IF(F38="India","Offshore", "Nearshore")) -> Offshore | X38: Tax | Y38: Tax Advisory | Z38: Manager | AA38: =[1]Resourcing!QD42 -> 0 | AB38: =IFERROR(VLOOKUP(O38,$B$187:$S$848,6,FALSE()),"combination not found") -> 240 | BN38: 45 | BO38: 45 | BP38: 45 | BQ38: 45 | BT38: 45 | BU38: 45 | BV38: 45 | BW38: 45 | BX38: 45 | BY38: 45 | BZ38: 45 | CA38: 45 | CB38: 45 | CC38: 45 | CD38: 45 | CE38: 45 | CF38: 45 | CG38: 45 | CH38: 45 | CI38: 45 | CJ38: 45 | CK38: 45 | CL38: 45 | CM38: 45 | CN38: 45 | CO38: 45 | CP38: 45 | CQ38: 45 | CR38: 45 | CS38: 45 | CT38: 45 | CU38: 45 | CV38: 45 | CW38: 45 | CX38: 45 | CY38: 45 | CZ38: 45 | DA38: 45 | DB38: 45 | DC38: 45 | DD38: 45 | DE38: 45 | DF38: 45 | DG38: 45 | DH38: 45 | DI38: 45 | DJ38: 45 | DK38: 45 | DL38: 45 | DM38: 45 | DN38: 45 | DO38: 45 | DP38: 45 | DQ38: 45 | DT38: 45 | DU38: 45 | DV38: 45 | DW38: 45 | DX38: 45 | DY38: 45 | DZ38: 45 | EA38: 45 | EB38: 45 | EC38: 45 | ED38: 23 | EE38: 23 | EF38: 23 | EG38: 23 | EH38: 23 | EI38: 23 | EJ38: 23 | EK38: 23 | EL38: 23 | EM38: 23 | EN38: 23 | EO38: 23 | EP38: 23 | EQ38: 23 | ER38: 23 | ES38: 23 | ET38: 23 | FQ38: =SUMIF($AC$11:$FP$11,FQ$12,$AC38:$FP38) -> #VALUE! | FR38: =SUMIF($AC$11:$FP$11,FR$12,$AC38:$FP38) -> #VALUE! | FS38: =SUMIF($AC$11:$FP$11,FS$12,$AC38:$FP38) -> #VALUE! | FT38: =SUMIF($AC$11:$FP$11,FT$12,$AC38:$FP38) -> #VALUE! | FU38: =SUMIF($AC$11:$FP$11,FU$12,$AC38:$FP38) -> #VALUE! | FV38: =SUMIF($AC$11:$FP$11,FV$12,$AC38:$FP38) -> #VALUE! | FW38: =SUMIF($AC$11:$FP$11,FW$12,$AC38:$FP38) -> #VALUE! | FX38: =SUMIF($AC$11:$FP$11,FX$12,$AC38:$FP38) -> #VALUE! | ... GO38: =SUMIF($AC$11:$FP$11,GO$12,$AC38:$FP38) -> #VALUE! | GP38: =SUMIF($AB$8:$FO$8,GP$9,$AB38:$FO38) -> 90 | GQ38: =SUMIF($AB$8:$FO$8,GQ$9,$AB38:$FO38) -> 180 | GR38: =SUMIF($AB$8:$FO$8,GR$9,$AB38:$FO38) -> 180 | GS38: =SUMIF($AB$8:$FO$8,GS$9,$AB38:$FO38) -> 136 | GT38: =SUMIF($AB$8:$FO$8,GT$9,$AB38:$FO38) -> 92 | GU38: =SUMIF($AB$8:$FO$8,GU$9,$AB38:$FO38) -> 92 | GV38: =SUMIF($AB$8:$FO$8,GV$9,$AB38:$FO38) -> 92 | GW38: =SUMIF($AB$8:$FO$8,GW$9,$AB38:$FO38) -> 69 | ... HE38: =SUMIF($AB$8:$FO$8,HE$9,$AB38:$FO38) -> 0
B39: Process | C39: TAX | D39: TAX | E39: Tax SAP / Vertex Offshore Team Member | F39: India | G39: TAX | H39: Tax Technology Consulting | I39: Tax Technology Consulting | J39: India | K39: Tax Services | L39: Core Tax | M39: L45 - Senior | N39: =_xlfn.CONCAT(C39,"-",D39) -> TAX-TAX | O39: =_xlfn.CONCAT(Y39,"-",Z39,"-",F39,"-",X39) -> Tax Advisory-Senior Consultant-India-Tax | P39: =_xlfn.CONCAT(C39," - ",Y39) -> TAX - Tax Advisory | Q39: =AB39*SUM(AZ39:ET39) -> 530280 | R39: =AB39*SUM(BC39:BN39) -> 3600 | S39: =SUM(GP39:HN39) -> 931 | T39: =SUM(AZ39:EZ39) -> 2946 | U39: =_xlfn.CONCAT(Y39," - ",Z39) -> Tax Advisory - Senior Consultant | V39: =VLOOKUP(O39,$B$187:$H$848,4,0) -> 3-6 years | W39: =IF(F39="US", "Onshore",IF(F39="India","Offshore", "Nearshore")) -> Offshore | X39: Tax | Y39: Tax Advisory | Z39: Senior Consultant | AA39: =[1]Resourcing!QD43 -> 358.68298 | AB39: =IFERROR(VLOOKUP(O39,$B$187:$S$848,6,FALSE()),"combination not found") -> 180 | BN39: 20 | BO39: 20 | BP39: 20 | BQ39: 20 | BT39: 20 | BU39: 20 | BV39: 20 | BW39: 20 | BX39: 20 | BY39: 20 | BZ39: 20 | CA39: 20 | CB39: 20 | CC39: 45 | CD39: 45 | CE39: 45 | CF39: 45 | CG39: 45 | CH39: 45 | CI39: 45 | CJ39: 45 | CK39: 45 | CL39: 45 | CM39: 45 | CN39: 45 | CO39: 45 | CP39: 45 | CQ39: 45 | CR39: 45 | CS39: 45 | CT39: 45 | CU39: 45 | CV39: 45 | CW39: 45 | CX39: 45 | CY39: 45 | CZ39: 45 | DA39: 45 | DB39: 45 | DC39: 45 | DD39: 45 | DE39: 45 | DF39: 45 | DG39: 45 | DH39: 45 | DI39: 45 | DJ39: 45 | DK39: 45 | DL39: 45 | DM39: 45 | DN39: 45 | DO39: 45 | DP39: 45 | DQ39: 45 | DT39: 45 | DU39: 45 | DV39: 45 | DW39: 45 | DX39: 45 | DY39: 45 | DZ39: 45 | EA39: 45 | EB39: 45 | EC39: 45 | ED39: 23 | EE39: 23 | EF39: 23 | EG39: 23 | EH39: 23 | EI39: 23 | EJ39: 23 | EK39: 23 | EL39: 23 | EM39: 23 | EN39: 23 | EO39: 23 | EP39: 23 | EQ39: 23 | ER39: 23 | ES39: 23 | ET39: 23 | FQ39: =SUMIF($AC$11:$FP$11,FQ$12,$AC39:$FP39) -> #VALUE! | FR39: =SUMIF($AC$11:$FP$11,FR$12,$AC39:$FP39) -> #VALUE! | FS39: =SUMIF($AC$11:$FP$11,FS$12,$AC39:$FP39) -> #VALUE! | FT39: =SUMIF($AC$11:$FP$11,FT$12,$AC39:$FP39) -> #VALUE! | FU39: =SUMIF($AC$11:$FP$11,FU$12,$AC39:$FP39) -> #VALUE! | FV39: =SUMIF($AC$11:$FP$11,FV$12,$AC39:$FP39) -> #VALUE! | FW39: =SUMIF($AC$11:$FP$11,FW$12,$AC39:$FP39) -> #VALUE! | FX39: =SUMIF($AC$11:$FP$11,FX$12,$AC39:$FP39) -> #VALUE! | ... GO39: =SUMIF($AC$11:$FP$11,GO$12,$AC39:$FP39) -> #VALUE! | GP39: =SUMIF($AB$8:$FO$8,GP$9,$AB39:$FO39) -> 90 | GQ39: =SUMIF($AB$8:$FO$8,GQ$9,$AB39:$FO39) -> 180 | GR39: =SUMIF($AB$8:$FO$8,GR$9,$AB39:$FO39) -> 180 | GS39: =SUMIF($AB$8:$FO$8,GS$9,$AB39:$FO39) -> 136 | GT39: =SUMIF($AB$8:$FO$8,GT$9,$AB39:$FO39) -> 92 | GU39: =SUMIF($AB$8:$FO$8,GU$9,$AB39:$FO39) -> 92 | GV39: =SUMIF($AB$8:$FO$8,GV$9,$AB39:$FO39) -> 92 | GW39: =SUMIF($AB$8:$FO$8,GW$9,$AB39:$FO39) -> 69 | ... HE39: =SUMIF($AB$8:$FO$8,HE$9,$AB39:$FO39) -> 0
B40: Process | C40: TAX | D40: TAX | E40: Tax DRC Architect | F40: India | G40: TAX | H40: Tax Technology Consulting | I40: Tax Technology Consulting | J40: India | K40: Tax Services | L40: Tax Technology Consulting | M40: L65 - Senior Manager | N40: =_xlfn.CONCAT(C40,"-",D40) -> TAX-TAX | O40: =_xlfn.CONCAT(Y40,"-",Z40,"-",F40,"-",X40) -> Tax Advisory-Senior Manager-India-Tax | P40: =_xlfn.CONCAT(C40," - ",Y40) -> TAX - Tax Advisory | Q40: =AB40*SUM(AZ40:ET40) -> 666600 | R40: =AB40*SUM(BC40:BN40) -> 14850 | S40: =SUM(GP40:HN40) -> 300 | T40: =SUM(AZ40:EZ40) -> 2020 | U40: =_xlfn.CONCAT(Y40," - ",Z40) -> Tax Advisory - Senior Manager | V40: =VLOOKUP(O40,$B$187:$H$848,4,0) -> 9-12 years | W40: =IF(F40="US", "Onshore",IF(F40="India","Offshore", "Nearshore")) -> Offshore | X40: Tax | Y40: Tax Advisory | Z40: Senior Manager | AA40: =[1]Resourcing!QD44 -> 321.75326 | AB40: =IFERROR(VLOOKUP(O40,$B$187:$S$848,6,FALSE()),"combination not found") -> 330 | BN40: 45 | BO40: 45 | BP40: 45 | BQ40: 45 | BT40: 45 | BU40: 45 | BV40: 45 | BW40: 45 | BX40: 45 | BY40: 45 | BZ40: 45 | CA40: 45 | CB40: 45 | CC40: 45 | CD40: 45 | CE40: 45 | CF40: 45 | CG40: 45 | CH40: 45 | CI40: 45 | CJ40: 45 | CK40: 25 | CL40: 25 | CM40: 25 | CN40: 25 | CO40: 25 | CP40: 25 | CQ40: 25 | CR40: 25 | CS40: 25 | CT40: 25 | CU40: 25 | CV40: 25 | CW40: 25 | CX40: 25 | CY40: 25 | CZ40: 25 | DA40: 25 | DB40: 25 | DC40: 25 | DD40: 25 | DE40: 25 | DF40: 25 | DG40: 25 | DH40: 25 | DI40: 25 | DJ40: 25 | DK40: 25 | DL40: 25 | DM40: 25 | DN40: 25 | DO40: 25 | DP40: 25 | DQ40: 25 | DT40: 25 | DU40: 25 | DV40: 25 | DW40: 25 | DX40: 25 | DY40: 25 | DZ40: 25 | EA40: 25 | EB40: 25 | EC40: 25 | FQ40: =SUMIF($AC$11:$FP$11,FQ$12,$AC40:$FP40) -> #VALUE! | FR40: =SUMIF($AC$11:$FP$11,FR$12,$AC40:$FP40) -> #VALUE! | FS40: =SUMIF($AC$11:$FP$11,FS$12,$AC40:$FP40) -> #VALUE! | FT40: =SUMIF($AC$11:$FP$11,FT$12,$AC40:$FP40) -> #VALUE! | FU40: =SUMIF($AC$11:$FP$11,FU$12,$AC40:$FP40) -> #VALUE! | FV40: =SUMIF($AC$11:$FP$11,FV$12,$AC40:$FP40) -> #VALUE! | FW40: =SUMIF($AC$11:$FP$11,FW$12,$AC40:$FP40) -> #VALUE! | FX40: =SUMIF($AC$11:$FP$11,FX$12,$AC40:$FP40) -> #VALUE! | ... GO40: =SUMIF($AC$11:$FP$11,GO$12,$AC40:$FP40) -> #VALUE! | GP40: =SUMIF($AB$8:$FO$8,GP$9,$AB40:$FO40) -> 50 | GQ40: =SUMIF($AB$8:$FO$8,GQ$9,$AB40:$FO40) -> 100 | GR40: =SUMIF($AB$8:$FO$8,GR$9,$AB40:$FO40) -> 100 | GS40: =SUMIF($AB$8:$FO$8,GS$9,$AB40:$FO40) -> 50 | GT40: =SUMIF($AB$8:$FO$8,GT$9,$AB40:$FO40) -> 0 | GU40: =SUMIF($AB$8:$FO$8,GU$9,$AB40:$FO40) -> 0 | GV40: =SUMIF($AB$8:$FO$8,GV$9,$AB40:$FO40) -> 0 | GW40: =SUMIF($AB$8:$FO$8,GW$9,$AB40:$FO40) -> 0 | ... HE40: =SUMIF($AB$8:$FO$8,HE$9,$AB40:$FO40) -> 0
B41: Process | C41: TAX | D41: TAX | E41: Tax DRC Offshore Team Member | F41: India | G41: TAX | H41: Tax Technology Consulting | I41: Tax Technology Consulting | J41: India | K41: Tax Services | L41: Core Tax | M41: L45 - Senior | N41: =_xlfn.CONCAT(C41,"-",D41) -> TAX-TAX | O41: =_xlfn.CONCAT(Y41,"-",Z41,"-",F41,"-",X41) -> Tax Advisory-Senior Consultant-India-Tax | P41: =_xlfn.CONCAT(C41," - ",Y41) -> TAX - Tax Advisory | Q41: =AB41*SUM(AZ41:ET41) -> 530280 | R41: =AB41*SUM(BC41:BN41) -> 3600 | S41: =SUM(GP41:HN41) -> 931 | T41: =SUM(AZ41:EZ41) -> 2946 | U41: =_xlfn.CONCAT(Y41," - ",Z41) -> Tax Advisory - Senior Consultant | V41: =VLOOKUP(O41,$B$187:$H$848,4,0) -> 3-6 years | W41: =IF(F41="US", "Onshore",IF(F41="India","Offshore", "Nearshore")) -> Offshore | X41: Tax | Y41: Tax Advisory | Z41: Senior Consultant | AA41: =[1]Resourcing!QD45 -> 98.24247 | AB41: =IFERROR(VLOOKUP(O41,$B$187:$S$848,6,FALSE()),"combination not found") -> 180 | BN41: 20 | BO41: 20 | BP41: 20 | BQ41: 20 | BT41: 20 | BU41: 20 | BV41: 20 | BW41: 20 | BX41: 20 | BY41: 20 | BZ41: 20 | CA41: 20 | CB41: 20 | CC41: 45 | CD41: 45 | CE41: 45 | CF41: 45 | CG41: 45 | CH41: 45 | CI41: 45 | CJ41: 45 | CK41: 45 | CL41: 45 | CM41: 45 | CN41: 45 | CO41: 45 | CP41: 45 | CQ41: 45 | CR41: 45 | CS41: 45 | CT41: 45 | CU41: 45 | CV41: 45 | CW41: 45 | CX41: 45 | CY41: 45 | CZ41: 45 | DA41: 45 | DB41: 45 | DC41: 45 | DD41: 45 | DE41: 45 | DF41: 45 | DG41: 45 | DH41: 45 | DI41: 45 | DJ41: 45 | DK41: 45 | DL41: 45 | DM41: 45 | DN41: 45 | DO41: 45 | DP41: 45 | DQ41: 45 | DT41: 45 | DU41: 45 | DV41: 45 | DW41: 45 | DX41: 45 | DY41: 45 | DZ41: 45 | EA41: 45 | EB41: 45 | EC41: 45 | ED41: 23 | EE41: 23 | EF41: 23 | EG41: 23 | EH41: 23 | EI41: 23 | EJ41: 23 | EK41: 23 | EL41: 23 | EM41: 23 | EN41: 23 | EO41: 23 | EP41: 23 | EQ41: 23 | ER41: 23 | ES41: 23 | ET41: 23 | FQ41: =SUMIF($AC$11:$FP$11,FQ$12,$AC41:$FP41) -> #VALUE! | FR41: =SUMIF($AC$11:$FP$11,FR$12,$AC41:$FP41) -> #VALUE! | FS41: =SUMIF($AC$11:$FP$11,FS$12,$AC41:$FP41) -> #VALUE! | FT41: =SUMIF($AC$11:$FP$11,FT$12,$AC41:$FP41) -> #VALUE! | FU41: =SUMIF($AC$11:$FP$11,FU$12,$AC41:$FP41) -> #VALUE! | FV41: =SUMIF($AC$11:$FP$11,FV$12,$AC41:$FP41) -> #VALUE! | FW41: =SUMIF($AC$11:$FP$11,FW$12,$AC41:$FP41) -> #VALUE! | FX41: =SUMIF($AC$11:$FP$11,FX$12,$AC41:$FP41) -> #VALUE! | ... GO41: =SUMIF($AC$11:$FP$11,GO$12,$AC41:$FP41) -> #VALUE! | GP41: =SUMIF($AB$8:$FO$8,GP$9,$AB41:$FO41) -> 90 | GQ41: =SUMIF($AB$8:$FO$8,GQ$9,$AB41:$FO41) -> 180 | GR41: =SUMIF($AB$8:$FO$8,GR$9,$AB41:$FO41) -> 180 | GS41: =SUMIF($AB$8:$FO$8,GS$9,$AB41:$FO41) -> 136 | GT41: =SUMIF($AB$8:$FO$8,GT$9,$AB41:$FO41) -> 92 | GU41: =SUMIF($AB$8:$FO$8,GU$9,$AB41:$FO41) -> 92 | GV41: =SUMIF($AB$8:$FO$8,GV$9,$AB41:$FO41) -> 92 | GW41: =SUMIF($AB$8:$FO$8,GW$9,$AB41:$FO41) -> 69 | ... HE41: =SUMIF($AB$8:$FO$8,HE$9,$AB41:$FO41) -> 0
B42: Process | C42: TAX | D42: TAX | E42: Tax SAP / Vertex / DRC Onshore Team Member | F42: US | G42: TAX | H42: Tax Technology Consulting | I42: Tax Technology Consulting | J42: US | K42: Tax Services | L42: Core Tax | M42: L45 - Senior | N42: =_xlfn.CONCAT(C42,"-",D42) -> TAX-TAX | O42: =_xlfn.CONCAT(Y42,"-",Z42,"-",F42,"-",X42) -> Tax Advisory-Senior Consultant-US-Tax | P42: =_xlfn.CONCAT(C42," - ",Y42) -> TAX - Tax Advisory | Q42: =AB42*SUM(AZ42:ET42) -> 615600 | R42: =AB42*SUM(BC42:BN42) -> 5700 | S42: =SUM(GP42:HN42) -> 820 | T42: =SUM(AZ42:EZ42) -> 2160 | U42: =_xlfn.CONCAT(Y42," - ",Z42) -> Tax Advisory - Senior Consultant | V42: =VLOOKUP(O42,$B$187:$H$848,4,0) -> 3-6 years | W42: =IF(F42="US", "Onshore",IF(F42="India","Offshore", "Nearshore")) -> Onshore | X42: Tax | Y42: Tax Advisory | Z42: Senior Consultant | AA42: =[1]Resourcing!QD46 -> 77.84222 | AB42: =IFERROR(VLOOKUP(O42,$B$187:$S$848,6,FALSE()),"combination not found") -> 285 | BN42: 20 | BO42: 20 | BP42: 20 | BQ42: 20 | BT42: 20 | BU42: 20 | BV42: 20 | BW42: 20 | BX42: 20 | BY42: 20 | BZ42: 20 | CA42: 20 | CB42: 20 | CC42: 20 | CD42: 20 | CE42: 20 | CF42: 20 | CG42: 20 | CH42: 20 | CI42: 20 | CJ42: 20 | CK42: 20 | CL42: 20 | CM42: 20 | CN42: 20 | CO42: 20 | CP42: 20 | CQ42: 20 | CR42: 20 | CS42: 20 | CT42: 20 | CU42: 20 | CV42: 20 | CW42: 20 | CX42: 20 | CY42: 20 | CZ42: 20 | DA42: 40 | DB42: 40 | DC42: 40 | DD42: 40 | DE42: 40 | DF42: 40 | DG42: 40 | DH42: 40 | DI42: 40 | DJ42: 40 | DK42: 40 | DL42: 40 | DM42: 40 | DN42: 40 | DO42: 40 | DP42: 40 | DQ42: 40 | DT42: 40 | DU42: 40 | DV42: 40 | DW42: 40 | DX42: 40 | DY42: 40 | DZ42: 40 | EA42: 40 | EB42: 40 | EC42: 40 | ED42: 20 | EE42: 20 | EF42: 20 | EG42: 20 | EH42: 20 | EI42: 20 | EJ42: 20 | EK42: 20 | EL42: 20 | EM42: 20 | EN42: 20 | EO42: 20 | EP42: 20 | EQ42: 20 | ER42: 20 | ES42: 20 | ET42: 20 | FQ42: =SUMIF($AC$11:$FP$11,FQ$12,$AC42:$FP42) -> #VALUE! | FR42: =SUMIF($AC$11:$FP$11,FR$12,$AC42:$FP42) -> #VALUE! | FS42: =SUMIF($AC$11:$FP$11,FS$12,$AC42:$FP42) -> #VALUE! | FT42: =SUMIF($AC$11:$FP$11,FT$12,$AC42:$FP42) -> #VALUE! | FU42: =SUMIF($AC$11:$FP$11,FU$12,$AC42:$FP42) -> #VALUE! | FV42: =SUMIF($AC$11:$FP$11,FV$12,$AC42:$FP42) -> #VALUE! | FW42: =SUMIF($AC$11:$FP$11,FW$12,$AC42:$FP42) -> #VALUE! | FX42: =SUMIF($AC$11:$FP$11,FX$12,$AC42:$FP42) -> #VALUE! | ... GO42: =SUMIF($AC$11:$FP$11,GO$12,$AC42:$FP42) -> #VALUE! | GP42: =SUMIF($AB$8:$FO$8,GP$9,$AB42:$FO42) -> 80 | GQ42: =SUMIF($AB$8:$FO$8,GQ$9,$AB42:$FO42) -> 160 | GR42: =SUMIF($AB$8:$FO$8,GR$9,$AB42:$FO42) -> 160 | GS42: =SUMIF($AB$8:$FO$8,GS$9,$AB42:$FO42) -> 120 | GT42: =SUMIF($AB$8:$FO$8,GT$9,$AB42:$FO42) -> 80 | GU42: =SUMIF($AB$8:$FO$8,GU$9,$AB42:$FO42) -> 80 | GV42: =SUMIF($AB$8:$FO$8,GV$9,$AB42:$FO42) -> 80 | GW42: =SUMIF($AB$8:$FO$8,GW$9,$AB42:$FO42) -> 60 | ... HE42: =SUMIF($AB$8:$FO$8,HE$9,$AB42:$FO42) -> 0
Q43: =AB43*SUM(AZ43:ET43) -> 0 | R43: =AB43*SUM(BC43:BN43) -> 0 | T43: =SUM(AZ43:EZ43) -> 0 | AA43: =[1]Resourcing!QD47 -> 122.89604 | FQ43: =SUMIF($AC$11:$FP$11,FQ$12,$AC43:$FP43) -> #VALUE! | FR43: =SUMIF($AC$11:$FP$11,FR$12,$AC43:$FP43) -> #VALUE! | FS43: =SUMIF($AC$11:$FP$11,FS$12,$AC43:$FP43) -> #VALUE! | FT43: =SUMIF($AC$11:$FP$11,FT$12,$AC43:$FP43) -> #VALUE! | FU43: =SUMIF($AC$11:$FP$11,FU$12,$AC43:$FP43) -> #VALUE! | FV43: =SUMIF($AC$11:$FP$11,FV$12,$AC43:$FP43) -> #VALUE! | FW43: =SUMIF($AC$11:$FP$11,FW$12,$AC43:$FP43) -> #VALUE! | FX43: =SUMIF($AC$11:$FP$11,FX$12,$AC43:$FP43) -> #VALUE! | ... GO43: =SUMIF($AC$11:$FP$11,GO$12,$AC43:$FP43) -> #VALUE! | GP43: =SUMIF($AB$8:$FO$8,GP$9,$AB43:$FO43) -> 0 | GQ43: =SUMIF($AB$8:$FO$8,GQ$9,$AB43:$FO43) -> 0 | GR43: =SUMIF($AB$8:$FO$8,GR$9,$AB43:$FO43) -> 0 | GS43: =SUMIF($AB$8:$FO$8,GS$9,$AB43:$FO43) -> 0 | GT43: =SUMIF($AB$8:$FO$8,GT$9,$AB43:$FO43) -> 0 | GU43: =SUMIF($AB$8:$FO$8,GU$9,$AB43:$FO43) -> 0 | GV43: =SUMIF($AB$8:$FO$8,GV$9,$AB43:$FO43) -> 0 | GW43: =SUMIF($AB$8:$FO$8,GW$9,$AB43:$FO43) -> 0 | ... HE43: =SUMIF($AB$8:$FO$8,HE$9,$AB43:$FO43) -> 0
B44: Process | C44: OTC | D44: Order Management | E44: Overall OTC Lead | F44: US | G44: Consulting Services | H44: Enterprise Performance | I44: SAP | J44: US | K44: Package and Technology Enablement | L44: Package Functional Transformation | M44: L55 - Manager | N44: =_xlfn.CONCAT(C44,"-",D44) -> OTC-Order Management | O44: =_xlfn.CONCAT(Y44,"-",Z44,"-",F44,"-",X44) -> Technology-Manager-US-Consulting | P44: =_xlfn.CONCAT(C44," - ",Y44) -> OTC - Technology | Q44: =AB44*SUM(AZ44:ET44) -> 1101600 | R44: =AB44*SUM(BC44:BN44) -> 134640 | S44: =SUM(GP44:HN44) -> 0 | T44: =SUM(AZ44:EZ44) -> 3600 | U44: =_xlfn.CONCAT(Y44," - ",Z44) -> Technology - Manager | V44: =VLOOKUP(O44,$B$187:$H$848,4,0) -> 5-7 years | W44: =IF(F44="US", "Onshore",IF(F44="India","Offshore", "Nearshore")) -> Onshore | X44: Consulting | Y44: Technology | Z44: Manager | AA44: =[1]Resourcing!QD48 -> 77.84222 | AB44: =IFERROR(VLOOKUP(O44,$B$187:$S$848,6,FALSE()),"combination not found") -> 306 | BD44: 40 | BE44: 40 | BF44: 40 | BG44: 40 | BH44: 40 | BI44: 40 | BJ44: 40 | BK44: 40 | BL44: 40 | BM44: 40 | BN44: 40 | BO44: 40 | BP44: 40 | BQ44: 40 | BT44: 40 | BU44: 40 | BV44: 40 | BW44: 40 | BX44: 40 | BY44: 40 | BZ44: 40 | CA44: 40 | CB44: 40 | CC44: 40 | CD44: 40 | CE44: 40 | CF44: 40 | CG44: 40 | CH44: 40 | CI44: 40 | CJ44: 40 | CK44: 40 | CL44: 40 | CM44: 40 | CN44: 40 | CO44: 40 | CP44: 40 | CQ44: 40 | CR44: 40 | CS44: 40 | CT44: 40 | CU44: 40 | CV44: 40 | CW44: 40 | CX44: 40 | CY44: 40 | CZ44: 40 | DA44: 40 | DB44: 40 | DC44: 40 | DD44: 40 | DE44: 40 | DF44: 40 | DG44: 40 | DH44: 40 | DI44: 40 | DJ44: 40 | DK44: 40 | DL44: 40 | DM44: 40 | DN44: 40 | DO44: 40 | DP44: 40 | DQ44: 40 | DT44: 40 | DU44: 40 | DV44: 40 | DW44: 40 | DX44: 40 | DY44: 40 | DZ44: 40 | EA44: 40 | EB44: 40 | EC44: 40 | ED44: 40 | EE44: 40 | EF44: 40 | EG44: 40 | EH44: 40 | EI44: 40 | EJ44: 40 | EK44: 40 | EL44: 40 | EM44: 40 | EN44: 40 | EO44: 40 | EP44: 40 | EQ44: 40 | ER44: 40 | ES44: 40 | FQ44: =SUMIF($AC$11:$FP$11,FQ$12,$AC44:$FP44) -> #VALUE! | FR44: =SUMIF($AC$11:$FP$11,FR$12,$AC44:$FP44) -> #VALUE! | FS44: =SUMIF($AC$11:$FP$11,FS$12,$AC44:$FP44) -> #VALUE! | FT44: =SUMIF($AC$11:$FP$11,FT$12,$AC44:$FP44) -> #VALUE! | FU44: =SUMIF($AC$11:$FP$11,FU$12,$AC44:$FP44) -> #VALUE! | FV44: =SUMIF($AC$11:$FP$11,FV$12,$AC44:$FP44) -> #VALUE! | FW44: =SUMIF($AC$11:$FP$11,FW$12,$AC44:$FP44) -> #VALUE! | FX44: =SUMIF($AC$11:$FP$11,FX$12,$AC44:$FP44) -> #VALUE! | ... GO44: =SUMIF($AC$11:$FP$11,GO$12,$AC44:$FP44) -> #VALUE!
B45: Process | C45: OTC | D45: Order Management | E45: Order Management & Pricing SME | F45: US | G45: Consulting Services | H45: Enterprise Performance | I45: SAP | J45: US | K45: Package and Technology Enablement | L45: Package Functional Transformation | M45: L35 - Consultant | N45: =_xlfn.CONCAT(C45,"-",D45) -> OTC-Order Management | O45: =_xlfn.CONCAT(Y45,"-",Z45,"-",F45,"-",X45) -> Technology-Consultant-US-Consulting | P45: =_xlfn.CONCAT(C45," - ",Y45) -> OTC - Technology | Q45: =AB45*SUM(AZ45:ET45) -> 445230 | R45: =AB45*SUM(BC45:BN45) -> 0 | S45: =SUM(GP45:HN45) -> #VALUE! | T45: =SUM(AZ45:EZ45) -> 2295 | U45: =_xlfn.CONCAT(Y45," - ",Z45) -> Technology - Consultant | V45: =VLOOKUP(O45,$B$187:$H$848,4,0) -> 1-3 years | W45: =IF(F45="US", "Onshore",IF(F45="India","Offshore", "Nearshore")) -> Onshore | X45: Consulting | Y45: Technology | Z45: Consultant | AA45: =[1]Resourcing!QD49 -> 227.01676 | AB45: =IFERROR(VLOOKUP(O45,$B$187:$S$848,6,FALSE()),"combination not found") -> 194 | BT45: 45 | BU45: 45 | BV45: 45 | BW45: 45 | BX45: 45 | BY45: 45 | BZ45: 45 | CA45: 45 | CB45: 45 | CC45: 45 | CD45: 45 | CE45: 45 | CF45: 45 | CG45: 45 | CH45: 45 | CI45: 45 | CJ45: 45 | CK45: 45 | CL45: 45 | CM45: 45 | CN45: 45 | CO45: 45 | CP45: 45 | CQ45: 45 | CR45: 45 | CS45: 45 | CT45: 45 | CU45: 45 | CV45: 45 | CW45: 45 | CX45: 45 | CY45: 45 | CZ45: 45 | DA45: 45 | DB45: 45 | DC45: 45 | DD45: 45 | DE45: 45 | DF45: 45 | DG45: 45 | DH45: 45 | DI45: 45 | DJ45: 45 | DK45: 45 | DL45: 45 | DM45: 45 | DN45: 45 | DO45: 45 | DP45: 45 | DQ45: 45 | DT45: 45 | FQ45: =SUMIF($AC$11:$FP$11,FQ$12,$AC45:$FP45) -> #VALUE! | FR45: =SUMIF($AC$11:$FP$11,FR$12,$AC45:$FP45) -> #VALUE! | FS45: =SUMIF($AC$11:$FP$11,FS$12,$AC45:$FP45) -> #VALUE! | FT45: =SUMIF($AC$11:$FP$11,FT$12,$AC45:$FP45) -> #VALUE! | FU45: =SUMIF($AC$11:$FP$11,FU$12,$AC45:$FP45) -> #VALUE! | FV45: =SUMIF($AC$11:$FP$11,FV$12,$AC45:$FP45) -> #VALUE! | FW45: =SUMIF($AC$11:$FP$11,FW$12,$AC45:$FP45) -> #VALUE! | FX45: =SUMIF($AC$11:$FP$11,FX$12,$AC45:$FP45) -> #VALUE! | ... GO45: =SUMIF($AC$11:$FP$11,GO$12,$AC45:$FP45) -> #VALUE! | GP45: =SUMIF($AB$8:$FO$8,GP$9,$AB45:$FO45) -> 90 | GQ45: =SUMIF($AB$8:$FO$8,GQ$9,$AB45:$FO45) -> 45 | GR45: =SUMIF($AB$8:$FO$8,GR$9,$AB45:$FO45) -> 0 | GS45: =SUMIF($AB$8:$FO$8,GS$9,$AB45:$FO45) -> 0 | GT45: =SUMIF($AB$8:$FO$8,GT$9,$AB45:$FO45) -> 0 | GU45: =SUMIF($AB$8:$FO$8,GU$9,$AB45:$FO45) -> 0 | GV45: =SUMIF($AB$8:$FO$8,GV$9,$AB45:$FO45) -> 0 | GW45: =SUMIF($AB$8:$FO$8,GW$9,$AB45:$FO45) -> 0 | ... HE45: =SUMIF($AB$8:$FO$8,HE$9,$AB45:$FO45) -> 0 | HF45: =SUM(FQ45:HE45) -> #VALUE! | HG45: =HF45-S67 -> #VALUE!
B46: Process | C46: OTC | D46: Order Management | E46: Order Mgmt Offshore Lead | F46: India | G46: Consulting Services | H46: Enterprise Performance | I46: SAP | J46: India | K46: Package and Technology Enablement | L46: Package Functional Transformation | M46: L55 - Manager | N46: =_xlfn.CONCAT(C46,"-",D46) -> OTC-Order Management | O46: =_xlfn.CONCAT(Y46,"-",Z46,"-",F46,"-",X46) -> Technology-Manager-India-Consulting | P46: =_xlfn.CONCAT(C46," - ",Y46) -> OTC - Technology | Q46: =AB46*SUM(AZ46:ET46) -> 392040 | R46: =AB46*SUM(BC46:BN46) -> 44550 | S46: =SUM(GP46:HN46) -> 1215 | T46: =SUM(AZ46:EZ46) -> 3960 | U46: =_xlfn.CONCAT(Y46," - ",Z46) -> Technology - Manager | V46: =VLOOKUP(O46,$B$187:$H$848,4,0) -> 5-7 years | W46: =IF(F46="US", "Onshore",IF(F46="India","Offshore", "Nearshore")) -> Offshore | X46: Consulting | Y46: Technology | Z46: Manager | AA46: =[1]Resourcing!QD50 -> 0 | AB46: =IFERROR(VLOOKUP(O46,$B$187:$S$848,6,FALSE()),"combination not found") -> 99 | BE46: 45 | BF46: 45 | BG46: 45 | BH46: 45 | BI46: 45 | BJ46: 45 | BK46: 45 | BL46: 45 | BM46: 45 | BN46: 45 | BO46: 45 | BP46: 45 | BQ46: 45 | BT46: 45 | BU46: 45 | BV46: 45 | BW46: 45 | BX46: 45 | BY46: 45 | BZ46: 45 | CA46: 45 | CB46: 45 | CC46: 45 | CD46: 45 | CE46: 45 | CF46: 45 | CG46: 45 | CH46: 45 | CI46: 45 | CJ46: 45 | CK46: 45 | CL46: 45 | CM46: 45 | CN46: 45 | CO46: 45 | CP46: 45 | CQ46: 45 | CR46: 45 | CS46: 45 | CT46: 45 | CU46: 45 | CV46: 45 | CW46: 45 | CX46: 45 | CY46: 45 | CZ46: 45 | DA46: 45 | DB46: 45 | DC46: 45 | DD46: 45 | DE46: 45 | DF46: 45 | DG46: 45 | DH46: 45 | DI46: 45 | DJ46: 45 | DK46: 45 | DL46: 45 | DM46: 45 | DN46: 45 | DO46: 45 | DP46: 45 | DQ46: 45 | DT46: 45 | DU46: 45 | DV46: 45 | DW46: 45 | DX46: 45 | DY46: 45 | DZ46: 45 | EA46: 45 | EB46: 45 | EC46: 45 | ED46: 45 | EE46: 45 | EF46: 45 | EG46: 45 | EH46: 45 | EI46: 45 | EJ46: 45 | EK46: 45 | EL46: 45 | EM46: 45 | EN46: 45 | EO46: 45 | EP46: 45 | EQ46: 45 | ER46: 45 | FQ46: =SUMIF($AC$11:$FP$11,FQ$12,$AC46:$FP46) -> #VALUE! | FR46: =SUMIF($AC$11:$FP$11,FR$12,$AC46:$FP46) -> #VALUE! | FS46: =SUMIF($AC$11:$FP$11,FS$12,$AC46:$FP46) -> #VALUE! | FT46: =SUMIF($AC$11:$FP$11,FT$12,$AC46:$FP46) -> #VALUE! | FU46: =SUMIF($AC$11:$FP$11,FU$12,$AC46:$FP46) -> #VALUE! | FV46: =SUMIF($AC$11:$FP$11,FV$12,$AC46:$FP46) -> #VALUE! | FW46: =SUMIF($AC$11:$FP$11,FW$12,$AC46:$FP46) -> #VALUE! | FX46: =SUMIF($AC$11:$FP$11,FX$12,$AC46:$FP46) -> #VALUE! | ... GO46: =SUMIF($AC$11:$FP$11,GO$12,$AC46:$FP46) -> #VALUE! | GP46: =SUMIF($AB$8:$FO$8,GP$9,$AB46:$FO46) -> 90 | GQ46: =SUMIF($AB$8:$FO$8,GQ$9,$AB46:$FO46) -> 180 | GR46: =SUMIF($AB$8:$FO$8,GR$9,$AB46:$FO46) -> 180 | GS46: =SUMIF($AB$8:$FO$8,GS$9,$AB46:$FO46) -> 180 | GT46: =SUMIF($AB$8:$FO$8,GT$9,$AB46:$FO46) -> 180 | GU46: =SUMIF($AB$8:$FO$8,GU$9,$AB46:$FO46) -> 180 | GV46: =SUMIF($AB$8:$FO$8,GV$9,$AB46:$FO46) -> 180 | GW46: =SUMIF($AB$8:$FO$8,GW$9,$AB46:$FO46) -> 45 | ... HE46: =SUMIF($AB$8:$FO$8,HE$9,$AB46:$FO46) -> 0
B47: Process | C47: OTC | D47: Order Management | E47: Pricing & Vistex Integration | F47: India | G47: Consulting Services | H47: Enterprise Performance | I47: SAP | J47: India | K47: Package and Technology Enablement | L47: Package Functional Transformation | M47: L45 - Senior Consultant | N47: =_xlfn.CONCAT(C47,"-",D47) -> OTC-Order Management | O47: =_xlfn.CONCAT(Y47,"-",Z47,"-",F47,"-",X47) -> Technology-Senior Consultant-India-Consulting | P47: =_xlfn.CONCAT(C47," - ",Y47) -> OTC - Technology | Q47: =AB47*SUM(AZ47:ET47) -> 255600 | R47: =AB47*SUM(BC47:BN47) -> 0 | S47: =SUM(GP47:HN47) -> 1305 | T47: =SUM(AZ47:EZ47) -> 3600 | U47: =_xlfn.CONCAT(Y47," - ",Z47) -> Technology - Senior Consultant | V47: =VLOOKUP(O47,$B$187:$H$848,4,0) -> 3-5 years | W47: =IF(F47="US", "Onshore",IF(F47="India","Offshore", "Nearshore")) -> Offshore | X47: Consulting | Y47: Technology | Z47: Senior Consultant | AA47: =[1]Resourcing!QD51 -> 358.79278 | AB47: =IFERROR(VLOOKUP(O47,$B$187:$S$848,6,FALSE()),"combination not found") -> 71 | BO47: 45 | BP47: 45 | BQ47: 45 | BT47: 45 | BU47: 45 | BV47: 45 | BW47: 45 | BX47: 45 | BY47: 45 | BZ47: 45 | CA47: 45 | CB47: 45 | CC47: 45 | CD47: 45 | CE47: 45 | CF47: 45 | CG47: 45 | CH47: 45 | CI47: 45 | CJ47: 45 | CK47: 45 | CL47: 45 | CM47: 45 | CN47: 45 | CO47: 45 | CP47: 45 | CQ47: 45 | CR47: 45 | CS47: 45 | CT47: 45 | CU47: 45 | CV47: 45 | CW47: 45 | CX47: 45 | CY47: 45 | CZ47: 45 | DA47: 45 | DB47: 45 | DC47: 45 | DD47: 45 | DE47: 45 | DF47: 45 | DG47: 45 | DH47: 45 | DI47: 45 | DJ47: 45 | DK47: 45 | DL47: 45 | DM47: 45 | DN47: 45 | DO47: 45 | DP47: 45 | DQ47: 45 | DT47: 45 | DU47: 45 | DV47: 45 | DW47: 45 | DX47: 45 | DY47: 45 | DZ47: 45 | EA47: 45 | EB47: 45 | EC47: 45 | ED47: 45 | EE47: 45 | EF47: 45 | EG47: 45 | EH47: 45 | EI47: 45 | EJ47: 45 | EK47: 45 | EL47: 45 | EM47: 45 | EN47: 45 | EO47: 45 | EP47: 45 | EQ47: 45 | ER47: 45 | ES47: 45 | ET47: 45 | FQ47: =SUMIF($AC$11:$FP$11,FQ$12,$AC47:$FP47) -> #VALUE! | FR47: =SUMIF($AC$11:$FP$11,FR$12,$AC47:$FP47) -> #VALUE! | FS47: =SUMIF($AC$11:$FP$11,FS$12,$AC47:$FP47) -> #VALUE! | FT47: =SUMIF($AC$11:$FP$11,FT$12,$AC47:$FP47) -> #VALUE! | FU47: =SUMIF($AC$11:$FP$11,FU$12,$AC47:$FP47) -> #VALUE! | FV47: =SUMIF($AC$11:$FP$11,FV$12,$AC47:$FP47) -> #VALUE! | FW47: =SUMIF($AC$11:$FP$11,FW$12,$AC47:$FP47) -> #VALUE! | FX47: =SUMIF($AC$11:$FP$11,FX$12,$AC47:$FP47) -> #VALUE! | ... GO47: =SUMIF($AC$11:$FP$11,GO$12,$AC47:$FP47) -> #VALUE! | GP47: =SUMIF($AB$8:$FO$8,GP$9,$AB47:$FO47) -> 90 | GQ47: =SUMIF($AB$8:$FO$8,GQ$9,$AB47:$FO47) -> 180 | GR47: =SUMIF($AB$8:$FO$8,GR$9,$AB47:$FO47) -> 180 | GS47: =SUMIF($AB$8:$FO$8,GS$9,$AB47:$FO47) -> 180 | GT47: =SUMIF($AB$8:$FO$8,GT$9,$AB47:$FO47) -> 180 | GU47: =SUMIF($AB$8:$FO$8,GU$9,$AB47:$FO47) -> 180 | GV47: =SUMIF($AB$8:$FO$8,GV$9,$AB47:$FO47) -> 180 | GW47: =SUMIF($AB$8:$FO$8,GW$9,$AB47:$FO47) -> 135 | ... HE47: =SUMIF($AB$8:$FO$8,HE$9,$AB47:$FO47) -> 0
B48: Process | C48: OTC | D48: Order Management | E48: Billing | F48: India | G48: Consulting Services | H48: Enterprise Performance | I48: SAP | J48: India | K48: Package and Technology Enablement | L48: Package Functional Transformation | M48: L35 - Consultant | N48: =_xlfn.CONCAT(C48,"-",D48) -> OTC-Order Management | O48: =_xlfn.CONCAT(Y48,"-",Z48,"-",F48,"-",X48) -> Technology-Consultant-India-Consulting | P48: =_xlfn.CONCAT(C48," - ",Y48) -> OTC - Technology | Q48: =AB48*SUM(AZ48:ET48) -> 191700 | R48: =AB48*SUM(BC48:BN48) -> 0 | S48: =SUM(GP48:HN48) -> 1215 | T48: =SUM(AZ48:EZ48) -> 3195 | U48: =_xlfn.CONCAT(Y48," - ",Z48) -> Technology - Consultant | V48: =VLOOKUP(O48,$B$187:$H$848,4,0) -> 1-3 years | W48: =IF(F48="US", "Onshore",IF(F48="India","Offshore", "Nearshore")) -> Offshore | X48: Consulting | Y48: Technology | Z48: Consultant | AA48: =[1]Resourcing!QD52 -> 285.11765 | AB48: =IFERROR(VLOOKUP(O48,$B$187:$S$848,6,FALSE()),"combination not found") -> 60 | BX48: 45 | BY48: 45 | BZ48: 45 | CA48: 45 | CB48: 45 | CC48: 45 | CD48: 45 | CE48: 45 | CF48: 45 | CG48: 45 | CH48: 45 | CI48: 45 | CJ48: 45 | CK48: 45 | CL48: 45 | CM48: 45 | CN48: 45 | CO48: 45 | CP48: 45 | CQ48: 45 | CR48: 45 | CS48: 45 | CT48: 45 | CU48: 45 | CV48: 45 | CW48: 45 | CX48: 45 | CY48: 45 | CZ48: 45 | DA48: 45 | DB48: 45 | DC48: 45 | DD48: 45 | DE48: 45 | DF48: 45 | DG48: 45 | DH48: 45 | DI48: 45 | DJ48: 45 | DK48: 45 | DL48: 45 | DM48: 45 | DN48: 45 | DO48: 45 | DP48: 45 | DQ48: 45 | DT48: 45 | DU48: 45 | DV48: 45 | DW48: 45 | DX48: 45 | DY48: 45 | DZ48: 45 | EA48: 45 | EB48: 45 | EC48: 45 | ED48: 45 | EE48: 45 | EF48: 45 | EG48: 45 | EH48: 45 | EI48: 45 | EJ48: 45 | EK48: 45 | EL48: 45 | EM48: 45 | EN48: 45 | EO48: 45 | EP48: 45 | EQ48: 45 | ER48: 45 | FQ48: =SUMIF($AC$11:$FP$11,FQ$12,$AC48:$FP48) -> #VALUE! | FR48: =SUMIF($AC$11:$FP$11,FR$12,$AC48:$FP48) -> #VALUE! | FS48: =SUMIF($AC$11:$FP$11,FS$12,$AC48:$FP48) -> #VALUE! | FT48: =SUMIF($AC$11:$FP$11,FT$12,$AC48:$FP48) -> #VALUE! | FU48: =SUMIF($AC$11:$FP$11,FU$12,$AC48:$FP48) -> #VALUE! | FV48: =SUMIF($AC$11:$FP$11,FV$12,$AC48:$FP48) -> #VALUE! | FW48: =SUMIF($AC$11:$FP$11,FW$12,$AC48:$FP48) -> #VALUE! | FX48: =SUMIF($AC$11:$FP$11,FX$12,$AC48:$FP48) -> #VALUE! | ... GO48: =SUMIF($AC$11:$FP$11,GO$12,$AC48:$FP48) -> #VALUE! | GP48: =SUMIF($AB$8:$FO$8,GP$9,$AB48:$FO48) -> 90 | GQ48: =SUMIF($AB$8:$FO$8,GQ$9,$AB48:$FO48) -> 180 | GR48: =SUMIF($AB$8:$FO$8,GR$9,$AB48:$FO48) -> 180 | GS48: =SUMIF($AB$8:$FO$8,GS$9,$AB48:$FO48) -> 180 | GT48: =SUMIF($AB$8:$FO$8,GT$9,$AB48:$FO48) -> 180 | GU48: =SUMIF($AB$8:$FO$8,GU$9,$AB48:$FO48) -> 180 | GV48: =SUMIF($AB$8:$FO$8,GV$9,$AB48:$FO48) -> 180 | GW48: =SUMIF($AB$8:$FO$8,GW$9,$AB48:$FO48) -> 45 | ... HE48: =SUMIF($AB$8:$FO$8,HE$9,$AB48:$FO48) -> 0
B49: Process | C49: OTC | D49: Order Management | E49: Order Processing -Master Data | F49: India | G49: Consulting Services | H49: Enterprise Performance | I49: SAP | J49: India | K49: Package and Technology Enablement | L49: Package Functional Transformation | M49: L25 - Analyst | N49: =_xlfn.CONCAT(C49,"-",D49) -> OTC-Order Management | O49: =_xlfn.CONCAT(Y49,"-",Z49,"-",F49,"-",X49) -> Technology-Analyst-India-Consulting | P49: =_xlfn.CONCAT(C49," - ",Y49) -> OTC - Technology | Q49: =AB49*SUM(AZ49:ET49) -> 157680 | R49: =AB49*SUM(BC49:BN49) -> 0 | S49: =SUM(GP49:HN49) -> 1305 | T49: =SUM(AZ49:EZ49) -> 3285 | U49: =_xlfn.CONCAT(Y49," - ",Z49) -> Technology - Analyst | V49: =VLOOKUP(O49,$B$187:$H$848,4,0) -> 0-1 years | W49: =IF(F49="US", "Onshore",IF(F49="India","Offshore", "Nearshore")) -> Offshore | X49: Consulting | Y49: Technology | Z49: Analyst | AA49: =[1]Resourcing!QD53 -> 85.256364 | AB49: =IFERROR(VLOOKUP(O49,$B$187:$S$848,6,FALSE()),"combination not found") -> 48 | BX49: 45 | BY49: 45 | BZ49: 45 | CA49: 45 | CB49: 45 | CC49: 45 | CD49: 45 | CE49: 45 | CF49: 45 | CG49: 45 | CH49: 45 | CI49: 45 | CJ49: 45 | CK49: 45 | CL49: 45 | CM49: 45 | CN49: 45 | CO49: 45 | CP49: 45 | CQ49: 45 | CR49: 45 | CS49: 45 | CT49: 45 | CU49: 45 | CV49: 45 | CW49: 45 | CX49: 45 | CY49: 45 | CZ49: 45 | DA49: 45 | DB49: 45 | DC49: 45 | DD49: 45 | DE49: 45 | DF49: 45 | DG49: 45 | DH49: 45 | DI49: 45 | DJ49: 45 | DK49: 45 | DL49: 45 | DM49: 45 | DN49: 45 | DO49: 45 | DP49: 45 | DQ49: 45 | DT49: 45 | DU49: 45 | DV49: 45 | DW49: 45 | DX49: 45 | DY49: 45 | DZ49: 45 | EA49: 45 | EB49: 45 | EC49: 45 | ED49: 45 | EE49: 45 | EF49: 45 | EG49: 45 | EH49: 45 | EI49: 45 | EJ49: 45 | EK49: 45 | EL49: 45 | EM49: 45 | EN49: 45 | EO49: 45 | EP49: 45 | EQ49: 45 | ER49: 45 | ES49: 45 | ET49: 45 | FQ49: =SUMIF($AC$11:$FP$11,FQ$12,$AC49:$FP49) -> #VALUE! | FR49: =SUMIF($AC$11:$FP$11,FR$12,$AC49:$FP49) -> #VALUE! | FS49: =SUMIF($AC$11:$FP$11,FS$12,$AC49:$FP49) -> #VALUE! | FT49: =SUMIF($AC$11:$FP$11,FT$12,$AC49:$FP49) -> #VALUE! | FU49: =SUMIF($AC$11:$FP$11,FU$12,$AC49:$FP49) -> #VALUE! | FV49: =SUMIF($AC$11:$FP$11,FV$12,$AC49:$FP49) -> #VALUE! | FW49: =SUMIF($AC$11:$FP$11,FW$12,$AC49:$FP49) -> #VALUE! | FX49: =SUMIF($AC$11:$FP$11,FX$12,$AC49:$FP49) -> #VALUE! | ... GO49: =SUMIF($AC$11:$FP$11,GO$12,$AC49:$FP49) -> #VALUE! | GP49: =SUMIF($AB$8:$FO$8,GP$9,$AB49:$FO49) -> 90 | GQ49: =SUMIF($AB$8:$FO$8,GQ$9,$AB49:$FO49) -> 180 | GR49: =SUMIF($AB$8:$FO$8,GR$9,$AB49:$FO49) -> 180 | GS49: =SUMIF($AB$8:$FO$8,GS$9,$AB49:$FO49) -> 180 | GT49: =SUMIF($AB$8:$FO$8,GT$9,$AB49:$FO49) -> 180 | GU49: =SUMIF($AB$8:$FO$8,GU$9,$AB49:$FO49) -> 180 | GV49: =SUMIF($AB$8:$FO$8,GV$9,$AB49:$FO49) -> 180 | GW49: =SUMIF($AB$8:$FO$8,GW$9,$AB49:$FO49) -> 135 | ... HE49: =SUMIF($AB$8:$FO$8,HE$9,$AB49:$FO49) -> 0
B50: Process | C50: OTC | D50: Order Management | E50: Order Processing aATP | F50: India | G50: Consulting Services | H50: Enterprise Performance | I50: SAP | J50: India | K50: Package and Technology Enablement | L50: Package Functional Transformation | M50: L35 - Consultant | N50: =_xlfn.CONCAT(C50,"-",D50) -> OTC-Order Management | O50: =_xlfn.CONCAT(Y50,"-",Z50,"-",F50,"-",X50) -> Technology-Consultant-India-Consulting | P50: =_xlfn.CONCAT(C50," - ",Y50) -> OTC - Technology | Q50: =AB50*SUM(AZ50:ET50) -> 167400 | R50: =AB50*SUM(BC50:BN50) -> 0 | S50: =SUM(GP50:HN50) -> 810 | T50: =SUM(AZ50:EZ50) -> 2790 | U50: =_xlfn.CONCAT(Y50," - ",Z50) -> Technology - Consultant | V50: =VLOOKUP(O50,$B$187:$H$848,4,0) -> 1-3 years | W50: =IF(F50="US", "Onshore",IF(F50="India","Offshore", "Nearshore")) -> Offshore | X50: Consulting | Y50: Technology | Z50: Consultant | AA50: =[1]Resourcing!QD54 -> 62.8065 | AB50: =IFERROR(VLOOKUP(O50,$B$187:$S$848,6,FALSE()),"combination not found") -> 60 | BX50: 45 | BY50: 45 | BZ50: 45 | CA50: 45 | CB50: 45 | CC50: 45 | CD50: 45 | CE50: 45 | CF50: 45 | CG50: 45 | CH50: 45 | CI50: 45 | CJ50: 45 | CK50: 45 | CL50: 45 | CM50: 45 | CN50: 45 | CO50: 45 | CP50: 45 | CQ50: 45 | CR50: 45 | CS50: 45 | CT50: 45 | CU50: 45 | CV50: 45 | CW50: 45 | CX50: 45 | CY50: 45 | CZ50: 45 | DA50: 45 | DB50: 45 | DC50: 45 | DD50: 45 | DE50: 45 | DF50: 45 | DG50: 45 | DH50: 45 | DI50: 45 | DJ50: 45 | DK50: 45 | DL50: 45 | DM50: 45 | DN50: 45 | DO50: 45 | DP50: 45 | DQ50: 45 | DT50: 45 | DU50: 45 | DV50: 45 | DW50: 45 | DX50: 45 | DY50: 45 | DZ50: 45 | EA50: 45 | EB50: 45 | EC50: 45 | ED50: 45 | EE50: 45 | EF50: 45 | EG50: 45 | EH50: 45 | EI50: 45 | FQ50: =SUMIF($AC$11:$FP$11,FQ$12,$AC50:$FP50) -> #VALUE! | FR50: =SUMIF($AC$11:$FP$11,FR$12,$AC50:$FP50) -> #VALUE! | FS50: =SUMIF($AC$11:$FP$11,FS$12,$AC50:$FP50) -> #VALUE! | FT50: =SUMIF($AC$11:$FP$11,FT$12,$AC50:$FP50) -> #VALUE! | FU50: =SUMIF($AC$11:$FP$11,FU$12,$AC50:$FP50) -> #VALUE! | FV50: =SUMIF($AC$11:$FP$11,FV$12,$AC50:$FP50) -> #VALUE! | FW50: =SUMIF($AC$11:$FP$11,FW$12,$AC50:$FP50) -> #VALUE! | FX50: =SUMIF($AC$11:$FP$11,FX$12,$AC50:$FP50) -> #VALUE! | ... GO50: =SUMIF($AC$11:$FP$11,GO$12,$AC50:$FP50) -> #VALUE! | GP50: =SUMIF($AB$8:$FO$8,GP$9,$AB50:$FO50) -> 90 | GQ50: =SUMIF($AB$8:$FO$8,GQ$9,$AB50:$FO50) -> 180 | GR50: =SUMIF($AB$8:$FO$8,GR$9,$AB50:$FO50) -> 180 | GS50: =SUMIF($AB$8:$FO$8,GS$9,$AB50:$FO50) -> 180 | GT50: =SUMIF($AB$8:$FO$8,GT$9,$AB50:$FO50) -> 180 | GU50: =SUMIF($AB$8:$FO$8,GU$9,$AB50:$FO50) -> 0 | GV50: =SUMIF($AB$8:$FO$8,GV$9,$AB50:$FO50) -> 0 | GW50: =SUMIF($AB$8:$FO$8,GW$9,$AB50:$FO50) -> 0 | ... HE50: =SUMIF($AB$8:$FO$8,HE$9,$AB50:$FO50) -> 0
B51: Process | C51: S&R | D51: Service Management | E51: Service Management Lead | F51: US | G51: Consulting Services | H51: Enterprise Performance | I51: SAP | J51: US | K51: Package and Technology Enablement | L51: Package Functional Transformation | M51: L45 - Senior Consultant | N51: =_xlfn.CONCAT(C51,"-",D51) -> S&R-Service Management | O51: =_xlfn.CONCAT(Y51,"-",Z51,"-",F51,"-",X51) -> Technology-Senior Consultant-US-Consulting | P51: =_xlfn.CONCAT(C51," - ",Y51) -> S&R - Technology | Q51: =AB51*SUM(AZ51:ET51) -> 889200 | R51: =AB51*SUM(BC51:BN51) -> 117000 | S51: =SUM(GP51:HN51) -> 0 | T51: =SUM(AZ51:EZ51) -> 3420 | U51: =_xlfn.CONCAT(Y51," - ",Z51) -> Technology - Senior Consultant | V51: =VLOOKUP(O51,$B$187:$H$848,4,0) -> 3-5 years | W51: =IF(F51="US", "Onshore",IF(F51="India","Offshore", "Nearshore")) -> Onshore | X51: Consulting | Y51: Technology | Z51: Senior Consultant | AA51: =[1]Resourcing!QD55 -> 53.509859 | AB51: =IFERROR(VLOOKUP(O51,$B$187:$S$848,6,FALSE()),"combination not found") -> 260 | BE51: 45 | BF51: 45 | BG51: 45 | BH51: 45 | BI51: 45 | BJ51: 45 | BK51: 45 | BL51: 45 | BM51: 45 | BN51: 45 | BO51: 45 | BP51: 45 | BQ51: 45 | BT51: 45 | BU51: 45 | BV51: 45 | BW51: 45 | BX51: 45 | BY51: 45 | BZ51: 45 | CA51: 45 | CB51: 45 | CC51: 45 | CD51: 45 | CE51: 45 | CF51: 45 | CG51: 45 | CH51: 45 | CI51: 45 | CJ51: 45 | CK51: 45 | CL51: 45 | CM51: 45 | CN51: 45 | CO51: 45 | CP51: 45 | CQ51: 45 | CR51: 45 | CS51: 45 | CT51: 45 | CU51: 45 | CV51: 45 | CW51: 45 | CX51: 45 | CY51: 45 | CZ51: 45 | DA51: 45 | DB51: 45 | DC51: 45 | DD51: 45 | DE51: 45 | DF51: 45 | DG51: 45 | DH51: 45 | DI51: 45 | DJ51: 45 | DK51: 45 | DL51: 45 | DM51: 45 | DN51: 45 | DO51: 45 | DP51: 45 | DQ51: 45 | DT51: 45 | DU51: 45 | DV51: 45 | DW51: 45 | DX51: 45 | DY51: 45 | DZ51: 45 | EA51: 45 | EB51: 45 | EC51: 45 | ED51: 45 | EE51: 45 | EF51: 45 | FQ51: =SUMIF($AC$11:$FP$11,FQ$12,$AC51:$FP51) -> #VALUE! | FR51: =SUMIF($AC$11:$FP$11,FR$12,$AC51:$FP51) -> #VALUE! | FS51: =SUMIF($AC$11:$FP$11,FS$12,$AC51:$FP51) -> #VALUE! | FT51: =SUMIF($AC$11:$FP$11,FT$12,$AC51:$FP51) -> #VALUE! | FU51: =SUMIF($AC$11:$FP$11,FU$12,$AC51:$FP51) -> #VALUE! | FV51: =SUMIF($AC$11:$FP$11,FV$12,$AC51:$FP51) -> #VALUE! | FW51: =SUMIF($AC$11:$FP$11,FW$12,$AC51:$FP51) -> #VALUE! | FX51: =SUMIF($AC$11:$FP$11,FX$12,$AC51:$FP51) -> #VALUE! | ... GO51: =SUMIF($AC$11:$FP$11,GO$12,$AC51:$FP51) -> #VALUE!
B52: Process | C52: S&R | D52: Service Management | E52: Service-Inhouse Repair | F52: India | G52: Consulting Services | H52: Enterprise Performance | I52: SAP | J52: India | K52: Package and Technology Enablement | L52: Package Functional Transformation | M52: L45 - Senior Consultant | N52: =_xlfn.CONCAT(C52,"-",D52) -> S&R-Service Management | O52: =_xlfn.CONCAT(Y52,"-",Z52,"-",F52,"-",X52) -> Technology-Consultant-India-Consulting | P52: =_xlfn.CONCAT(C52," - ",Y52) -> S&R - Technology | Q52: =AB52*SUM(AZ52:ET52) -> 237600 | R52: =AB52*SUM(BC52:BN52) -> 21600 | S52: =SUM(GP52:HN52) -> 1305 | T52: =SUM(AZ52:EZ52) -> 3960 | U52: =_xlfn.CONCAT(Y52," - ",Z52) -> Technology - Consultant | V52: =VLOOKUP(O52,$B$187:$H$848,4,0) -> 1-3 years | W52: =IF(F52="US", "Onshore",IF(F52="India","Offshore", "Nearshore")) -> Offshore | X52: Consulting | Y52: Technology | Z52: Consultant | AA52: =[1]Resourcing!QD56 -> 43.101644 | AB52: =IFERROR(VLOOKUP(O52,$B$187:$S$848,6,FALSE()),"combination not found") -> 60 | BG52: 45 | BH52: 45 | BI52: 45 | BJ52: 45 | BK52: 45 | BL52: 45 | BM52: 45 | BN52: 45 | BO52: 45 | BP52: 45 | BQ52: 45 | BT52: 45 | BU52: 45 | BV52: 45 | BW52: 45 | BX52: 45 | BY52: 45 | BZ52: 45 | CA52: 45 | CB52: 45 | CC52: 45 | CD52: 45 | CE52: 45 | CF52: 45 | CG52: 45 | CH52: 45 | CI52: 45 | CJ52: 45 | CK52: 45 | CL52: 45 | CM52: 45 | CN52: 45 | CO52: 45 | CP52: 45 | CQ52: 45 | CR52: 45 | CS52: 45 | CT52: 45 | CU52: 45 | CV52: 45 | CW52: 45 | CX52: 45 | CY52: 45 | CZ52: 45 | DA52: 45 | DB52: 45 | DC52: 45 | DD52: 45 | DE52: 45 | DF52: 45 | DG52: 45 | DH52: 45 | DI52: 45 | DJ52: 45 | DK52: 45 | DL52: 45 | DM52: 45 | DN52: 45 | DO52: 45 | DP52: 45 | DQ52: 45 | DT52: 45 | DU52: 45 | DV52: 45 | DW52: 45 | DX52: 45 | DY52: 45 | DZ52: 45 | EA52: 45 | EB52: 45 | EC52: 45 | ED52: 45 | EE52: 45 | EF52: 45 | EG52: 45 | EH52: 45 | EI52: 45 | EJ52: 45 | EK52: 45 | EL52: 45 | EM52: 45 | EN52: 45 | EO52: 45 | EP52: 45 | EQ52: 45 | ER52: 45 | ES52: 45 | ET52: 45 | FQ52: =SUMIF($AC$11:$FP$11,FQ$12,$AC52:$FP52) -> #VALUE! | FR52: =SUMIF($AC$11:$FP$11,FR$12,$AC52:$FP52) -> #VALUE! | FS52: =SUMIF($AC$11:$FP$11,FS$12,$AC52:$FP52) -> #VALUE! | FT52: =SUMIF($AC$11:$FP$11,FT$12,$AC52:$FP52) -> #VALUE! | FU52: =SUMIF($AC$11:$FP$11,FU$12,$AC52:$FP52) -> #VALUE! | FV52: =SUMIF($AC$11:$FP$11,FV$12,$AC52:$FP52) -> #VALUE! | FW52: =SUMIF($AC$11:$FP$11,FW$12,$AC52:$FP52) -> #VALUE! | FX52: =SUMIF($AC$11:$FP$11,FX$12,$AC52:$FP52) -> #VALUE! | ... GO52: =SUMIF($AC$11:$FP$11,GO$12,$AC52:$FP52) -> #VALUE! | GP52: =SUMIF($AB$8:$FO$8,GP$9,$AB52:$FO52) -> 90 | GQ52: =SUMIF($AB$8:$FO$8,GQ$9,$AB52:$FO52) -> 180 | GR52: =SUMIF($AB$8:$FO$8,GR$9,$AB52:$FO52) -> 180 | GS52: =SUMIF($AB$8:$FO$8,GS$9,$AB52:$FO52) -> 180 | GT52: =SUMIF($AB$8:$FO$8,GT$9,$AB52:$FO52) -> 180 | GU52: =SUMIF($AB$8:$FO$8,GU$9,$AB52:$FO52) -> 180 | GV52: =SUMIF($AB$8:$FO$8,GV$9,$AB52:$FO52) -> 180 | GW52: =SUMIF($AB$8:$FO$8,GW$9,$AB52:$FO52) -> 135 | ... HE52: =SUMIF($AB$8:$FO$8,HE$9,$AB52:$FO52) -> 0
B53: Process | C53: S&R | D53: Service Management | E53: Service - Loaners & Field Service | F53: India | G53: Consulting Services | H53: Enterprise Performance | I53: SAP | J53: India | K53: Package and Technology Enablement | L53: Package Functional Transformation | M53: L25 - Analyst | N53: =_xlfn.CONCAT(C53,"-",D53) -> S&R-Service Management | O53: =_xlfn.CONCAT(Y53,"-",Z53,"-",F53,"-",X53) -> Technology-Consultant-India-Consulting | P53: =_xlfn.CONCAT(C53," - ",Y53) -> S&R - Technology | Q53: =AB53*SUM(AZ53:ET53) -> 191700 | R53: =AB53*SUM(BC53:BN53) -> 0 | S53: =SUM(GP53:HN53) -> 1215 | T53: =SUM(AZ53:EZ53) -> 3195 | U53: =_xlfn.CONCAT(Y53," - ",Z53) -> Technology - Consultant | V53: =VLOOKUP(O53,$B$187:$H$848,4,0) -> 1-3 years | W53: =IF(F53="US", "Onshore",IF(F53="India","Offshore", "Nearshore")) -> Offshore | X53: Consulting | Y53: Technology | Z53: Consultant | AA53: =[1]Resourcing!QD57 -> 53.220968 | AB53: =IFERROR(VLOOKUP(O53,$B$187:$S$848,6,FALSE()),"combination not found") -> 60 | BX53: 45 | BY53: 45 | BZ53: 45 | CA53: 45 | CB53: 45 | CC53: 45 | CD53: 45 | CE53: 45 | CF53: 45 | CG53: 45 | CH53: 45 | CI53: 45 | CJ53: 45 | CK53: 45 | CL53: 45 | CM53: 45 | CN53: 45 | CO53: 45 | CP53: 45 | CQ53: 45 | CR53: 45 | CS53: 45 | CT53: 45 | CU53: 45 | CV53: 45 | CW53: 45 | CX53: 45 | CY53: 45 | CZ53: 45 | DA53: 45 | DB53: 45 | DC53: 45 | DD53: 45 | DE53: 45 | DF53: 45 | DG53: 45 | DH53: 45 | DI53: 45 | DJ53: 45 | DK53: 45 | DL53: 45 | DM53: 45 | DN53: 45 | DO53: 45 | DP53: 45 | DQ53: 45 | DT53: 45 | DU53: 45 | DV53: 45 | DW53: 45 | DX53: 45 | DY53: 45 | DZ53: 45 | EA53: 45 | EB53: 45 | EC53: 45 | ED53: 45 | EE53: 45 | EF53: 45 | EG53: 45 | EH53: 45 | EI53: 45 | EJ53: 45 | EK53: 45 | EL53: 45 | EM53: 45 | EN53: 45 | EO53: 45 | EP53: 45 | EQ53: 45 | ER53: 45 | FQ53: =SUMIF($AC$11:$FP$11,FQ$12,$AC53:$FP53) -> #VALUE! | FR53: =SUMIF($AC$11:$FP$11,FR$12,$AC53:$FP53) -> #VALUE! | FS53: =SUMIF($AC$11:$FP$11,FS$12,$AC53:$FP53) -> #VALUE! | FT53: =SUMIF($AC$11:$FP$11,FT$12,$AC53:$FP53) -> #VALUE! | FU53: =SUMIF($AC$11:$FP$11,FU$12,$AC53:$FP53) -> #VALUE! | FV53: =SUMIF($AC$11:$FP$11,FV$12,$AC53:$FP53) -> #VALUE! | FW53: =SUMIF($AC$11:$FP$11,FW$12,$AC53:$FP53) -> #VALUE! | FX53: =SUMIF($AC$11:$FP$11,FX$12,$AC53:$FP53) -> #VALUE! | ... GO53: =SUMIF($AC$11:$FP$11,GO$12,$AC53:$FP53) -> #VALUE! | GP53: =SUMIF($AB$8:$FO$8,GP$9,$AB53:$FO53) -> 90 | GQ53: =SUMIF($AB$8:$FO$8,GQ$9,$AB53:$FO53) -> 180 | GR53: =SUMIF($AB$8:$FO$8,GR$9,$AB53:$FO53) -> 180 | GS53: =SUMIF($AB$8:$FO$8,GS$9,$AB53:$FO53) -> 180 | GT53: =SUMIF($AB$8:$FO$8,GT$9,$AB53:$FO53) -> 180 | GU53: =SUMIF($AB$8:$FO$8,GU$9,$AB53:$FO53) -> 180 | GV53: =SUMIF($AB$8:$FO$8,GV$9,$AB53:$FO53) -> 180 | GW53: =SUMIF($AB$8:$FO$8,GW$9,$AB53:$FO53) -> 45 | ... HE53: =SUMIF($AB$8:$FO$8,HE$9,$AB53:$FO53) -> 0
B54: Process | C54: S&R | D54: Service Management | E54: EAM - Installed base & Asset Management | F54: India | G54: Consulting Services | H54: Enterprise Performance | I54: SAP | J54: India | K54: Package and Technology Enablement | L54: Package Functional Transformation | M54: L35 - Consultant | N54: =_xlfn.CONCAT(C54,"-",D54) -> S&R-Service Management | O54: =_xlfn.CONCAT(Y54,"-",Z54,"-",F54,"-",X54) -> Technology-Consultant-India-Consulting | P54: =_xlfn.CONCAT(C54," - ",Y54) -> S&R - Technology | Q54: =AB54*SUM(AZ54:ET54) -> 197100 | R54: =AB54*SUM(BC54:BN54) -> 0 | S54: =SUM(GP54:HN54) -> 1305 | T54: =SUM(AZ54:EZ54) -> 3285 | U54: =_xlfn.CONCAT(Y54," - ",Z54) -> Technology - Consultant | V54: =VLOOKUP(O54,$B$187:$H$848,4,0) -> 1-3 years | W54: =IF(F54="US", "Onshore",IF(F54="India","Offshore", "Nearshore")) -> Offshore | X54: Consulting | Y54: Technology | Z54: Consultant | AA54: =[1]Resourcing!QD58 -> 320.32895 | AB54: =IFERROR(VLOOKUP(O54,$B$187:$S$848,6,FALSE()),"combination not found") -> 60 | BX54: 45 | BY54: 45 | BZ54: 45 | CA54: 45 | CB54: 45 | CC54: 45 | CD54: 45 | CE54: 45 | CF54: 45 | CG54: 45 | CH54: 45 | CI54: 45 | CJ54: 45 | CK54: 45 | CL54: 45 | CM54: 45 | CN54: 45 | CO54: 45 | CP54: 45 | CQ54: 45 | CR54: 45 | CS54: 45 | CT54: 45 | CU54: 45 | CV54: 45 | CW54: 45 | CX54: 45 | CY54: 45 | CZ54: 45 | DA54: 45 | DB54: 45 | DC54: 45 | DD54: 45 | DE54: 45 | DF54: 45 | DG54: 45 | DH54: 45 | DI54: 45 | DJ54: 45 | DK54: 45 | DL54: 45 | DM54: 45 | DN54: 45 | DO54: 45 | DP54: 45 | DQ54: 45 | DT54: 45 | DU54: 45 | DV54: 45 | DW54: 45 | DX54: 45 | DY54: 45 | DZ54: 45 | EA54: 45 | EB54: 45 | EC54: 45 | ED54: 45 | EE54: 45 | EF54: 45 | EG54: 45 | EH54: 45 | EI54: 45 | EJ54: 45 | EK54: 45 | EL54: 45 | EM54: 45 | EN54: 45 | EO54: 45 | EP54: 45 | EQ54: 45 | ER54: 45 | ES54: 45 | ET54: 45 | FQ54: =SUMIF($AC$11:$FP$11,FQ$12,$AC54:$FP54) -> #VALUE! | FR54: =SUMIF($AC$11:$FP$11,FR$12,$AC54:$FP54) -> #VALUE! | FS54: =SUMIF($AC$11:$FP$11,FS$12,$AC54:$FP54) -> #VALUE! | FT54: =SUMIF($AC$11:$FP$11,FT$12,$AC54:$FP54) -> #VALUE! | FU54: =SUMIF($AC$11:$FP$11,FU$12,$AC54:$FP54) -> #VALUE! | FV54: =SUMIF($AC$11:$FP$11,FV$12,$AC54:$FP54) -> #VALUE! | FW54: =SUMIF($AC$11:$FP$11,FW$12,$AC54:$FP54) -> #VALUE! | FX54: =SUMIF($AC$11:$FP$11,FX$12,$AC54:$FP54) -> #VALUE! | ... GO54: =SUMIF($AC$11:$FP$11,GO$12,$AC54:$FP54) -> #VALUE! | GP54: =SUMIF($AB$8:$FO$8,GP$9,$AB54:$FO54) -> 90 | GQ54: =SUMIF($AB$8:$FO$8,GQ$9,$AB54:$FO54) -> 180 | GR54: =SUMIF($AB$8:$FO$8,GR$9,$AB54:$FO54) -> 180 | GS54: =SUMIF($AB$8:$FO$8,GS$9,$AB54:$FO54) -> 180 | GT54: =SUMIF($AB$8:$FO$8,GT$9,$AB54:$FO54) -> 180 | GU54: =SUMIF($AB$8:$FO$8,GU$9,$AB54:$FO54) -> 180 | GV54: =SUMIF($AB$8:$FO$8,GV$9,$AB54:$FO54) -> 180 | GW54: =SUMIF($AB$8:$FO$8,GW$9,$AB54:$FO54) -> 135 | ... HE54: =SUMIF($AB$8:$FO$8,HE$9,$AB54:$FO54) -> 0
Q55: =AB55*SUM(AZ55:ET55) -> 0 | R55: =AB55*SUM(BC55:BN55) -> 0 | T55: =SUM(AZ55:EZ55) -> 0 | AA55: =[1]Resourcing!QD59 -> 62.551364 | FQ55: =SUMIF($AC$11:$FP$11,FQ$12,$AC55:$FP55) -> #VALUE! | FR55: =SUMIF($AC$11:$FP$11,FR$12,$AC55:$FP55) -> #VALUE! | FS55: =SUMIF($AC$11:$FP$11,FS$12,$AC55:$FP55) -> #VALUE! | FT55: =SUMIF($AC$11:$FP$11,FT$12,$AC55:$FP55) -> #VALUE! | FU55: =SUMIF($AC$11:$FP$11,FU$12,$AC55:$FP55) -> #VALUE! | FV55: =SUMIF($AC$11:$FP$11,FV$12,$AC55:$FP55) -> #VALUE! | FW55: =SUMIF($AC$11:$FP$11,FW$12,$AC55:$FP55) -> #VALUE! | FX55: =SUMIF($AC$11:$FP$11,FX$12,$AC55:$FP55) -> #VALUE! | ... GO55: =SUMIF($AC$11:$FP$11,GO$12,$AC55:$FP55) -> #VALUE! | GP55: =SUMIF($AB$8:$FO$8,GP$9,$AB55:$FO55) -> 0 | GQ55: =SUMIF($AB$8:$FO$8,GQ$9,$AB55:$FO55) -> 0 | GR55: =SUMIF($AB$8:$FO$8,GR$9,$AB55:$FO55) -> 0 | GS55: =SUMIF($AB$8:$FO$8,GS$9,$AB55:$FO55) -> 0 | GT55: =SUMIF($AB$8:$FO$8,GT$9,$AB55:$FO55) -> 0 | GU55: =SUMIF($AB$8:$FO$8,GU$9,$AB55:$FO55) -> 0 | GV55: =SUMIF($AB$8:$FO$8,GV$9,$AB55:$FO55) -> 0 | GW55: =SUMIF($AB$8:$FO$8,GW$9,$AB55:$FO55) -> 0 | ... HE55: =SUMIF($AB$8:$FO$8,HE$9,$AB55:$FO55) -> 0
B56: Process | C56: PTP | D56: Procurement | E56: PTP Overall Lead | F56: US | G56: Consulting Services | H56: Enterprise Performance | I56: SAP | J56: US | K56: Package and Technology Enablement | L56: Package Functional Transformation | M56: L55 - Manager | N56: =_xlfn.CONCAT(C56,"-",D56) -> PTP-Procurement | O56: =_xlfn.CONCAT(Y56,"-",Z56,"-",F56,"-",X56) -> Technology-Manager-US-Consulting | P56: =_xlfn.CONCAT(C56," - ",Y56) -> PTP - Technology | Q56: =AB56*SUM(AZ56:ET56) -> 1101600 | R56: =AB56*SUM(BC56:BN56) -> 134640 | S56: =SUM(GP56:HN56) -> 0 | T56: =SUM(AZ56:EZ56) -> 3600 | U56: =_xlfn.CONCAT(Y56," - ",Z56) -> Technology - Manager | V56: =VLOOKUP(O56,$B$187:$H$848,4,0) -> 5-7 years | W56: =IF(F56="US", "Onshore",IF(F56="India","Offshore", "Nearshore")) -> Onshore | X56: Consulting | Y56: Technology | Z56: Manager | AA56: =[1]Resourcing!QD60 -> 43.018028 | AB56: =IFERROR(VLOOKUP(O56,$B$187:$S$848,6,FALSE()),"combination not found") -> 306 | BD56: 40 | BE56: 40 | BF56: 40 | BG56: 40 | BH56: 40 | BI56: 40 | BJ56: 40 | BK56: 40 | BL56: 40 | BM56: 40 | BN56: 40 | BO56: 40 | BP56: 40 | BQ56: 40 | BT56: 40 | BU56: 40 | BV56: 40 | BW56: 40 | BX56: 40 | BY56: 40 | BZ56: 40 | CA56: 40 | CB56: 40 | CC56: 40 | CD56: 40 | CE56: 40 | CF56: 40 | CG56: 40 | CH56: 40 | CI56: 40 | CJ56: 40 | CK56: 40 | CL56: 40 | CM56: 40 | CN56: 40 | CO56: 40 | CP56: 40 | CQ56: 40 | CR56: 40 | CS56: 40 | CT56: 40 | CU56: 40 | CV56: 40 | CW56: 40 | CX56: 40 | CY56: 40 | CZ56: 40 | DA56: 40 | DB56: 40 | DC56: 40 | DD56: 40 | DE56: 40 | DF56: 40 | DG56: 40 | DH56: 40 | DI56: 40 | DJ56: 40 | DK56: 40 | DL56: 40 | DM56: 40 | DN56: 40 | DO56: 40 | DP56: 40 | DQ56: 40 | DT56: 40 | DU56: 40 | DV56: 40 | DW56: 40 | DX56: 40 | DY56: 40 | DZ56: 40 | EA56: 40 | EB56: 40 | EC56: 40 | ED56: 40 | EE56: 40 | EF56: 40 | EG56: 40 | EH56: 40 | EI56: 40 | EJ56: 40 | EK56: 40 | EL56: 40 | EM56: 40 | EN56: 40 | EO56: 40 | EP56: 40 | EQ56: 40 | ER56: 40 | ES56: 40 | FQ56: =SUMIF($AC$11:$FP$11,FQ$12,$AC56:$FP56) -> #VALUE! | FR56: =SUMIF($AC$11:$FP$11,FR$12,$AC56:$FP56) -> #VALUE! | FS56: =SUMIF($AC$11:$FP$11,FS$12,$AC56:$FP56) -> #VALUE! | FT56: =SUMIF($AC$11:$FP$11,FT$12,$AC56:$FP56) -> #VALUE! | FU56: =SUMIF($AC$11:$FP$11,FU$12,$AC56:$FP56) -> #VALUE! | FV56: =SUMIF($AC$11:$FP$11,FV$12,$AC56:$FP56) -> #VALUE! | FW56: =SUMIF($AC$11:$FP$11,FW$12,$AC56:$FP56) -> #VALUE! | FX56: =SUMIF($AC$11:$FP$11,FX$12,$AC56:$FP56) -> #VALUE! | ... GO56: =SUMIF($AC$11:$FP$11,GO$12,$AC56:$FP56) -> #VALUE!
B57: Process | C57: PTP | D57: Procurement | E57: PTP Offshore Lead | F57: India | G57: Consulting Services | H57: Enterprise Performance | I57: SAP | J57: India | K57: Package and Technology Enablement | L57: Package Functional Transformation | M57: L45 - Senior Consultant | N57: =_xlfn.CONCAT(C57,"-",D57) -> PTP-Procurement | O57: =_xlfn.CONCAT(Y57,"-",Z57,"-",F57,"-",X57) -> Technology-Senior Consultant-India-Consulting | P57: =_xlfn.CONCAT(C57," - ",Y57) -> PTP - Technology | Q57: =AB57*SUM(AZ57:ET57) -> 287550 | R57: =AB57*SUM(BC57:BN57) -> 35145 | S57: =SUM(GP57:HN57) -> #VALUE! | T57: =SUM(AZ57:EZ57) -> 4050 | U57: =_xlfn.CONCAT(Y57," - ",Z57) -> Technology - Senior Consultant | V57: =VLOOKUP(O57,$B$187:$H$848,4,0) -> 3-5 years | W57: =IF(F57="US", "Onshore",IF(F57="India","Offshore", "Nearshore")) -> Offshore | X57: Consulting | Y57: Technology | Z57: Senior Consultant | AA57: =[1]Resourcing!QD61 -> 53.613699 | AB57: =IFERROR(VLOOKUP(O57,$B$187:$S$848,6,FALSE()),"combination not found") -> 71 | BD57: 45 | BE57: 45 | BF57: 45 | BG57: 45 | BH57: 45 | BI57: 45 | BJ57: 45 | BK57: 45 | BL57: 45 | BM57: 45 | BN57: 45 | BO57: 45 | BP57: 45 | BQ57: 45 | BT57: 45 | BU57: 45 | BV57: 45 | BW57: 45 | BX57: 45 | BY57: 45 | BZ57: 45 | CA57: 45 | CB57: 45 | CC57: 45 | CD57: 45 | CE57: 45 | CF57: 45 | CG57: 45 | CH57: 45 | CI57: 45 | CJ57: 45 | CK57: 45 | CL57: 45 | CM57: 45 | CN57: 45 | CO57: 45 | CP57: 45 | CQ57: 45 | CR57: 45 | CS57: 45 | CT57: 45 | CU57: 45 | CV57: 45 | CW57: 45 | CX57: 45 | CY57: 45 | CZ57: 45 | DA57: 45 | DB57: 45 | DC57: 45 | DD57: 45 | DE57: 45 | DF57: 45 | DG57: 45 | DH57: 45 | DI57: 45 | DJ57: 45 | DK57: 45 | DL57: 45 | DM57: 45 | DN57: 45 | DO57: 45 | DP57: 45 | DQ57: 45 | DT57: 45 | DU57: 45 | DV57: 45 | DW57: 45 | DX57: 45 | DY57: 45 | DZ57: 45 | EA57: 45 | EB57: 45 | EC57: 45 | ED57: 45 | EE57: 45 | EF57: 45 | EG57: 45 | EH57: 45 | EI57: 45 | EJ57: 45 | EK57: 45 | EL57: 45 | EM57: 45 | EN57: 45 | EO57: 45 | EP57: 45 | EQ57: 45 | ER57: 45 | ES57: 45 | FQ57: =SUMIF($AC$11:$FP$11,FQ$12,$AC57:$FP57) -> #VALUE! | FR57: =SUMIF($AC$11:$FP$11,FR$12,$AC57:$FP57) -> #VALUE! | FS57: =SUMIF($AC$11:$FP$11,FS$12,$AC57:$FP57) -> #VALUE! | FT57: =SUMIF($AC$11:$FP$11,FT$12,$AC57:$FP57) -> #VALUE! | FU57: =SUMIF($AC$11:$FP$11,FU$12,$AC57:$FP57) -> #VALUE! | FV57: =SUMIF($AC$11:$FP$11,FV$12,$AC57:$FP57) -> #VALUE! | FW57: =SUMIF($AC$11:$FP$11,FW$12,$AC57:$FP57) -> #VALUE! | FX57: =SUMIF($AC$11:$FP$11,FX$12,$AC57:$FP57) -> #VALUE! | ... GO57: =SUMIF($AC$11:$FP$11,GO$12,$AC57:$FP57) -> #VALUE! | GP57: =SUMIF($AB$8:$FO$8,GP$9,$AB57:$FO57) -> 90 | GQ57: =SUMIF($AB$8:$FO$8,GQ$9,$AB57:$FO57) -> 180 | GR57: =SUMIF($AB$8:$FO$8,GR$9,$AB57:$FO57) -> 180 | GS57: =SUMIF($AB$8:$FO$8,GS$9,$AB57:$FO57) -> 180 | GT57: =SUMIF($AB$8:$FO$8,GT$9,$AB57:$FO57) -> 180 | GU57: =SUMIF($AB$8:$FO$8,GU$9,$AB57:$FO57) -> 180 | GV57: =SUMIF($AB$8:$FO$8,GV$9,$AB57:$FO57) -> 180 | GW57: =SUMIF($AB$8:$FO$8,GW$9,$AB57:$FO57) -> 90 | ... HE57: =SUMIF($AB$8:$FO$8,HE$9,$AB57:$FO57) -> 0 | HF57: =SUM(FQ57:HE57) -> #VALUE! | HG57: =HF57-#REF! -> #REF!
B58: Process | C58: PTP | D58: Accounts Payable | E58: PTP Offshore AP/Banking SME | F58: India | G58: Consulting Services | H58: Enterprise Performance | I58: SAP | J58: India | K58: Package and Technology Enablement | L58: Package Functional Transformation | M58: L45 - Senior Consultant | N58: =_xlfn.CONCAT(C58,"-",D58) -> PTP-Accounts Payable | O58: =_xlfn.CONCAT(Y58,"-",Z58,"-",F58,"-",X58) -> Technology-Senior Consultant-India-Consulting | P58: =_xlfn.CONCAT(C58," - ",Y58) -> PTP - Technology | Q58: =AB58*SUM(AZ58:ET58) -> 287550 | R58: =AB58*SUM(BC58:BN58) -> 35145 | S58: =SUM(GP58:HN58) -> #VALUE! | T58: =SUM(AZ58:EZ58) -> 4050 | U58: =_xlfn.CONCAT(Y58," - ",Z58) -> Technology - Senior Consultant | V58: =VLOOKUP(O58,$B$187:$H$848,4,0) -> 3-5 years | W58: =IF(F58="US", "Onshore",IF(F58="India","Offshore", "Nearshore")) -> Offshore | X58: Consulting | Y58: Technology | Z58: Senior Consultant | AA58: =[1]Resourcing!QD62 -> 0 | AB58: =IFERROR(VLOOKUP(O58,$B$187:$S$848,6,FALSE()),"combination not found") -> 71 | BD58: 45 | BE58: 45 | BF58: 45 | BG58: 45 | BH58: 45 | BI58: 45 | BJ58: 45 | BK58: 45 | BL58: 45 | BM58: 45 | BN58: 45 | BO58: 45 | BP58: 45 | BQ58: 45 | BT58: 45 | BU58: 45 | BV58: 45 | BW58: 45 | BX58: 45 | BY58: 45 | BZ58: 45 | CA58: 45 | CB58: 45 | CC58: 45 | CD58: 45 | CE58: 45 | CF58: 45 | CG58: 45 | CH58: 45 | CI58: 45 | CJ58: 45 | CK58: 45 | CL58: 45 | CM58: 45 | CN58: 45 | CO58: 45 | CP58: 45 | CQ58: 45 | CR58: 45 | CS58: 45 | CT58: 45 | CU58: 45 | CV58: 45 | CW58: 45 | CX58: 45 | CY58: 45 | CZ58: 45 | DA58: 45 | DB58: 45 | DC58: 45 | DD58: 45 | DE58: 45 | DF58: 45 | DG58: 45 | DH58: 45 | DI58: 45 | DJ58: 45 | DK58: 45 | DL58: 45 | DM58: 45 | DN58: 45 | DO58: 45 | DP58: 45 | DQ58: 45 | DT58: 45 | DU58: 45 | DV58: 45 | DW58: 45 | DX58: 45 | DY58: 45 | DZ58: 45 | EA58: 45 | EB58: 45 | EC58: 45 | ED58: 45 | EE58: 45 | EF58: 45 | EG58: 45 | EH58: 45 | EI58: 45 | EJ58: 45 | EK58: 45 | EL58: 45 | EM58: 45 | EN58: 45 | EO58: 45 | EP58: 45 | EQ58: 45 | ER58: 45 | ES58: 45 | FQ58: =SUMIF($AC$11:$FP$11,FQ$12,$AC58:$FP58) -> #VALUE! | FR58: =SUMIF($AC$11:$FP$11,FR$12,$AC58:$FP58) -> #VALUE! | FS58: =SUMIF($AC$11:$FP$11,FS$12,$AC58:$FP58) -> #VALUE! | FT58: =SUMIF($AC$11:$FP$11,FT$12,$AC58:$FP58) -> #VALUE! | FU58: =SUMIF($AC$11:$FP$11,FU$12,$AC58:$FP58) -> #VALUE! | FV58: =SUMIF($AC$11:$FP$11,FV$12,$AC58:$FP58) -> #VALUE! | FW58: =SUMIF($AC$11:$FP$11,FW$12,$AC58:$FP58) -> #VALUE! | FX58: =SUMIF($AC$11:$FP$11,FX$12,$AC58:$FP58) -> #VALUE! | ... GO58: =SUMIF($AC$11:$FP$11,GO$12,$AC58:$FP58) -> #VALUE! | GP58: =SUMIF($AB$8:$FO$8,GP$9,$AB58:$FO58) -> 90 | GQ58: =SUMIF($AB$8:$FO$8,GQ$9,$AB58:$FO58) -> 180 | GR58: =SUMIF($AB$8:$FO$8,GR$9,$AB58:$FO58) -> 180 | GS58: =SUMIF($AB$8:$FO$8,GS$9,$AB58:$FO58) -> 180 | GT58: =SUMIF($AB$8:$FO$8,GT$9,$AB58:$FO58) -> 180 | GU58: =SUMIF($AB$8:$FO$8,GU$9,$AB58:$FO58) -> 180 | GV58: =SUMIF($AB$8:$FO$8,GV$9,$AB58:$FO58) -> 180 | GW58: =SUMIF($AB$8:$FO$8,GW$9,$AB58:$FO58) -> 90 | ... HE58: =SUMIF($AB$8:$FO$8,HE$9,$AB58:$FO58) -> 0 | HF58: =SUM(FQ58:HE58) -> #VALUE! | HG58: =HF58-S111 -> #VALUE!
B59: Process | C59: PTP | D59: Procurement | E59: PTP Offshore Procurement Support | F59: India | G59: Consulting Services | H59: Enterprise Performance | I59: SAP | J59: India | K59: Package and Technology Enablement | L59: Package Functional Transformation | M59: L35 - Consultant | N59: =_xlfn.CONCAT(C59,"-",D59) -> PTP-Procurement | O59: =_xlfn.CONCAT(Y59,"-",Z59,"-",F59,"-",X59) -> Technology-Consultant-India-Consulting | P59: =_xlfn.CONCAT(C59," - ",Y59) -> PTP - Technology | Q59: =AB59*SUM(AZ59:ET59) -> 243000 | R59: =AB59*SUM(BC59:BN59) -> 29700 | S59: =SUM(GP59:HN59) -> #VALUE! | T59: =SUM(AZ59:EZ59) -> 4050 | U59: =_xlfn.CONCAT(Y59," - ",Z59) -> Technology - Consultant | V59: =VLOOKUP(O59,$B$187:$H$848,4,0) -> 1-3 years | W59: =IF(F59="US", "Onshore",IF(F59="India","Offshore", "Nearshore")) -> Offshore | X59: Consulting | Y59: Technology | Z59: Consultant | AA59: =[1]Resourcing!QD63 -> 358.79278 | AB59: =IFERROR(VLOOKUP(O59,$B$187:$S$848,6,FALSE()),"combination not found") -> 60 | BD59: 45 | BE59: 45 | BF59: 45 | BG59: 45 | BH59: 45 | BI59: 45 | BJ59: 45 | BK59: 45 | BL59: 45 | BM59: 45 | BN59: 45 | BO59: 45 | BP59: 45 | BQ59: 45 | BT59: 45 | BU59: 45 | BV59: 45 | BW59: 45 | BX59: 45 | BY59: 45 | BZ59: 45 | CA59: 45 | CB59: 45 | CC59: 45 | CD59: 45 | CE59: 45 | CF59: 45 | CG59: 45 | CH59: 45 | CI59: 45 | CJ59: 45 | CK59: 45 | CL59: 45 | CM59: 45 | CN59: 45 | CO59: 45 | CP59: 45 | CQ59: 45 | CR59: 45 | CS59: 45 | CT59: 45 | CU59: 45 | CV59: 45 | CW59: 45 | CX59: 45 | CY59: 45 | CZ59: 45 | DA59: 45 | DB59: 45 | DC59: 45 | DD59: 45 | DE59: 45 | DF59: 45 | DG59: 45 | DH59: 45 | DI59: 45 | DJ59: 45 | DK59: 45 | DL59: 45 | DM59: 45 | DN59: 45 | DO59: 45 | DP59: 45 | DQ59: 45 | DT59: 45 | DU59: 45 | DV59: 45 | DW59: 45 | DX59: 45 | DY59: 45 | DZ59: 45 | EA59: 45 | EB59: 45 | EC59: 45 | ED59: 45 | EE59: 45 | EF59: 45 | EG59: 45 | EH59: 45 | EI59: 45 | EJ59: 45 | EK59: 45 | EL59: 45 | EM59: 45 | EN59: 45 | EO59: 45 | EP59: 45 | EQ59: 45 | ER59: 45 | ES59: 45 | FQ59: =SUMIF($AC$11:$FP$11,FQ$12,$AC59:$FP59) -> #VALUE! | FR59: =SUMIF($AC$11:$FP$11,FR$12,$AC59:$FP59) -> #VALUE! | FS59: =SUMIF($AC$11:$FP$11,FS$12,$AC59:$FP59) -> #VALUE! | FT59: =SUMIF($AC$11:$FP$11,FT$12,$AC59:$FP59) -> #VALUE! | FU59: =SUMIF($AC$11:$FP$11,FU$12,$AC59:$FP59) -> #VALUE! | FV59: =SUMIF($AC$11:$FP$11,FV$12,$AC59:$FP59) -> #VALUE! | FW59: =SUMIF($AC$11:$FP$11,FW$12,$AC59:$FP59) -> #VALUE! | FX59: =SUMIF($AC$11:$FP$11,FX$12,$AC59:$FP59) -> #VALUE! | ... GO59: =SUMIF($AC$11:$FP$11,GO$12,$AC59:$FP59) -> #VALUE! | GP59: =SUMIF($AB$8:$FO$8,GP$9,$AB59:$FO59) -> 90 | GQ59: =SUMIF($AB$8:$FO$8,GQ$9,$AB59:$FO59) -> 180 | GR59: =SUMIF($AB$8:$FO$8,GR$9,$AB59:$FO59) -> 180 | GS59: =SUMIF($AB$8:$FO$8,GS$9,$AB59:$FO59) -> 180 | GT59: =SUMIF($AB$8:$FO$8,GT$9,$AB59:$FO59) -> 180 | GU59: =SUMIF($AB$8:$FO$8,GU$9,$AB59:$FO59) -> 180 | GV59: =SUMIF($AB$8:$FO$8,GV$9,$AB59:$FO59) -> 180 | GW59: =SUMIF($AB$8:$FO$8,GW$9,$AB59:$FO59) -> 90 | ... HE59: =SUMIF($AB$8:$FO$8,HE$9,$AB59:$FO59) -> 0 | HF59: =SUM(FQ59:HE59) -> #VALUE! | HG59: =HF59-S112 -> #VALUE!
B60: Process | C60: PTP | D60: Procurement | E60: PTP Offshore Indirect SME | F60: India | G60: Consulting Services | H60: Enterprise Performance | I60: SAP | J60: India | K60: Package and Technology Enablement | L60: Package Functional Transformation | M60: L45 - Senior Consultant | N60: =_xlfn.CONCAT(C60,"-",D60) -> PTP-Procurement | O60: =_xlfn.CONCAT(Y60,"-",Z60,"-",F60,"-",X60) -> Technology-Senior Consultant-India-Consulting | P60: =_xlfn.CONCAT(C60," - ",Y60) -> PTP - Technology | Q60: =AB60*SUM(AZ60:ET60) -> 268380 | R60: =AB60*SUM(BC60:BN60) -> 15975 | S60: =SUM(GP60:HN60) -> #VALUE! | T60: =SUM(AZ60:EZ60) -> 3780 | U60: =_xlfn.CONCAT(Y60," - ",Z60) -> Technology - Senior Consultant | V60: =VLOOKUP(O60,$B$187:$H$848,4,0) -> 3-5 years | W60: =IF(F60="US", "Onshore",IF(F60="India","Offshore", "Nearshore")) -> Offshore | X60: Consulting | Y60: Technology | Z60: Senior Consultant | AA60: =[1]Resourcing!QD64 -> 62.412222 | AB60: =IFERROR(VLOOKUP(O60,$B$187:$S$848,6,FALSE()),"combination not found") -> 71 | BJ60: 45 | BK60: 45 | BL60: 45 | BM60: 45 | BN60: 45 | BO60: 45 | BP60: 45 | BQ60: 45 | BT60: 45 | BU60: 45 | BV60: 45 | BW60: 45 | BX60: 45 | BY60: 45 | BZ60: 45 | CA60: 45 | CB60: 45 | CC60: 45 | CD60: 45 | CE60: 45 | CF60: 45 | CG60: 45 | CH60: 45 | CI60: 45 | CJ60: 45 | CK60: 45 | CL60: 45 | CM60: 45 | CN60: 45 | CO60: 45 | CP60: 45 | CQ60: 45 | CR60: 45 | CS60: 45 | CT60: 45 | CU60: 45 | CV60: 45 | CW60: 45 | CX60: 45 | CY60: 45 | CZ60: 45 | DA60: 45 | DB60: 45 | DC60: 45 | DD60: 45 | DE60: 45 | DF60: 45 | DG60: 45 | DH60: 45 | DI60: 45 | DJ60: 45 | DK60: 45 | DL60: 45 | DM60: 45 | DN60: 45 | DO60: 45 | DP60: 45 | DQ60: 45 | DT60: 45 | DU60: 45 | DV60: 45 | DW60: 45 | DX60: 45 | DY60: 45 | DZ60: 45 | EA60: 45 | EB60: 45 | EC60: 45 | ED60: 45 | EE60: 45 | EF60: 45 | EG60: 45 | EH60: 45 | EI60: 45 | EJ60: 45 | EK60: 45 | EL60: 45 | EM60: 45 | EN60: 45 | EO60: 45 | EP60: 45 | EQ60: 45 | ER60: 45 | ES60: 45 | FQ60: =SUMIF($AC$11:$FP$11,FQ$12,$AC60:$FP60) -> #VALUE! | FR60: =SUMIF($AC$11:$FP$11,FR$12,$AC60:$FP60) -> #VALUE! | FS60: =SUMIF($AC$11:$FP$11,FS$12,$AC60:$FP60) -> #VALUE! | FT60: =SUMIF($AC$11:$FP$11,FT$12,$AC60:$FP60) -> #VALUE! | FU60: =SUMIF($AC$11:$FP$11,FU$12,$AC60:$FP60) -> #VALUE! | FV60: =SUMIF($AC$11:$FP$11,FV$12,$AC60:$FP60) -> #VALUE! | FW60: =SUMIF($AC$11:$FP$11,FW$12,$AC60:$FP60) -> #VALUE! | FX60: =SUMIF($AC$11:$FP$11,FX$12,$AC60:$FP60) -> #VALUE! | ... GO60: =SUMIF($AC$11:$FP$11,GO$12,$AC60:$FP60) -> #VALUE! | GP60: =SUMIF($AB$8:$FO$8,GP$9,$AB60:$FO60) -> 90 | GQ60: =SUMIF($AB$8:$FO$8,GQ$9,$AB60:$FO60) -> 180 | GR60: =SUMIF($AB$8:$FO$8,GR$9,$AB60:$FO60) -> 180 | GS60: =SUMIF($AB$8:$FO$8,GS$9,$AB60:$FO60) -> 180 | GT60: =SUMIF($AB$8:$FO$8,GT$9,$AB60:$FO60) -> 180 | GU60: =SUMIF($AB$8:$FO$8,GU$9,$AB60:$FO60) -> 180 | GV60: =SUMIF($AB$8:$FO$8,GV$9,$AB60:$FO60) -> 180 | GW60: =SUMIF($AB$8:$FO$8,GW$9,$AB60:$FO60) -> 90 | ... HE60: =SUMIF($AB$8:$FO$8,HE$9,$AB60:$FO60) -> 0 | HF60: =SUM(FQ60:HE60) -> #VALUE! | HG60: =HF60-S117 -> #VALUE!
B61: Process | C61: PTP | D61: Accounts Payable | E61: PTP Offshore AP Support | F61: India | G61: Consulting Services | H61: Enterprise Performance | I61: SAP | J61: India | K61: Package and Technology Enablement | L61: Package Functional Transformation | M61: L25 - Analyst | N61: =_xlfn.CONCAT(C61,"-",D61) -> PTP-Accounts Payable | O61: =_xlfn.CONCAT(Y61,"-",Z61,"-",F61,"-",X61) -> Technology-Analyst-India-Consulting | P61: =_xlfn.CONCAT(C61," - ",Y61) -> PTP - Technology | Q61: =AB61*SUM(AZ61:ET61) -> 157680 | R61: =AB61*SUM(BC61:BN61) -> 0 | S61: =SUM(GP61:HN61) -> #VALUE! | T61: =SUM(AZ61:EZ61) -> 3285 | U61: =_xlfn.CONCAT(Y61," - ",Z61) -> Technology - Analyst | V61: =VLOOKUP(O61,$B$187:$H$848,4,0) -> 0-1 years | W61: =IF(F61="US", "Onshore",IF(F61="India","Offshore", "Nearshore")) -> Offshore | X61: Consulting | Y61: Technology | Z61: Analyst | AA61: =[1]Resourcing!QD65 -> 62.412222 | AB61: =IFERROR(VLOOKUP(O61,$B$187:$S$848,6,FALSE()),"combination not found") -> 48 | BT61: 45 | BU61: 45 | BV61: 45 | BW61: 45 | BX61: 45 | BY61: 45 | BZ61: 45 | CA61: 45 | CB61: 45 | CC61: 45 | CD61: 45 | CE61: 45 | CF61: 45 | CG61: 45 | CH61: 45 | CI61: 45 | CJ61: 45 | CK61: 45 | CL61: 45 | CM61: 45 | CN61: 45 | CO61: 45 | CP61: 45 | CQ61: 45 | CR61: 45 | CS61: 45 | CT61: 45 | CU61: 45 | CV61: 45 | CW61: 45 | CX61: 45 | CY61: 45 | CZ61: 45 | DA61: 45 | DB61: 45 | DC61: 45 | DD61: 45 | DE61: 45 | DF61: 45 | DG61: 45 | DH61: 45 | DI61: 45 | DJ61: 45 | DK61: 45 | DL61: 45 | DM61: 45 | DN61: 45 | DO61: 45 | DP61: 45 | DQ61: 45 | DT61: 45 | DU61: 45 | DV61: 45 | DW61: 45 | DX61: 45 | DY61: 45 | DZ61: 45 | EA61: 45 | EB61: 45 | EC61: 45 | ED61: 45 | EE61: 45 | EF61: 45 | EG61: 45 | EH61: 45 | EI61: 45 | EJ61: 45 | EK61: 45 | EL61: 45 | EM61: 45 | EN61: 45 | EO61: 45 | EP61: 45 | FQ61: =SUMIF($AC$11:$FP$11,FQ$12,$AC61:$FP61) -> #VALUE! | FR61: =SUMIF($AC$11:$FP$11,FR$12,$AC61:$FP61) -> #VALUE! | FS61: =SUMIF($AC$11:$FP$11,FS$12,$AC61:$FP61) -> #VALUE! | FT61: =SUMIF($AC$11:$FP$11,FT$12,$AC61:$FP61) -> #VALUE! | FU61: =SUMIF($AC$11:$FP$11,FU$12,$AC61:$FP61) -> #VALUE! | FV61: =SUMIF($AC$11:$FP$11,FV$12,$AC61:$FP61) -> #VALUE! | FW61: =SUMIF($AC$11:$FP$11,FW$12,$AC61:$FP61) -> #VALUE! | FX61: =SUMIF($AC$11:$FP$11,FX$12,$AC61:$FP61) -> #VALUE! | ... GO61: =SUMIF($AC$11:$FP$11,GO$12,$AC61:$FP61) -> #VALUE! | GP61: =SUMIF($AB$8:$FO$8,GP$9,$AB61:$FO61) -> 90 | GQ61: =SUMIF($AB$8:$FO$8,GQ$9,$AB61:$FO61) -> 180 | GR61: =SUMIF($AB$8:$FO$8,GR$9,$AB61:$FO61) -> 180 | GS61: =SUMIF($AB$8:$FO$8,GS$9,$AB61:$FO61) -> 180 | GT61: =SUMIF($AB$8:$FO$8,GT$9,$AB61:$FO61) -> 180 | GU61: =SUMIF($AB$8:$FO$8,GU$9,$AB61:$FO61) -> 180 | GV61: =SUMIF($AB$8:$FO$8,GV$9,$AB61:$FO61) -> 135 | GW61: =SUMIF($AB$8:$FO$8,GW$9,$AB61:$FO61) -> 0 | ... HE61: =SUMIF($AB$8:$FO$8,HE$9,$AB61:$FO61) -> 0 | HF61: =SUM(FQ61:HE61) -> #VALUE! | HG61: =HF61-S118 -> #VALUE!
B62: Process | C62: PTP | D62: Accounts Payable | E62: PTP Offshore Ariba Support | F62: India | G62: Consulting Services | H62: Enterprise Performance | I62: SAP | J62: India | K62: Package and Technology Enablement | L62: Package Functional Transformation | M62: L25 - Analyst | N62: =_xlfn.CONCAT(C62,"-",D62) -> PTP-Accounts Payable | O62: =_xlfn.CONCAT(Y62,"-",Z62,"-",F62,"-",X62) -> Technology-Analyst-India-Consulting | P62: =_xlfn.CONCAT(C62," - ",Y62) -> PTP - Technology | Q62: =AB62*SUM(AZ62:ET62) -> 86400 | R62: =AB62*SUM(BC62:BN62) -> 0 | S62: =SUM(GP62:HN62) -> #VALUE! | T62: =SUM(AZ62:EZ62) -> 1800 | U62: =_xlfn.CONCAT(Y62," - ",Z62) -> Technology - Analyst | V62: =VLOOKUP(O62,$B$187:$H$848,4,0) -> 0-1 years | W62: =IF(F62="US", "Onshore",IF(F62="India","Offshore", "Nearshore")) -> Offshore | X62: Consulting | Y62: Technology | Z62: Analyst | AA62: =[1]Resourcing!QD66 -> 53.05 | AB62: =IFERROR(VLOOKUP(O62,$B$187:$S$848,6,FALSE()),"combination not found") -> 48 | CD62: 45 | CE62: 45 | CF62: 45 | CG62: 45 | CH62: 45 | CI62: 45 | CJ62: 45 | CK62: 45 | CL62: 45 | CM62: 45 | CN62: 45 | CO62: 45 | CP62: 45 | CQ62: 45 | CR62: 45 | CS62: 45 | CT62: 45 | CU62: 45 | CV62: 45 | CW62: 45 | CX62: 45 | CY62: 45 | CZ62: 45 | DA62: 45 | DB62: 45 | DC62: 45 | DD62: 45 | DE62: 45 | DF62: 45 | DG62: 45 | DH62: 45 | DI62: 45 | DJ62: 45 | DK62: 45 | DL62: 45 | DM62: 45 | DN62: 45 | DO62: 45 | DP62: 45 | DQ62: 45 | FQ62: =SUMIF($AC$11:$FP$11,FQ$12,$AC62:$FP62) -> #VALUE! | FR62: =SUMIF($AC$11:$FP$11,FR$12,$AC62:$FP62) -> #VALUE! | FS62: =SUMIF($AC$11:$FP$11,FS$12,$AC62:$FP62) -> #VALUE! | FT62: =SUMIF($AC$11:$FP$11,FT$12,$AC62:$FP62) -> #VALUE! | FU62: =SUMIF($AC$11:$FP$11,FU$12,$AC62:$FP62) -> #VALUE! | FV62: =SUMIF($AC$11:$FP$11,FV$12,$AC62:$FP62) -> #VALUE! | FW62: =SUMIF($AC$11:$FP$11,FW$12,$AC62:$FP62) -> #VALUE! | FX62: =SUMIF($AC$11:$FP$11,FX$12,$AC62:$FP62) -> #VALUE! | ... GO62: =SUMIF($AC$11:$FP$11,GO$12,$AC62:$FP62) -> #VALUE! | GP62: =SUMIF($AB$8:$FO$8,GP$9,$AB62:$FO62) -> 90 | GQ62: =SUMIF($AB$8:$FO$8,GQ$9,$AB62:$FO62) -> 0 | GR62: =SUMIF($AB$8:$FO$8,GR$9,$AB62:$FO62) -> 0 | GS62: =SUMIF($AB$8:$FO$8,GS$9,$AB62:$FO62) -> 0 | GT62: =SUMIF($AB$8:$FO$8,GT$9,$AB62:$FO62) -> 0 | GU62: =SUMIF($AB$8:$FO$8,GU$9,$AB62:$FO62) -> 0 | GV62: =SUMIF($AB$8:$FO$8,GV$9,$AB62:$FO62) -> 0 | GW62: =SUMIF($AB$8:$FO$8,GW$9,$AB62:$FO62) -> 0 | ... HE62: =SUMIF($AB$8:$FO$8,HE$9,$AB62:$FO62) -> 0 | HF62: =SUM(FQ62:HE62) -> #VALUE! | HG62: =HF62-#REF! -> #REF!
B63: Process | C63: PTP | D63: Accounts Payable | E63: PTP Offshore Support | F63: India | G63: Consulting Services | H63: Enterprise Performance | I63: SAP | J63: India | K63: Package and Technology Enablement | L63: Package Functional Transformation | M63: L25 - Analyst | N63: =_xlfn.CONCAT(C63,"-",D63) -> PTP-Accounts Payable | O63: =_xlfn.CONCAT(Y63,"-",Z63,"-",F63,"-",X63) -> Technology-Analyst-India-Consulting | P63: =_xlfn.CONCAT(C63," - ",Y63) -> PTP - Technology | Q63: =AB63*SUM(AZ63:ET63) -> 86400 | R63: =AB63*SUM(BC63:BN63) -> 0 | S63: =SUM(GP63:HN63) -> #VALUE! | T63: =SUM(AZ63:EZ63) -> 1800 | U63: =_xlfn.CONCAT(Y63," - ",Z63) -> Technology - Analyst | V63: =VLOOKUP(O63,$B$187:$H$848,4,0) -> 0-1 years | W63: =IF(F63="US", "Onshore",IF(F63="India","Offshore", "Nearshore")) -> Offshore | X63: Consulting | Y63: Technology | Z63: Analyst | AA63: =[1]Resourcing!QD67 -> 62.584524 | AB63: =IFERROR(VLOOKUP(O63,$B$187:$S$848,6,FALSE()),"combination not found") -> 48 | CW63: 45 | CX63: 45 | CY63: 45 | CZ63: 45 | DA63: 45 | DB63: 45 | DC63: 45 | DD63: 45 | DE63: 45 | DF63: 45 | DG63: 45 | DH63: 45 | DI63: 45 | DJ63: 45 | DK63: 45 | DL63: 45 | DM63: 45 | DN63: 45 | DO63: 45 | DP63: 45 | DQ63: 45 | DT63: 45 | DU63: 45 | DV63: 45 | DW63: 45 | DX63: 45 | DY63: 45 | DZ63: 45 | EA63: 45 | EB63: 45 | EC63: 45 | ED63: 45 | EE63: 45 | EF63: 45 | EG63: 45 | EH63: 45 | EI63: 45 | EJ63: 45 | EK63: 45 | EL63: 45 | FQ63: =SUMIF($AC$11:$FP$11,FQ$12,$AC63:$FP63) -> #VALUE! | FR63: =SUMIF($AC$11:$FP$11,FR$12,$AC63:$FP63) -> #VALUE! | FS63: =SUMIF($AC$11:$FP$11,FS$12,$AC63:$FP63) -> #VALUE! | FT63: =SUMIF($AC$11:$FP$11,FT$12,$AC63:$FP63) -> #VALUE! | FU63: =SUMIF($AC$11:$FP$11,FU$12,$AC63:$FP63) -> #VALUE! | FV63: =SUMIF($AC$11:$FP$11,FV$12,$AC63:$FP63) -> #VALUE! | FW63: =SUMIF($AC$11:$FP$11,FW$12,$AC63:$FP63) -> #VALUE! | FX63: =SUMIF($AC$11:$FP$11,FX$12,$AC63:$FP63) -> #VALUE! | ... GO63: =SUMIF($AC$11:$FP$11,GO$12,$AC63:$FP63) -> #VALUE! | GP63: =SUMIF($AB$8:$FO$8,GP$9,$AB63:$FO63) -> 90 | GQ63: =SUMIF($AB$8:$FO$8,GQ$9,$AB63:$FO63) -> 180 | GR63: =SUMIF($AB$8:$FO$8,GR$9,$AB63:$FO63) -> 180 | GS63: =SUMIF($AB$8:$FO$8,GS$9,$AB63:$FO63) -> 180 | GT63: =SUMIF($AB$8:$FO$8,GT$9,$AB63:$FO63) -> 180 | GU63: =SUMIF($AB$8:$FO$8,GU$9,$AB63:$FO63) -> 135 | GV63: =SUMIF($AB$8:$FO$8,GV$9,$AB63:$FO63) -> 0 | GW63: =SUMIF($AB$8:$FO$8,GW$9,$AB63:$FO63) -> 0 | ... HE63: =SUMIF($AB$8:$FO$8,HE$9,$AB63:$FO63) -> 0 | HF63: =SUM(FQ63:HE63) -> #VALUE! | HG63: =HF63-S133 -> #VALUE!
Q64: =AB64*SUM(AZ64:ET64) -> 0 | R64: =AB64*SUM(BC64:BN64) -> 0 | T64: =SUM(AZ64:EZ64) -> 0 | AA64: =[1]Resourcing!QD68 -> 42.823836 | FQ64: =SUMIF($AC$11:$FP$11,FQ$12,$AC64:$FP64) -> #VALUE! | FR64: =SUMIF($AC$11:$FP$11,FR$12,$AC64:$FP64) -> #VALUE! | FS64: =SUMIF($AC$11:$FP$11,FS$12,$AC64:$FP64) -> #VALUE! | FT64: =SUMIF($AC$11:$FP$11,FT$12,$AC64:$FP64) -> #VALUE! | FU64: =SUMIF($AC$11:$FP$11,FU$12,$AC64:$FP64) -> #VALUE! | FV64: =SUMIF($AC$11:$FP$11,FV$12,$AC64:$FP64) -> #VALUE! | FW64: =SUMIF($AC$11:$FP$11,FW$12,$AC64:$FP64) -> #VALUE! | FX64: =SUMIF($AC$11:$FP$11,FX$12,$AC64:$FP64) -> #VALUE! | ... GO64: =SUMIF($AC$11:$FP$11,GO$12,$AC64:$FP64) -> #VALUE! | GP64: =SUMIF($AB$8:$FO$8,GP$9,$AB64:$FO64) -> 0 | GQ64: =SUMIF($AB$8:$FO$8,GQ$9,$AB64:$FO64) -> 0 | GR64: =SUMIF($AB$8:$FO$8,GR$9,$AB64:$FO64) -> 0 | GS64: =SUMIF($AB$8:$FO$8,GS$9,$AB64:$FO64) -> 0 | GT64: =SUMIF($AB$8:$FO$8,GT$9,$AB64:$FO64) -> 0 | GU64: =SUMIF($AB$8:$FO$8,GU$9,$AB64:$FO64) -> 0 | GV64: =SUMIF($AB$8:$FO$8,GV$9,$AB64:$FO64) -> 0 | GW64: =SUMIF($AB$8:$FO$8,GW$9,$AB64:$FO64) -> 0 | ... HE64: =SUMIF($AB$8:$FO$8,HE$9,$AB64:$FO64) -> 0 | HF64: =SUM(FQ64:HE64) -> #VALUE! | HG64: =HF64-S134 -> #VALUE!
B65: Process | C65: PTD | D65: Delivery Warehouse | E65: Logistics Lead (WM/TM/3PL) | F65: US | G65: Consulting Services | H65: Enterprise Performance | I65: SAP | J65: US | K65: Package and Technology Enablement | L65: Package Functional Transformation | M65: L55 - Manager | N65: =_xlfn.CONCAT(C65,"-",D65) -> PTD-Delivery Warehouse | O65: =_xlfn.CONCAT(Y65,"-",Z65,"-",F65,"-",X65) -> Technology-Senior Consultant-US-Consulting | P65: =_xlfn.CONCAT(C65," - ",Y65) -> PTD - Technology | Q65: =AB65*SUM(AZ65:ET65) -> 1076400 | R65: =AB65*SUM(BC65:BN65) -> 140400 | S65: =SUM(GP65:HN65) -> 0 | T65: =SUM(AZ65:EZ65) -> 4140 | U65: =_xlfn.CONCAT(Y65," - ",Z65) -> Technology - Senior Consultant | V65: =VLOOKUP(O65,$B$187:$H$848,4,0) -> 3-5 years | W65: =IF(F65="US", "Onshore",IF(F65="India","Offshore", "Nearshore")) -> Onshore | X65: Consulting | Y65: Technology | Z65: Senior Consultant | AA65: =[1]Resourcing!QD69 -> 42.7835 | AB65: =IFERROR(VLOOKUP(O65,$B$187:$S$848,6,FALSE()),"combination not found") -> 260 | BC65: 45 | BD65: 45 | BE65: 45 | BF65: 45 | BG65: 45 | BH65: 45 | BI65: 45 | BJ65: 45 | BK65: 45 | BL65: 45 | BM65: 45 | BN65: 45 | BO65: 45 | BP65: 45 | BQ65: 45 | BT65: 45 | BU65: 45 | BV65: 45 | BW65: 45 | BX65: 45 | BY65: 45 | BZ65: 45 | CA65: 45 | CB65: 45 | CC65: 45 | CD65: 45 | CE65: 45 | CF65: 45 | CG65: 45 | CH65: 45 | CI65: 45 | CJ65: 45 | CK65: 45 | CL65: 45 | CM65: 45 | CN65: 45 | CO65: 45 | CP65: 45 | CQ65: 45 | CR65: 45 | CS65: 45 | CT65: 45 | CU65: 45 | CV65: 45 | CW65: 45 | CX65: 45 | CY65: 45 | CZ65: 45 | DA65: 45 | DB65: 45 | DC65: 45 | DD65: 45 | DE65: 45 | DF65: 45 | DG65: 45 | DH65: 45 | DI65: 45 | DJ65: 45 | DK65: 45 | DL65: 45 | DM65: 45 | DN65: 45 | DO65: 45 | DP65: 45 | DQ65: 45 | DT65: 45 | DU65: 45 | DV65: 45 | DW65: 45 | DX65: 45 | DY65: 45 | DZ65: 45 | EA65: 45 | EB65: 45 | EC65: 45 | ED65: 45 | EE65: 45 | EF65: 45 | EG65: 45 | EH65: 45 | EI65: 45 | EJ65: 45 | EK65: 45 | EL65: 45 | EM65: 45 | EN65: 45 | EO65: 45 | EP65: 45 | EQ65: 45 | ER65: 45 | ES65: 45 | ET65: 45 | FQ65: =SUMIF($AC$11:$FP$11,FQ$12,$AC65:$FP65) -> #VALUE! | FR65: =SUMIF($AC$11:$FP$11,FR$12,$AC65:$FP65) -> #VALUE! | FS65: =SUMIF($AC$11:$FP$11,FS$12,$AC65:$FP65) -> #VALUE! | FT65: =SUMIF($AC$11:$FP$11,FT$12,$AC65:$FP65) -> #VALUE! | FU65: =SUMIF($AC$11:$FP$11,FU$12,$AC65:$FP65) -> #VALUE! | FV65: =SUMIF($AC$11:$FP$11,FV$12,$AC65:$FP65) -> #VALUE! | FW65: =SUMIF($AC$11:$FP$11,FW$12,$AC65:$FP65) -> #VALUE! | FX65: =SUMIF($AC$11:$FP$11,FX$12,$AC65:$FP65) -> #VALUE! | ... GO65: =SUMIF($AC$11:$FP$11,GO$12,$AC65:$FP65) -> #VALUE!
B66: Process | C66: PTD | D66: Delivery Warehouse | E66: Logistics Lead (WM/TM/3PL) | F66: India | G66: Consulting Services | H66: Enterprise Performance | I66: SAP | J66: India | K66: Package and Technology Enablement | L66: Package Functional Transformation | M66: L55 - Manager | N66: =_xlfn.CONCAT(C66,"-",D66) -> PTD-Delivery Warehouse | O66: =_xlfn.CONCAT(Y66,"-",Z66,"-",F66,"-",X66) -> Technology-Senior Consultant-India-Consulting | P66: =_xlfn.CONCAT(C66," - ",Y66) -> PTD - Technology | Q66: =AB66*SUM(AZ66:ET66) -> 293940 | R66: =AB66*SUM(BC66:BN66) -> 38340 | S66: =SUM(GP66:HN66) -> #VALUE! | T66: =SUM(AZ66:EZ66) -> 4140 | U66: =_xlfn.CONCAT(Y66," - ",Z66) -> Technology - Senior Consultant | V66: =VLOOKUP(O66,$B$187:$H$848,4,0) -> 3-5 years | W66: =IF(F66="US", "Onshore",IF(F66="India","Offshore", "Nearshore")) -> Offshore | X66: Consulting | Y66: Technology | Z66: Senior Consultant | AA66: =[1]Resourcing!QD70 -> 43.46 | AB66: =IFERROR(VLOOKUP(O66,$B$187:$S$848,6,FALSE()),"combination not found") -> 71 | BC66: 45 | BD66: 45 | BE66: 45 | BF66: 45 | BG66: 45 | BH66: 45 | BI66: 45 | BJ66: 45 | BK66: 45 | BL66: 45 | BM66: 45 | BN66: 45 | BO66: 45 | BP66: 45 | BQ66: 45 | BT66: 45 | BU66: 45 | BV66: 45 | BW66: 45 | BX66: 45 | BY66: 45 | BZ66: 45 | CA66: 45 | CB66: 45 | CC66: 45 | CD66: 45 | CE66: 45 | CF66: 45 | CG66: 45 | CH66: 45 | CI66: 45 | CJ66: 45 | CK66: 45 | CL66: 45 | CM66: 45 | CN66: 45 | CO66: 45 | CP66: 45 | CQ66: 45 | CR66: 45 | CS66: 45 | CT66: 45 | CU66: 45 | CV66: 45 | CW66: 45 | CX66: 45 | CY66: 45 | CZ66: 45 | DA66: 45 | DB66: 45 | DC66: 45 | DD66: 45 | DE66: 45 | DF66: 45 | DG66: 45 | DH66: 45 | DI66: 45 | DJ66: 45 | DK66: 45 | DL66: 45 | DM66: 45 | DN66: 45 | DO66: 45 | DP66: 45 | DQ66: 45 | DT66: 45 | DU66: 45 | DV66: 45 | DW66: 45 | DX66: 45 | DY66: 45 | DZ66: 45 | EA66: 45 | EB66: 45 | EC66: 45 | ED66: 45 | EE66: 45 | EF66: 45 | EG66: 45 | EH66: 45 | EI66: 45 | EJ66: 45 | EK66: 45 | EL66: 45 | EM66: 45 | EN66: 45 | EO66: 45 | EP66: 45 | EQ66: 45 | ER66: 45 | ES66: 45 | ET66: 45 | FQ66: =SUMIF($AC$11:$FP$11,FQ$12,$AC66:$FP66) -> #VALUE! | FR66: =SUMIF($AC$11:$FP$11,FR$12,$AC66:$FP66) -> #VALUE! | FS66: =SUMIF($AC$11:$FP$11,FS$12,$AC66:$FP66) -> #VALUE! | FT66: =SUMIF($AC$11:$FP$11,FT$12,$AC66:$FP66) -> #VALUE! | FU66: =SUMIF($AC$11:$FP$11,FU$12,$AC66:$FP66) -> #VALUE! | FV66: =SUMIF($AC$11:$FP$11,FV$12,$AC66:$FP66) -> #VALUE! | FW66: =SUMIF($AC$11:$FP$11,FW$12,$AC66:$FP66) -> #VALUE! | FX66: =SUMIF($AC$11:$FP$11,FX$12,$AC66:$FP66) -> #VALUE! | ... GO66: =SUMIF($AC$11:$FP$11,GO$12,$AC66:$FP66) -> #VALUE! | GP66: =SUMIF($AB$8:$FO$8,GP$9,$AB66:$FO66) -> 90 | GQ66: =SUMIF($AB$8:$FO$8,GQ$9,$AB66:$FO66) -> 180 | GR66: =SUMIF($AB$8:$FO$8,GR$9,$AB66:$FO66) -> 180 | GS66: =SUMIF($AB$8:$FO$8,GS$9,$AB66:$FO66) -> 180 | GT66: =SUMIF($AB$8:$FO$8,GT$9,$AB66:$FO66) -> 180 | GU66: =SUMIF($AB$8:$FO$8,GU$9,$AB66:$FO66) -> 180 | GV66: =SUMIF($AB$8:$FO$8,GV$9,$AB66:$FO66) -> 180 | GW66: =SUMIF($AB$8:$FO$8,GW$9,$AB66:$FO66) -> 135 | ... HE66: =SUMIF($AB$8:$FO$8,HE$9,$AB66:$FO66) -> 0 | HF66: =SUM(FQ66:HE66) -> #VALUE! | HG66: =HF66-S112 -> #VALUE!
B67: Process | C67: PTD | D67: Delivery Warehouse | E67: Warehouse - Automation / Production Logistics | F67: India | G67: Consulting Services | H67: Enterprise Performance | I67: SAP | J67: India | K67: Package and Technology Enablement | L67: Package Functional Transformation | M67: L35 - Consultant | N67: =_xlfn.CONCAT(C67,"-",D67) -> PTD-Delivery Warehouse | O67: =_xlfn.CONCAT(Y67,"-",Z67,"-",F67,"-",X67) -> Technology-Consultant-India-Consulting | P67: =_xlfn.CONCAT(C67," - ",Y67) -> PTD - Technology | Q67: =AB67*SUM(AZ67:ET67) -> 240300 | R67: =AB67*SUM(BC67:BN67) -> 24300 | S67: =SUM(GP67:HN67) -> #VALUE! | T67: =SUM(AZ67:EZ67) -> 4005 | U67: =_xlfn.CONCAT(Y67," - ",Z67) -> Technology - Consultant | V67: =VLOOKUP(O67,$B$187:$H$848,4,0) -> 1-3 years | W67: =IF(F67="US", "Onshore",IF(F67="India","Offshore", "Nearshore")) -> Offshore | X67: Consulting | Y67: Technology | Z67: Consultant | AA67: =[1]Resourcing!QD71 -> 0 | AB67: =IFERROR(VLOOKUP(O67,$B$187:$S$848,6,FALSE()),"combination not found") -> 60 | BF67: 45 | BG67: 45 | BH67: 45 | BI67: 45 | BJ67: 45 | BK67: 45 | BL67: 45 | BM67: 45 | BN67: 45 | BO67: 45 | BP67: 45 | BQ67: 45 | BT67: 45 | BU67: 45 | BV67: 45 | BW67: 45 | BX67: 45 | BY67: 45 | BZ67: 45 | CA67: 45 | CB67: 45 | CC67: 45 | CD67: 45 | CE67: 45 | CF67: 45 | CG67: 45 | CH67: 45 | CI67: 45 | CJ67: 45 | CK67: 45 | CL67: 45 | CM67: 45 | CN67: 45 | CO67: 45 | CP67: 45 | CQ67: 45 | CR67: 45 | CS67: 45 | CT67: 45 | CU67: 45 | CV67: 45 | CW67: 45 | CX67: 45 | CY67: 45 | CZ67: 45 | DA67: 45 | DB67: 45 | DC67: 45 | DD67: 45 | DE67: 45 | DF67: 45 | DG67: 45 | DH67: 45 | DI67: 45 | DJ67: 45 | DK67: 45 | DL67: 45 | DM67: 45 | DN67: 45 | DO67: 45 | DP67: 45 | DQ67: 45 | DT67: 45 | DU67: 45 | DV67: 45 | DW67: 45 | DX67: 45 | DY67: 45 | DZ67: 45 | EA67: 45 | EB67: 45 | EC67: 45 | ED67: 45 | EE67: 45 | EF67: 45 | EG67: 45 | EH67: 45 | EI67: 45 | EJ67: 45 | EK67: 45 | EL67: 45 | EM67: 45 | EN67: 45 | EO67: 45 | EP67: 45 | EQ67: 45 | ER67: 45 | ES67: 45 | ET67: 45 | FQ67: =SUMIF($AC$11:$FP$11,FQ$12,$AC67:$FP67) -> #VALUE! | FR67: =SUMIF($AC$11:$FP$11,FR$12,$AC67:$FP67) -> #VALUE! | FS67: =SUMIF($AC$11:$FP$11,FS$12,$AC67:$FP67) -> #VALUE! | FT67: =SUMIF($AC$11:$FP$11,FT$12,$AC67:$FP67) -> #VALUE! | FU67: =SUMIF($AC$11:$FP$11,FU$12,$AC67:$FP67) -> #VALUE! | FV67: =SUMIF($AC$11:$FP$11,FV$12,$AC67:$FP67) -> #VALUE! | FW67: =SUMIF($AC$11:$FP$11,FW$12,$AC67:$FP67) -> #VALUE! | FX67: =SUMIF($AC$11:$FP$11,FX$12,$AC67:$FP67) -> #VALUE! | ... GO67: =SUMIF($AC$11:$FP$11,GO$12,$AC67:$FP67) -> #VALUE! | GP67: =SUMIF($AB$8:$FO$8,GP$9,$AB67:$FO67) -> 90 | GQ67: =SUMIF($AB$8:$FO$8,GQ$9,$AB67:$FO67) -> 180 | GR67: =SUMIF($AB$8:$FO$8,GR$9,$AB67:$FO67) -> 180 | GS67: =SUMIF($AB$8:$FO$8,GS$9,$AB67:$FO67) -> 180 | GT67: =SUMIF($AB$8:$FO$8,GT$9,$AB67:$FO67) -> 180 | GU67: =SUMIF($AB$8:$FO$8,GU$9,$AB67:$FO67) -> 180 | GV67: =SUMIF($AB$8:$FO$8,GV$9,$AB67:$FO67) -> 180 | GW67: =SUMIF($AB$8:$FO$8,GW$9,$AB67:$FO67) -> 135 | ... HE67: =SUMIF($AB$8:$FO$8,HE$9,$AB67:$FO67) -> 0 | HF67: =SUM(FQ67:HE67) -> #VALUE! | HG67: =HF67-S117 -> #VALUE!
B68: Process | C68: PTD | D68: Delivery Warehouse | E68: Warehouse - Outbound | F68: India | G68: Consulting Services | H68: Enterprise Performance | I68: SAP | J68: India | K68: Package and Technology Enablement | L68: Package Functional Transformation | M68: L35 - Consultant | N68: =_xlfn.CONCAT(C68,"-",D68) -> PTD-Delivery Warehouse | O68: =_xlfn.CONCAT(Y68,"-",Z68,"-",F68,"-",X68) -> Technology-Consultant-India-Consulting | P68: =_xlfn.CONCAT(C68," - ",Y68) -> PTD - Technology | Q68: =AB68*SUM(AZ68:ET68) -> 156600 | R68: =AB68*SUM(BC68:BN68) -> 0 | S68: =SUM(GP68:HN68) -> 630 | T68: =SUM(AZ68:EZ68) -> 2610 | U68: =_xlfn.CONCAT(Y68," - ",Z68) -> Technology - Consultant | V68: =VLOOKUP(O68,$B$187:$H$848,4,0) -> 1-3 years | W68: =IF(F68="US", "Onshore",IF(F68="India","Offshore", "Nearshore")) -> Offshore | X68: Consulting | Y68: Technology | Z68: Consultant | AA68: =[1]Resourcing!QD72 -> 358.95478 | AB68: =IFERROR(VLOOKUP(O68,$B$187:$S$848,6,FALSE()),"combination not found") -> 60 | BX68: 45 | BY68: 45 | BZ68: 45 | CA68: 45 | CB68: 45 | CC68: 45 | CD68: 45 | CE68: 45 | CF68: 45 | CG68: 45 | CH68: 45 | CI68: 45 | CJ68: 45 | CK68: 45 | CL68: 45 | CM68: 45 | CN68: 45 | CO68: 45 | CP68: 45 | CQ68: 45 | CR68: 45 | CS68: 45 | CT68: 45 | CU68: 45 | CV68: 45 | CW68: 45 | CX68: 45 | CY68: 45 | CZ68: 45 | DA68: 45 | DB68: 45 | DC68: 45 | DD68: 45 | DE68: 45 | DF68: 45 | DG68: 45 | DH68: 45 | DI68: 45 | DJ68: 45 | DK68: 45 | DL68: 45 | DM68: 45 | DN68: 45 | DO68: 45 | DP68: 45 | DQ68: 45 | DT68: 45 | DU68: 45 | DV68: 45 | DW68: 45 | DX68: 45 | DY68: 45 | DZ68: 45 | EA68: 45 | EB68: 45 | EC68: 45 | ED68: 45 | EE68: 45 | FQ68: =SUMIF($AC$11:$FP$11,FQ$12,$AC68:$FP68) -> #VALUE! | FR68: =SUMIF($AC$11:$FP$11,FR$12,$AC68:$FP68) -> #VALUE! | FS68: =SUMIF($AC$11:$FP$11,FS$12,$AC68:$FP68) -> #VALUE! | FT68: =SUMIF($AC$11:$FP$11,FT$12,$AC68:$FP68) -> #VALUE! | FU68: =SUMIF($AC$11:$FP$11,FU$12,$AC68:$FP68) -> #VALUE! | FV68: =SUMIF($AC$11:$FP$11,FV$12,$AC68:$FP68) -> #VALUE! | FW68: =SUMIF($AC$11:$FP$11,FW$12,$AC68:$FP68) -> #VALUE! | FX68: =SUMIF($AC$11:$FP$11,FX$12,$AC68:$FP68) -> #VALUE! | ... GO68: =SUMIF($AC$11:$FP$11,GO$12,$AC68:$FP68) -> #VALUE! | GP68: =SUMIF($AB$8:$FO$8,GP$9,$AB68:$FO68) -> 90 | GQ68: =SUMIF($AB$8:$FO$8,GQ$9,$AB68:$FO68) -> 180 | GR68: =SUMIF($AB$8:$FO$8,GR$9,$AB68:$FO68) -> 180 | GS68: =SUMIF($AB$8:$FO$8,GS$9,$AB68:$FO68) -> 180 | GT68: =SUMIF($AB$8:$FO$8,GT$9,$AB68:$FO68) -> 0 | GU68: =SUMIF($AB$8:$FO$8,GU$9,$AB68:$FO68) -> 0 | GV68: =SUMIF($AB$8:$FO$8,GV$9,$AB68:$FO68) -> 0 | GW68: =SUMIF($AB$8:$FO$8,GW$9,$AB68:$FO68) -> 0 | ... HE68: =SUMIF($AB$8:$FO$8,HE$9,$AB68:$FO68) -> 0
B69: Process | C69: PTD | D69: Delivery Warehouse | E69: Warehouse - Inbound + Internal | F69: India | G69: Consulting Services | H69: Enterprise Performance | I69: SAP | J69: India | K69: Package and Technology Enablement | L69: Package Functional Transformation | M69: L35 - Consultant | N69: =_xlfn.CONCAT(C69,"-",D69) -> PTD-Delivery Warehouse | O69: =_xlfn.CONCAT(Y69,"-",Z69,"-",F69,"-",X69) -> Technology-Consultant-India-Consulting | P69: =_xlfn.CONCAT(C69," - ",Y69) -> PTD - Technology | Q69: =AB69*SUM(AZ69:ET69) -> 162000 | R69: =AB69*SUM(BC69:BN69) -> 0 | S69: =SUM(GP69:HN69) -> 1305 | T69: =SUM(AZ69:EZ69) -> 2700 | U69: =_xlfn.CONCAT(Y69," - ",Z69) -> Technology - Consultant | V69: =VLOOKUP(O69,$B$187:$H$848,4,0) -> 1-3 years | W69: =IF(F69="US", "Onshore",IF(F69="India","Offshore", "Nearshore")) -> Offshore | X69: Consulting | Y69: Technology | Z69: Consultant | AA69: =[1]Resourcing!QD73 -> 85.335217 | AB69: =IFERROR(VLOOKUP(O69,$B$187:$S$848,6,FALSE()),"combination not found") -> 60 | BY69: 0 | BZ69: 0 | CA69: 0 | CB69: 0 | CC69: 0 | CD69: 0 | CE69: 0 | CF69: 0 | CG69: 0 | CH69: 0 | CI69: 0 | CJ69: 0 | CK69: 45 | CL69: 45 | CM69: 45 | CN69: 45 | CO69: 45 | CP69: 45 | CQ69: 45 | CR69: 45 | CS69: 45 | CT69: 45 | CU69: 45 | CV69: 45 | CW69: 45 | CX69: 45 | CY69: 45 | CZ69: 45 | DA69: 45 | DB69: 45 | DC69: 45 | DD69: 45 | DE69: 45 | DF69: 45 | DG69: 45 | DH69: 45 | DI69: 45 | DJ69: 45 | DK69: 45 | DL69: 45 | DM69: 45 | DN69: 45 | DO69: 45 | DP69: 45 | DQ69: 45 | DT69: 45 | DU69: 45 | DV69: 45 | DW69: 45 | DX69: 45 | DY69: 45 | DZ69: 45 | EA69: 45 | EB69: 45 | EC69: 45 | ED69: 45 | EE69: 45 | EF69: 45 | EG69: 45 | EH69: 45 | EI69: 45 | EJ69: 45 | EK69: 45 | EL69: 45 | EM69: 45 | EN69: 45 | EO69: 45 | EP69: 45 | EQ69: 45 | ER69: 45 | ES69: 45 | ET69: 45 | FQ69: =SUMIF($AC$11:$FP$11,FQ$12,$AC69:$FP69) -> #VALUE! | FR69: =SUMIF($AC$11:$FP$11,FR$12,$AC69:$FP69) -> #VALUE! | FS69: =SUMIF($AC$11:$FP$11,FS$12,$AC69:$FP69) -> #VALUE! | FT69: =SUMIF($AC$11:$FP$11,FT$12,$AC69:$FP69) -> #VALUE! | FU69: =SUMIF($AC$11:$FP$11,FU$12,$AC69:$FP69) -> #VALUE! | FV69: =SUMIF($AC$11:$FP$11,FV$12,$AC69:$FP69) -> #VALUE! | FW69: =SUMIF($AC$11:$FP$11,FW$12,$AC69:$FP69) -> #VALUE! | FX69: =SUMIF($AC$11:$FP$11,FX$12,$AC69:$FP69) -> #VALUE! | ... GO69: =SUMIF($AC$11:$FP$11,GO$12,$AC69:$FP69) -> #VALUE! | GP69: =SUMIF($AB$8:$FO$8,GP$9,$AB69:$FO69) -> 90 | GQ69: =SUMIF($AB$8:$FO$8,GQ$9,$AB69:$FO69) -> 180 | GR69: =SUMIF($AB$8:$FO$8,GR$9,$AB69:$FO69) -> 180 | GS69: =SUMIF($AB$8:$FO$8,GS$9,$AB69:$FO69) -> 180 | GT69: =SUMIF($AB$8:$FO$8,GT$9,$AB69:$FO69) -> 180 | GU69: =SUMIF($AB$8:$FO$8,GU$9,$AB69:$FO69) -> 180 | GV69: =SUMIF($AB$8:$FO$8,GV$9,$AB69:$FO69) -> 180 | GW69: =SUMIF($AB$8:$FO$8,GW$9,$AB69:$FO69) -> 135 | ... HE69: =SUMIF($AB$8:$FO$8,HE$9,$AB69:$FO69) -> 0
B70: Process | C70: PTD | D70: Delivery Warehouse | E70: Warehouse - Internal | F70: India | G70: Consulting Services | H70: Enterprise Performance | I70: SAP | J70: India | K70: Package and Technology Enablement | L70: Package Functional Transformation | M70: L25 - Analyst | N70: =_xlfn.CONCAT(C70,"-",D70) -> PTD-Delivery Warehouse | O70: =_xlfn.CONCAT(Y70,"-",Z70,"-",F70,"-",X70) -> Technology-Analyst-India-Consulting | P70: =_xlfn.CONCAT(C70," - ",Y70) -> PTD - Technology | Q70: =AB70*SUM(AZ70:ET70) -> 155520 | R70: =AB70*SUM(BC70:BN70) -> 0 | S70: =SUM(GP70:HN70) -> 1305 | T70: =SUM(AZ70:EZ70) -> 3240 | U70: =_xlfn.CONCAT(Y70," - ",Z70) -> Technology - Analyst | V70: =VLOOKUP(O70,$B$187:$H$848,4,0) -> 0-1 years | W70: =IF(F70="US", "Onshore",IF(F70="India","Offshore", "Nearshore")) -> Offshore | X70: Consulting | Y70: Technology | Z70: Analyst | AA70: =[1]Resourcing!QD74 -> 53.14382 | AB70: =IFERROR(VLOOKUP(O70,$B$187:$S$848,6,FALSE()),"combination not found") -> 48 | BY70: 45 | BZ70: 45 | CA70: 45 | CB70: 45 | CC70: 45 | CD70: 45 | CE70: 45 | CF70: 45 | CG70: 45 | CH70: 45 | CI70: 45 | CJ70: 45 | CK70: 45 | CL70: 45 | CM70: 45 | CN70: 45 | CO70: 45 | CP70: 45 | CQ70: 45 | CR70: 45 | CS70: 45 | CT70: 45 | CU70: 45 | CV70: 45 | CW70: 45 | CX70: 45 | CY70: 45 | CZ70: 45 | DA70: 45 | DB70: 45 | DC70: 45 | DD70: 45 | DE70: 45 | DF70: 45 | DG70: 45 | DH70: 45 | DI70: 45 | DJ70: 45 | DK70: 45 | DL70: 45 | DM70: 45 | DN70: 45 | DO70: 45 | DP70: 45 | DQ70: 45 | DT70: 45 | DU70: 45 | DV70: 45 | DW70: 45 | DX70: 45 | DY70: 45 | DZ70: 45 | EA70: 45 | EB70: 45 | EC70: 45 | ED70: 45 | EE70: 45 | EF70: 45 | EG70: 45 | EH70: 45 | EI70: 45 | EJ70: 45 | EK70: 45 | EL70: 45 | EM70: 45 | EN70: 45 | EO70: 45 | EP70: 45 | EQ70: 45 | ER70: 45 | ES70: 45 | ET70: 45 | FQ70: =SUMIF($AC$11:$FP$11,FQ$12,$AC70:$FP70) -> #VALUE! | FR70: =SUMIF($AC$11:$FP$11,FR$12,$AC70:$FP70) -> #VALUE! | FS70: =SUMIF($AC$11:$FP$11,FS$12,$AC70:$FP70) -> #VALUE! | FT70: =SUMIF($AC$11:$FP$11,FT$12,$AC70:$FP70) -> #VALUE! | FU70: =SUMIF($AC$11:$FP$11,FU$12,$AC70:$FP70) -> #VALUE! | FV70: =SUMIF($AC$11:$FP$11,FV$12,$AC70:$FP70) -> #VALUE! | FW70: =SUMIF($AC$11:$FP$11,FW$12,$AC70:$FP70) -> #VALUE! | FX70: =SUMIF($AC$11:$FP$11,FX$12,$AC70:$FP70) -> #VALUE! | ... GO70: =SUMIF($AC$11:$FP$11,GO$12,$AC70:$FP70) -> #VALUE! | GP70: =SUMIF($AB$8:$FO$8,GP$9,$AB70:$FO70) -> 90 | GQ70: =SUMIF($AB$8:$FO$8,GQ$9,$AB70:$FO70) -> 180 | GR70: =SUMIF($AB$8:$FO$8,GR$9,$AB70:$FO70) -> 180 | GS70: =SUMIF($AB$8:$FO$8,GS$9,$AB70:$FO70) -> 180 | GT70: =SUMIF($AB$8:$FO$8,GT$9,$AB70:$FO70) -> 180 | GU70: =SUMIF($AB$8:$FO$8,GU$9,$AB70:$FO70) -> 180 | GV70: =SUMIF($AB$8:$FO$8,GV$9,$AB70:$FO70) -> 180 | GW70: =SUMIF($AB$8:$FO$8,GW$9,$AB70:$FO70) -> 135 | ... HE70: =SUMIF($AB$8:$FO$8,HE$9,$AB70:$FO70) -> 0
B71: Process | C71: PTD | D71: Delivery Warehouse | E71: 3PL + XPS lead | F71: India | G71: Consulting Services | H71: Enterprise Performance | I71: SAP | J71: India | K71: Package and Technology Enablement | L71: Package Functional Transformation | M71: L45 - Senior Consultant | N71: =_xlfn.CONCAT(C71,"-",D71) -> PTD-Delivery Warehouse | O71: =_xlfn.CONCAT(Y71,"-",Z71,"-",F71,"-",X71) -> Technology-Senior Consultant-India-Consulting | P71: =_xlfn.CONCAT(C71," - ",Y71) -> PTD - Technology | Q71: =AB71*SUM(AZ71:ET71) -> 284355 | R71: =AB71*SUM(BC71:BN71) -> 28755 | S71: =SUM(GP71:HN71) -> 1305 | T71: =SUM(AZ71:EZ71) -> 4005 | U71: =_xlfn.CONCAT(Y71," - ",Z71) -> Technology - Senior Consultant | V71: =VLOOKUP(O71,$B$187:$H$848,4,0) -> 3-5 years | W71: =IF(F71="US", "Onshore",IF(F71="India","Offshore", "Nearshore")) -> Offshore | X71: Consulting | Y71: Technology | Z71: Senior Consultant | AA71: =[1]Resourcing!QD75 -> 53.163103 | AB71: =IFERROR(VLOOKUP(O71,$B$187:$S$848,6,FALSE()),"combination not found") -> 71 | BF71: 45 | BG71: 45 | BH71: 45 | BI71: 45 | BJ71: 45 | BK71: 45 | BL71: 45 | BM71: 45 | BN71: 45 | BO71: 45 | BP71: 45 | BQ71: 45 | BT71: 45 | BU71: 45 | BV71: 45 | BW71: 45 | BX71: 45 | BY71: 45 | BZ71: 45 | CA71: 45 | CB71: 45 | CC71: 45 | CD71: 45 | CE71: 45 | CF71: 45 | CG71: 45 | CH71: 45 | CI71: 45 | CJ71: 45 | CK71: 45 | CL71: 45 | CM71: 45 | CN71: 45 | CO71: 45 | CP71: 45 | CQ71: 45 | CR71: 45 | CS71: 45 | CT71: 45 | CU71: 45 | CV71: 45 | CW71: 45 | CX71: 45 | CY71: 45 | CZ71: 45 | DA71: 45 | DB71: 45 | DC71: 45 | DD71: 45 | DE71: 45 | DF71: 45 | DG71: 45 | DH71: 45 | DI71: 45 | DJ71: 45 | DK71: 45 | DL71: 45 | DM71: 45 | DN71: 45 | DO71: 45 | DP71: 45 | DQ71: 45 | DT71: 45 | DU71: 45 | DV71: 45 | DW71: 45 | DX71: 45 | DY71: 45 | DZ71: 45 | EA71: 45 | EB71: 45 | EC71: 45 | ED71: 45 | EE71: 45 | EF71: 45 | EG71: 45 | EH71: 45 | EI71: 45 | EJ71: 45 | EK71: 45 | EL71: 45 | EM71: 45 | EN71: 45 | EO71: 45 | EP71: 45 | EQ71: 45 | ER71: 45 | ES71: 45 | ET71: 45 | FQ71: =SUMIF($AC$11:$FP$11,FQ$12,$AC71:$FP71) -> #VALUE! | FR71: =SUMIF($AC$11:$FP$11,FR$12,$AC71:$FP71) -> #VALUE! | FS71: =SUMIF($AC$11:$FP$11,FS$12,$AC71:$FP71) -> #VALUE! | FT71: =SUMIF($AC$11:$FP$11,FT$12,$AC71:$FP71) -> #VALUE! | FU71: =SUMIF($AC$11:$FP$11,FU$12,$AC71:$FP71) -> #VALUE! | FV71: =SUMIF($AC$11:$FP$11,FV$12,$AC71:$FP71) -> #VALUE! | FW71: =SUMIF($AC$11:$FP$11,FW$12,$AC71:$FP71) -> #VALUE! | FX71: =SUMIF($AC$11:$FP$11,FX$12,$AC71:$FP71) -> #VALUE! | ... GO71: =SUMIF($AC$11:$FP$11,GO$12,$AC71:$FP71) -> #VALUE! | GP71: =SUMIF($AB$8:$FO$8,GP$9,$AB71:$FO71) -> 90 | GQ71: =SUMIF($AB$8:$FO$8,GQ$9,$AB71:$FO71) -> 180 | GR71: =SUMIF($AB$8:$FO$8,GR$9,$AB71:$FO71) -> 180 | GS71: =SUMIF($AB$8:$FO$8,GS$9,$AB71:$FO71) -> 180 | GT71: =SUMIF($AB$8:$FO$8,GT$9,$AB71:$FO71) -> 180 | GU71: =SUMIF($AB$8:$FO$8,GU$9,$AB71:$FO71) -> 180 | GV71: =SUMIF($AB$8:$FO$8,GV$9,$AB71:$FO71) -> 180 | GW71: =SUMIF($AB$8:$FO$8,GW$9,$AB71:$FO71) -> 135 | ... HE71: =SUMIF($AB$8:$FO$8,HE$9,$AB71:$FO71) -> 0
B72: Process | C72: PTD | D72: Delivery Warehouse | E72: 3PL + XPS Consultant | F72: India | G72: Consulting Services | H72: Enterprise Performance | I72: SAP | J72: India | K72: Package and Technology Enablement | L72: Package Functional Transformation | M72: L35 - Consultant | N72: =_xlfn.CONCAT(C72,"-",D72) -> PTD-Delivery Warehouse | O72: =_xlfn.CONCAT(Y72,"-",Z72,"-",F72,"-",X72) -> Technology-Consultant-India-Consulting | P72: =_xlfn.CONCAT(C72," - ",Y72) -> PTD - Technology | Q72: =AB72*SUM(AZ72:ET72) -> 162000 | R72: =AB72*SUM(BC72:BN72) -> 0 | S72: =SUM(GP72:HN72) -> 1305 | T72: =SUM(AZ72:EZ72) -> 2700 | U72: =_xlfn.CONCAT(Y72," - ",Z72) -> Technology - Consultant | V72: =VLOOKUP(O72,$B$187:$H$848,4,0) -> 1-3 years | W72: =IF(F72="US", "Onshore",IF(F72="India","Offshore", "Nearshore")) -> Offshore | X72: Consulting | Y72: Technology | Z72: Consultant | AA72: =[1]Resourcing!QD76 -> 54.18 | AB72: =IFERROR(VLOOKUP(O72,$B$187:$S$848,6,FALSE()),"combination not found") -> 60 | BY72: 0 | BZ72: 0 | CA72: 0 | CB72: 0 | CC72: 0 | CD72: 0 | CE72: 0 | CF72: 0 | CG72: 0 | CH72: 0 | CI72: 0 | CJ72: 0 | CK72: 45 | CL72: 45 | CM72: 45 | CN72: 45 | CO72: 45 | CP72: 45 | CQ72: 45 | CR72: 45 | CS72: 45 | CT72: 45 | CU72: 45 | CV72: 45 | CW72: 45 | CX72: 45 | CY72: 45 | CZ72: 45 | DA72: 45 | DB72: 45 | DC72: 45 | DD72: 45 | DE72: 45 | DF72: 45 | DG72: 45 | DH72: 45 | DI72: 45 | DJ72: 45 | DK72: 45 | DL72: 45 | DM72: 45 | DN72: 45 | DO72: 45 | DP72: 45 | DQ72: 45 | DT72: 45 | DU72: 45 | DV72: 45 | DW72: 45 | DX72: 45 | DY72: 45 | DZ72: 45 | EA72: 45 | EB72: 45 | EC72: 45 | ED72: 45 | EE72: 45 | EF72: 45 | EG72: 45 | EH72: 45 | EI72: 45 | EJ72: 45 | EK72: 45 | EL72: 45 | EM72: 45 | EN72: 45 | EO72: 45 | EP72: 45 | EQ72: 45 | ER72: 45 | ES72: 45 | ET72: 45 | FQ72: =SUMIF($AC$11:$FP$11,FQ$12,$AC72:$FP72) -> #VALUE! | FR72: =SUMIF($AC$11:$FP$11,FR$12,$AC72:$FP72) -> #VALUE! | FS72: =SUMIF($AC$11:$FP$11,FS$12,$AC72:$FP72) -> #VALUE! | FT72: =SUMIF($AC$11:$FP$11,FT$12,$AC72:$FP72) -> #VALUE! | FU72: =SUMIF($AC$11:$FP$11,FU$12,$AC72:$FP72) -> #VALUE! | FV72: =SUMIF($AC$11:$FP$11,FV$12,$AC72:$FP72) -> #VALUE! | FW72: =SUMIF($AC$11:$FP$11,FW$12,$AC72:$FP72) -> #VALUE! | FX72: =SUMIF($AC$11:$FP$11,FX$12,$AC72:$FP72) -> #VALUE! | ... GO72: =SUMIF($AC$11:$FP$11,GO$12,$AC72:$FP72) -> #VALUE! | GP72: =SUMIF($AB$8:$FO$8,GP$9,$AB72:$FO72) -> 90 | GQ72: =SUMIF($AB$8:$FO$8,GQ$9,$AB72:$FO72) -> 180 | GR72: =SUMIF($AB$8:$FO$8,GR$9,$AB72:$FO72) -> 180 | GS72: =SUMIF($AB$8:$FO$8,GS$9,$AB72:$FO72) -> 180 | GT72: =SUMIF($AB$8:$FO$8,GT$9,$AB72:$FO72) -> 180 | GU72: =SUMIF($AB$8:$FO$8,GU$9,$AB72:$FO72) -> 180 | GV72: =SUMIF($AB$8:$FO$8,GV$9,$AB72:$FO72) -> 180 | GW72: =SUMIF($AB$8:$FO$8,GW$9,$AB72:$FO72) -> 135 | ... HE72: =SUMIF($AB$8:$FO$8,HE$9,$AB72:$FO72) -> 0
B73: Process | C73: PTD | D73: Delivery Warehouse | E73: 3PL Analyst | F73: India | G73: Consulting Services | H73: Enterprise Performance | I73: SAP | J73: India | K73: Package and Technology Enablement | L73: Package Functional Transformation | M73: L25 - Analyst | N73: =_xlfn.CONCAT(C73,"-",D73) -> PTD-Delivery Warehouse | O73: =_xlfn.CONCAT(Y73,"-",Z73,"-",F73,"-",X73) -> Technology-Analyst-India-Consulting | P73: =_xlfn.CONCAT(C73," - ",Y73) -> PTD - Technology | Q73: =AB73*SUM(AZ73:ET73) -> 60480 | R73: =AB73*SUM(BC73:BN73) -> 0 | S73: =SUM(GP73:HN73) -> 630 | T73: =SUM(AZ73:EZ73) -> 1260 | U73: =_xlfn.CONCAT(Y73," - ",Z73) -> Technology - Analyst | V73: =VLOOKUP(O73,$B$187:$H$848,4,0) -> 0-1 years | W73: =IF(F73="US", "Onshore",IF(F73="India","Offshore", "Nearshore")) -> Offshore | X73: Consulting | Y73: Technology | Z73: Analyst | AA73: =[1]Resourcing!QD77 -> 43.130833 | AB73: =IFERROR(VLOOKUP(O73,$B$187:$S$848,6,FALSE()),"combination not found") -> 48 | BY73: 0 | BZ73: 0 | CA73: 0 | CB73: 0 | CC73: 0 | CD73: 0 | CE73: 0 | CF73: 0 | CG73: 0 | CH73: 0 | CI73: 0 | CJ73: 0 | CK73: 0 | CL73: 0 | CM73: 0 | CN73: 0 | CO73: 0 | CP73: 0 | CQ73: 0 | CR73: 0 | CS73: 0 | CT73: 0 | CU73: 0 | CV73: 0 | CW73: 0 | CX73: 0 | CY73: 0 | CZ73: 0 | DA73: 0 | DB73: 45 | DC73: 45 | DD73: 45 | DE73: 45 | DF73: 45 | DG73: 45 | DH73: 45 | DI73: 45 | DJ73: 45 | DK73: 45 | DL73: 45 | DM73: 45 | DN73: 45 | DO73: 45 | DP73: 45 | DQ73: 45 | DT73: 45 | DU73: 45 | DV73: 45 | DW73: 45 | DX73: 45 | DY73: 45 | DZ73: 45 | EA73: 45 | EB73: 45 | EC73: 45 | ED73: 45 | EE73: 45 | FQ73: =SUMIF($AC$11:$FP$11,FQ$12,$AC73:$FP73) -> #VALUE! | FR73: =SUMIF($AC$11:$FP$11,FR$12,$AC73:$FP73) -> #VALUE! | FS73: =SUMIF($AC$11:$FP$11,FS$12,$AC73:$FP73) -> #VALUE! | FT73: =SUMIF($AC$11:$FP$11,FT$12,$AC73:$FP73) -> #VALUE! | FU73: =SUMIF($AC$11:$FP$11,FU$12,$AC73:$FP73) -> #VALUE! | FV73: =SUMIF($AC$11:$FP$11,FV$12,$AC73:$FP73) -> #VALUE! | FW73: =SUMIF($AC$11:$FP$11,FW$12,$AC73:$FP73) -> #VALUE! | FX73: =SUMIF($AC$11:$FP$11,FX$12,$AC73:$FP73) -> #VALUE! | ... GO73: =SUMIF($AC$11:$FP$11,GO$12,$AC73:$FP73) -> #VALUE! | GP73: =SUMIF($AB$8:$FO$8,GP$9,$AB73:$FO73) -> 90 | GQ73: =SUMIF($AB$8:$FO$8,GQ$9,$AB73:$FO73) -> 180 | GR73: =SUMIF($AB$8:$FO$8,GR$9,$AB73:$FO73) -> 180 | GS73: =SUMIF($AB$8:$FO$8,GS$9,$AB73:$FO73) -> 180 | GT73: =SUMIF($AB$8:$FO$8,GT$9,$AB73:$FO73) -> 0 | GU73: =SUMIF($AB$8:$FO$8,GU$9,$AB73:$FO73) -> 0 | GV73: =SUMIF($AB$8:$FO$8,GV$9,$AB73:$FO73) -> 0 | GW73: =SUMIF($AB$8:$FO$8,GW$9,$AB73:$FO73) -> 0 | ... HE73: =SUMIF($AB$8:$FO$8,HE$9,$AB73:$FO73) -> 0
